Workbook

Sheet SOFP  10.18
A1: Magic Arun Hydropower Private Limitd
A2: Statement of Financial Position
A3: As at 18 Magh 2082
E4: Restated
C5: As at | D5: As at | E5: As at
B6: Notes | C6: 18 Magh 2082 | D6: 32 Ashadh 2082 | E6: 1 Shrawan 2081
A7: ASSETS
A8: Non-Current Assets
A9: Property, Plant and Equipment | B9: 3.1 | C9: ='3.1 10.18'!I44 -> 473888.75 | D9: ='3.1 10.18'!I42 -> 604474 | E9: 0 | G9: =+D9+D11 -> 604474 | H9: =+C9+C11 -> 473888.75
A10: Project in Progress (WIP) | B10: 3.1 | C10: ='3.1 10.18'!C70 -> 15814476 | D10: ='3.1 10.18'!F70 -> 12985641 | E10: ='3.1 10.18'!G50 -> 12985641
A11: Intangible Assets | B11: 3.2 | C11: ='[5]3.2'!E43 -> 0 | D11: ='[5]3.2'!E41 -> 0 | E11: ='[5]3.2'!E39 -> 0 | G11: 821236.13 | H11: =+'SOI 10.18'!C17 -> 130585.25
A12: Investments | B12: 3.3 | C12: ='[5]3.3'!C34 -> 0 | D12: ='[5]3.3'!D34 -> 0 | E12: ='[5]3.3'!E34 -> 0 | G12: =+G9-G11 -> -216762.13 | H12: =SUM(H9:H11) -> 604474
A13: Other Receivables | B13: 3.4 | C13: 0 | D13: 0 | E13: 0 | H13: 2699634.6 | I13: =+H12-H13 -> -2095160.6
A14: Total Non-Current Assets | C14: =SUM(C9:C13) -> 16288365 | D14: =SUM(D9:D13) -> 13590115 | E14: =SUM(E9:E13) -> 12985641
A15: Current Assets
A16: Investments | B16: 3.3 | C16: ='[5]3.3'!C35 -> 0 | D16: ='[5]3.3'!D35 -> 0 | E16: ='[5]3.3'!E35 -> 0
A17: Account receivables | B17: 3.4 | C17: ='3.4 to 3.6 ao 10.18'!C32 -> 21010112 | D17: ='3.4 to 3.6 ao 10.18'!D32 -> 15311962 | E17: ='3.4 to 3.6 ao 10.18'!E32 -> 21788699 | G17: AS per Tally
A18: Inventories | B18: 3.5 | D18: =+'3.4 to 3.6 ao 10.18'!D47 -> 0 | E18: =+'3.4 to 3.6 ao 10.18'!E47 -> 0 | G18: 10922985
A19: Cash and cash equivalents | B19: 3.6 | C19: ='3.4 to 3.6 ao 10.18'!C58 -> 12637.35 | D19: ='3.4 to 3.6 ao 10.18'!D58 -> 891197 | E19: ='3.4 to 3.6 ao 10.18'!E58 -> 67329
A20: Other current assets | B20: 3.7 | C20: =+'3.4 to 3.6 ao 10.18'!C68 -> 0 | D20: =+'3.4 to 3.6 ao 10.18'!D68 -> 0 | E20: =+'3.4 to 3.6 ao 10.18'!E68 -> 0
A21: Total Current Assets | C21: =SUM(C16:C20) -> 21022749 | D21: =SUM(D16:D20) -> 16203159 | E21: =SUM(E16:E20) -> 21856028
A22: Total Assets | C22: =C21+C14 -> 37311114 | D22: =D21+D14 -> 29793274 | E22: =E21+E14 -> 34841669
A23: EQUITY AND LIABILITIES
A24: Equity
A25: Share Capital | B25: 3.8 | C25: ='3.7 to 3.8 10.18'!D31 -> 10290000 | D25: ='3.7 to 3.8 10.18'!E31 -> 12600000 | E25: 0 | G25: 6175421.8 | H25: =+G25+D27 -> 5801845.8
A26: Calls in Advance | C26: ='3.7 to 3.8 10.18'!D38 -> 22500000 | D26: 0 | E26: ='3.7 to 3.8 10.18'!E38 -> 0
A27: Retained Earnings | B27: 3.9 | C27: ='3.7 to 3.8 10.18'!D47 -> -538061.25 | D27: ='3.7 to 3.8 10.18'!E47 -> -373576 | E27: ='3.7 to 3.8 10.18'!E45 -> -196480 | G27: -6165121.9 | H27: =+G27-D27 -> -5791545.9
A28: Total Equity | C28: =SUM(C25:C27) -> 32251939 | D28: =SUM(D25:D27) -> 12226424 | E28: =SUM(E25:E27) -> -196480 | H28: 79025.12
A29: Liabilities
A30: Non-Current Liabilities
A31: Loans and Borrowings | B31: 3.10 | C31: ='3.9 to 3.11 AO 10.18'!D25 -> 3870000 | D31: ='3.9 to 3.11 AO 10.18'!E25 -> 17165000 | E31: ='3.9 to 3.11 AO 10.18'!F25 -> 20756010
A32: Provision for Employee Benefits | C32: ='3.9 to 3.11 AO 10.18'!D36 -> 0 | D32: ='3.9 to 3.11 AO 10.18'!E36 -> 0 | E32: ='3.9 to 3.11 AO 10.18'!F36 -> 0
A33: Provisions | D33: 0 | E33: 0
A34: Total Non-Current Liabilities | C34: =SUM(C31:C33) -> 3870000 | D34: =SUM(D31:D33) -> 17165000 | E34: =SUM(E31:E33) -> 20756010
A35: Current Liabilities
A36: Loans and Borrowings | B36: 3.10 | C36: ='3.9 to 3.11 AO 10.18'!D26 -> 0 | D36: ='3.9 to 3.11 AO 10.18'!E26 -> 0 | E36: ='3.9 to 3.11 AO 10.18'!F26 -> 0
A37: Trade and other payables | B37: 3.11 | C37: ='3.9 to 3.11 AO 10.18'!D49+'3.9 to 3.11 AO 10.18'!D61 -> 1189175 | D37: ='3.9 to 3.11 AO 10.18'!E49 -> 401850 | E37: ='3.9 to 3.11 AO 10.18'!F49 -> 28498
A38: Income Tax Liability | C38: ='3.9 to 3.11 AO 10.18'!D69 -> 0 | D38: ='3.9 to 3.11 AO 10.18'!E69 -> 0 | E38: ='3.9 to 3.11 AO 10.18'!F69 -> 0
A39: Provision for Employee Benefits | C39: 0 | D39: 0 | E39: 0
A40: Provisions | C40: 0 | D40: 0 | E40: 0
A41: Total Current Liabilities | C41: =SUM(C36:C40) -> 1189175 | D41: =SUM(D36:D40) -> 401850 | E41: =SUM(E36:E40) -> 28498
A42: Total Liabilities | C42: =C34+C41 -> 5059175 | D42: =D34+D41 -> 17566850 | E42: =E34+E41 -> 20784508
A43: Total Equity and Liabilities | C43: =C42+C28 -> 37311114 | D43: =D42+D28 -> 29793274 | E43: =E42+E28 -> 20588028
C49: =C22-C43 -> 0 | D49: =D22-D43 -> 0.15 | E49: =E22-E43 -> 14253641

Sheet SOI 10.18
A1: ='SOFP 10.18'!A1 -> Magic Arun Hydropower Private Limitd
A3: Statement of Income
A4: For the Year Ended 18 Magh 2082
D5: Figures in NPR
D6: Restated
A7: Particulars | B7: Notes | C7: Upto 18 Magh 2082 | D7: FY 2081-82
A8: Revenue from Operations | B8: 3.12 | C8: ='3.12 to 3.18 ao 10.18'!D12 -> 0 | D8: ='3.12 to 3.18 ao 10.18'!E12 -> 0 | G8: =C8-D8 -> 0 | H8: =G8/D8 -> #DIV/0!
A9: Interest Income | C9: 0 | D9: 0
A10: Other Income | B10: 3.13 | C10: ='3.12 to 3.18 ao 10.18'!D21 -> 0 | D10: ='3.12 to 3.18 ao 10.18'!E21 -> 0
A11: Total Income | C11: =SUM(C8:C10) -> 0 | D11: =SUM(D8:D10) -> 0
A12: Material Consumed Expenses | B12: 3.14 | C12: ='3.12 to 3.18 ao 10.18'!D30 -> 0 | D12: ='3.12 to 3.18 ao 10.18'!E30 -> 0 | E12: =(C12+C13)/C8 -> #DIV/0! | F12: =(D12+D13)/D8 -> #DIV/0! | G12: =C12-D12 -> 0 | H12: =G12/D12 -> #DIV/0!
A13: Direct Expenses | B13: 3.15 | C13: =+'3.12 to 3.18 ao 10.18'!D38 -> 0 | D13: =+'3.12 to 3.18 ao 10.18'!E38 -> 0 | G13: =C13-D13 -> 0 | H13: =G13/D13 -> #DIV/0!
A14: Employee Benefit Expenses | B14: 3.16 | C14: =+'3.12 to 3.18 ao 10.18'!D50 -> 0 | D14: =+'3.12 to 3.18 ao 10.18'!E50 -> 0 | G14: =C14-D14 -> 0 | H14: =G14/D14 -> #DIV/0!
A15: Administrative and Other Expenses | B15: 3.17 | C15: ='3.12 to 3.18 ao 10.18'!D81 -> 33900 | D15: ='3.12 to 3.18 ao 10.18'!E81 -> 29382 | G15: =C15-D15 -> 4518 | H15: =G15/D15 -> 0.15376761
A16: Interest Expenses | B16: 3.18 | C16: ='3.12 to 3.18 ao 10.18'!D86 -> 0 | D16: ='3.12 to 3.18 ao 10.18'!E86 -> 0 | G16: =C16-D16 -> 0 | H16: =G16/D16 -> #DIV/0!
A17: Depreciation and Amortization Expenses | B17: 3.1 & 3.2 | C17: =+'3.1 10.18'!I30+'[5]3.2'!E32 -> 130585.25 | D17: =+'3.1 10.18'!I28+'[5]3.2'!E30 -> 147714 | E17: 187078.71 | F17: =+D17-E17 -> -39364.71 | G17: =C17-D17 -> -17128.75 | H17: =G17/D17 -> -0.11595888
A18: Total Expenses | C18: =SUM(C12:C17) -> 164485.25 | D18: =SUM(D12:D17) -> 177096
A19: Profit Before Tax | C19: =C11-C18 -> -164485.25 | D19: =D11-D18 -> -177096 | E19: -2368782.9 | F19: =+D19-E19 -> 2191686.9
A20: Income Tax Expense | C20: =SUM(C21:C22) -> 0 | D20: =SUM(D21:D22) -> 0
A21: Current year | C21: 0 | D21: 0
A22: Previous years | C22: 0 | D22: 0
A23: Net Profit for the year | C23: =C19-C20 -> -164485.25 | D23: =D19-D20 -> -177096

Sheet SOCE 10.18
A1: ='SOI 10.18'!A1 -> Magic Arun Hydropower Private Limitd
A3: Statement of Changes in Equity
A4: ='SOI 10.18'!A4 -> For the Year Ended 18 Magh 2082
G6: Figures in NPR
A7: Particulars | C7: Share Capital | D7: Calls in Advance | E7: Retained Earnings | F7: Other Reserves | G7: Total
A8: Balance at 1 Shrawan 2081 | C8: =+'SOFP 10.18'!E25 -> 0 | D8: 7600000 | E8: =+'3.7 to 3.8 10.18'!E45 -> -196480 | F8: 0 | G8: =SUM(C8:F8) -> 7403520
A9: Restatements on transition to NAS for MEs | C9: 0 | D9: 0 | E9: =SUM([5]Reco!F5:F8) -> 0 | F9: 0 | G9: =SUM(C9:F9) -> 0
A10: Balance at 1 Shrawan 2081 (restated) | C10: =SUM(C8:C9) -> 0 | D10: =SUM(D8:D9) -> 7600000 | E10: =SUM(E8:E9) -> -196480 | F10: =SUM(F8:F9) -> 0 | G10: =SUM(G8:G9) -> 7403520 | H10: ='SOFP 10.18'!E28 -> -196480 | I10: =G10-H10 -> 7600000
A11: Profit for the year | C11: 0 | D11: 0 | E11: ='SOI 10.18'!D23 -> -177096 | F11: 0 | G11: =+SUM(C11:F11) -> -177096
A12: Issue of Shares | C12: 12600000 | D12: -7600000 | E12: 0 | F12: 0 | G12: =+SUM(C12:F12) -> 5000000
A13: Dividends to Shareholders | C13: 0 | D13: 0 | E13: 0 | F13: 0 | G13: =+SUM(C13:F13) -> 0
A14: Other Changes | C14: 0 | D14: 0 | E14: 0 | F14: 0 | G14: =+SUM(C14:F14) -> 0
A15: Balance at 32 Ashad 2082 | C15: =SUM(C10:C14) -> 12600000 | D15: =SUM(D10:D14) -> 0 | E15: =SUM(E10:E14) -> -373576 | F15: =SUM(F10:F14) -> 0 | G15: =SUM(G10:G14) -> 12226424 | H15: ='SOFP 10.18'!D28 -> 12226424 | I15: =G15-H15 -> 0
A16: Profit for the year | C16: 0 | D16: 0 | E16: =+'SOI 10.18'!C23 -> -164485.25 | F16: 0 | G16: =+SUM(C16:F16) -> -164485.25
A17: Issue of Shares | C17: 0 | D17: 0 | E17: 0 | F17: 0 | G17: =+SUM(C17:F17) -> 0
A18: Dividends to Shareholders | C18: 0 | D18: 0 | E18: 0 | F18: 0 | G18: =+SUM(C18:F18) -> 0
A19: Other Changes | C19: 0 | D19: 0 | E19: 0 | F19: 0 | G19: =+SUM(C19:F19) -> 0
A20: Balance at 32 Ashad 2083 | C20: =SUM(C15:C19) -> 12600000 | D20: =SUM(D15:D19) -> 0 | E20: =SUM(E15:E19) -> -538061.25 | F20: =SUM(F15:F19) -> 0 | G20: =SUM(G15:G19) -> 12061939 | H20: ='SOFP 10.18'!C28 -> 32251939 | I20: =G20-H20 -> -20190000

Sheet SCF 10.18
A1: ='SOCE 10.18'!A1 -> Magic Arun Hydropower Private Limitd
A3: Statement of Cash Flows
A4: ='SOCE 10.18'!A4 -> For the Year Ended 18 Magh 2082
C5: Figures in NPR
A6: Particulars | B6: ='SOI 10.18'!C7 -> Upto 18 Magh 2082 | C6: ='SOI 10.18'!D7 -> FY 2081-82
A7: CASH FLOWS FROM OPERATING ACTIVITIES
A8: Profit for the year | B8: ='SOI 10.18'!C19 -> -164485.25 | C8: ='SOI 10.18'!D19 -> -177096 | D8: =B8-'SOFP 10.18'!J27 -> -164485.25
A9: Adjustment for:
A10: Depreciation/Impairment on Property, Plant and Equipment | B10: ='SOI 10.18'!C17 -> 130585.25 | C10: ='SOI 10.18'!D17 -> 147714
A11: Interest Income
A12: Interest Expense | B12: ='SOI 10.18'!C16 -> 0 | C12: ='SOI 10.18'!D16 -> 0
A13: Loss/(gain) on sale of Property, Plant and Equipment
A14: Income Tax expense charged to statement of income
A15: Working Capital Adjustments
A16: Decrease/(Increase) in trade and other receivables | B16: ='SOFP 10.18'!J17+'SOFP 10.18'!J20 -> 0 | C16: ='SOFP 10.18'!E17-'SOFP 10.18'!D17 -> 6476737
A17: Decrease/(Increase) in Inventories | B17: ='SOFP 10.18'!J18 -> 0 | C17: ='SOFP 10.18'!K18 -> 0
A18: Increase/(Decrease) in trade and other payables | B18: ='SOFP 10.18'!J37 -> 0 | C18: ='SOFP 10.18'!K37 -> 0
A19: Increase/(Decrease) Loan and Borrowings | C19: ='SOFP 10.18'!D31-'SOFP 10.18'!E31 -> -3591010
A20: Increase/(Decrease) in other liabilities | C20: 0
A21: Cash Generated from Operations | B21: =SUM(B8:B20) -> -33900 | C21: =SUM(C8:C20) -> 2856345
A22: Interest paid | C22: 0
A23: Income tax paid | C23: 0
A24: NET CASH FLOWS FROM OPERATING ACTIVITIES (A) | B24: =SUM(B21:B23) -> -33900 | C24: =SUM(C21:C23) -> 2856345
A25: CASH FLOW FROM INVESTING ACTIVITIES
A26: Proceeds from sale of PPE, Investments/Financial Assets | C26: =-'3.1 10.18'!I8 -> 0
A27: Increase in project WIP | B27: ='SOFP 10.18'!J12 -> 0 | C27: =-'SOFP 10.18'!D10+'SOFP 10.18'!E10 -> 0
A28: Acquisition of Property, Plant and Equipment | B28: =-'3.1 10.18'!I15-'[5]3.2'!E17 -> 0 | C28: =-'3.1 10.18'!I10-'[5]3.2'!E12 -> -752188
A29: NET CASH FLOWS FROM INVESTING ACTIVITIES (B) | B29: =SUM(B25:B28) -> 0 | C29: =SUM(C25:C28) -> -752188
A30: CASH FLOW FROM FINANCING ACTIVITIES
A31: Proceeds from the issue of Equity and Preference Share | C31: ='SOFP 10.18'!D25-'SOFP 10.18'!E26 -> 12600000
A32: Proceeds from loans and borrowings borrowings | B32: ='SOFP 10.18'!J36 -> 0 | C32: ='SOFP 10.18'!K36 -> 0
A33: Interest Expenses | B33: =-B12 -> 0 | C33: =-C12 -> 0
A34: Dividend Paid
A35: NET CASH FLOW FROM FINANCING ACTIVITIES (C) | B35: =SUM(B31:B34) -> 0 | C35: =SUM(C31:C34) -> 12600000
A36: Net Increase in Cash and Cash Equivalents | B36: =B24+B29+B35 -> -33900 | C36: =C24+C29+C35 -> 14704157
A37: Cash and Cash Equivalents at the beginning | B37: ='SOFP 10.18'!D19 -> 891197 | C37: ='SOFP 10.18'!E19 -> 67329
A38: Exchange gains/(losses) in cash and cash equivalents
A39: Cash and Cash Equivalents at the end | B39: =B36+B37 -> 857297 | C39: =C36+C37 -> 14771486
B40: ='3.4 to 3.6 ao 10.18'!C58 -> 12637.35 | C40: ='3.4 to 3.6 ao 10.18'!D58 -> 891197
B41: =B39-B40 -> 844659.65 | C41: =C39-C40 -> 13880289

Sheet 3.1 10.18
A1: ='SOFP 10.18'!A1 -> Magic Arun Hydropower Private Limitd
A2: Notes to Financial Statements
I3: Figures in NPR
A4: 3.1 | B4: Property, Plant and Equipment
C5: Furniture & Fixtures | D5: Computer | E5: Office Equipments | F5: Vehicles | G5: Plant and Machinery | H5: Office Furnishing | I5: Total
B6: Cost
B8: Balance at 1 Shrawan 2081 | C8: 0 | D8: 0 | E8: 0 | F8: 0 | G8: 0 | I8: =SUM(C8:G8) -> 0
I9: =SUM(C9:G9) -> 0
B10: Additions | C10: 532188 | D10: 0 | E10: 0 | F10: 220000 | G10: 0 | I10: =SUM(C10:G10) -> 752188
B11: Disposals | C11: 0 | D11: 0 | E11: 0 | F11: 0 | G11: 0 | I11: =SUM(C11:G11) -> 0
B13: Balance at 32 Ashadh 2082 | C13: =SUM(C8:C11) -> 532188 | D13: =SUM(D8:D11) -> 0 | E13: =SUM(E8:E11) -> 0 | F13: =SUM(F8:F11) -> 220000 | G13: =SUM(G8:G11) -> 0 | I13: =SUM(I8:I11) -> 752188
B15: Additions | C15: 0 | E15: 0 | G15: 0 | I15: =SUM(C15:G15) -> 0
B16: Disposals | C16: 0 | D16: 0 | E16: 0 | F16: 0 | G16: 0 | I16: =SUM(C16:G16) -> 0
B18: Balance at 18 Magh 2082 | C18: =SUM(C13:C16) -> 532188 | D18: =SUM(D13:D16) -> 0 | E18: =SUM(E13:E16) -> 0 | F18: =SUM(F13:F16) -> 220000 | G18: =SUM(G13:G16) -> 0 | H18: =SUM(H13:H16) -> 0 | I18: =SUM(C18:G18) -> 752188
B21: Accumulated depreciation
B23: =B8 -> Balance at 1 Shrawan 2081 | C23: 0 | D23: 0 | E23: 0 | F23: 0 | G23: 0 | I23: =SUM(C23:G23) -> 0
B25: Charge for the year | C25: 133047 | D25: 0 | E25: 0 | F25: 14667 | G25: 0 | H25: 0 | I25: =SUM(C25:H25) -> 147714
B26: Disposals
B28: =B13 -> Balance at 32 Ashadh 2082 | C28: =SUM(C23:C26) -> 133047 | D28: =SUM(D23:D26) -> 0 | E28: =SUM(E23:E26) -> 0 | F28: =SUM(F23:F26) -> 14667 | G28: =SUM(G23:G26) -> 0 | H28: =SUM(H23:H26) -> 0 | I28: =SUM(I23:I26) -> 147714
B30: Charge for the year | C30: =(C13-C25)*25% -> 99785.25 | E30: 0 | F30: 30800 | G30: 0 | H30: =(H18-H28)*15% -> 0 | I30: =SUM(C30:G30) -> 130585.25
B31: Disposals
B33: =B18 -> Balance at 18 Magh 2082 | C33: =C30+C28 -> 232832.25 | D33: =SUM(D28:D31) -> 0 | E33: =SUM(E28:E31) -> 0 | F33: =F30+F28 -> 45467 | G33: =SUM(G28:G31) -> 0 | H33: =SUM(H28:H31) -> 0 | I33: =SUM(C33:G33) -> 278299.25
B38: Net Book Value
B40: As at 1st Shrawan 2081 | C40: =C8-C23 -> 0 | D40: =D8-D23 -> 0 | E40: =E8-E23 -> 0 | F40: =F8-F23 -> 0 | G40: =G8-G23 -> 0 | H40: =H8-H23 -> 0 | I40: =I8-I23 -> 0
B42: As at 32nd Ashad 2082 | C42: =C13-C28 -> 399141 | D42: =D13-D28 -> 0 | E42: =E13-E28 -> 0 | F42: =F13-F28 -> 205333 | G42: =G13-G28 -> 0 | H42: =H13-H28 -> 0 | I42: =SUM(C42:G42) -> 604474
B44: As at 10 Magh 2082 | C44: =C18-C33 -> 299355.75 | D44: =D18-D33 -> 0 | E44: =E18-E33 -> 0 | F44: =F18-F33 -> 174533 | G44: =G18-G33 -> 0 | H44: =H18-H33 -> 0 | I44: =SUM(C44:G44) -> 473888.75
B48: 3.1.2 Project in Progress (WIP)
B49: Particulars | C49: As on 10 Magh 2082 | E49: During the period | G49: 2080.081
B50: Project Initial Expenses | C50: =C70 -> 15814476 | E50: =D70 -> 2828835 | G50: =F70 -> 12985641
C52: As on 10 Magh 2082 | D52: During the period | F52: 2081-82
B53: Survey License Fee | C53: =F53+D53 -> 8000000 | D53: ='TB update upto 10.18'!E59 -> 0 | F53: ='TB update upto 10.18'!C59 -> 8000000
B54: License Renewal Fee | C54: =F54+D54 -> 2000000 | D54: ='TB update upto 10.18'!E60 -> 2000000 | F54: ='TB update upto 10.18'!C60 -> 0
B55: PPA Fee | C55: =F55+D55 -> 300000 | D55: ='TB update upto 10.18'!E61 -> 0 | F55: ='TB update upto 10.18'!C61 -> 300000
B56: Grid Impat Study Expenses (NEA) | C56: =F56+D56 -> 102000 | D56: ='TB update upto 10.18'!E62 -> 0 | F56: ='TB update upto 10.18'!C62 -> 102000
B57: Bank Charges | C57: =F57+D57 -> 274657.15 | D57: ='TB update upto 10.18'!E63 -> 0 | F57: ='TB update upto 10.18'!C63 -> 274657.15
B58: ERC Approval | C58: =F58+D58 -> 197000 | D58: ='TB update upto 10.18'!E64 -> 0 | F58: ='TB update upto 10.18'!C64 -> 197000
B59: Salary Expenses | C59: =F59+D59 -> 2990000 | D59: ='TB update upto 10.18'!E65 -> 415000 | F59: ='TB update upto 10.18'!C65 -> 2575000
B60: Travelling & Site Visit Expenses | C60: =F60+D60 -> 808129 | D60: ='TB update upto 10.18'!E66 -> 343785 | F60: ='TB update upto 10.18'!C66 -> 464344
B61: Labour Wages | C61: =F61+D61 -> 660000 | D61: ='TB update upto 10.18'!E67 -> 0 | F61: ='TB update upto 10.18'!C67 -> 660000
B62: Office Rent | C62: =F62+D62 -> 240000 | D62: ='TB update upto 10.18'!E68 -> 0 | F62: ='TB update upto 10.18'!C68 -> 240000
B63: Repair & Maintenance Expenses | C63: =F63+D63 -> 37700 | D63: ='TB update upto 10.18'!E69 -> 0 | F63: ='TB update upto 10.18'!C69 -> 37700
B64: Printing & Stationary Expenses | C64: =F64+D64 -> 49315 | D64: ='TB update upto 10.18'!E70 -> 6965 | F64: ='TB update upto 10.18'!C70 -> 42350
... B69: TADA | C69: =F69+D69 -> 0 | D69: ='TB update upto 10.18'!E75 -> 0 | F69: ='TB update upto 10.18'!C75 -> 0
C70: =SUM(C53:C69) -> 15814476 | D70: =SUM(D53:D69) -> 2828835 | F70: =SUM(F53:F69) -> 12985641

Sheet 3.4 to 3.6 ao 10.18
A1: ='SOFP 10.18'!A1 -> Magic Arun Hydropower Private Limitd
A2: Notes to Financial Statements
D4: Figures in NPR
A6: 3.4 | B6: Account Receivables | C6: ='[5]3.3'!C29 -> As at | D6: ='[5]3.3'!D29 -> As at | E6: ='[5]3.3'!E29 -> As at
C7: 18 Magh 2082 | D7: ='[5]3.3'!D30 -> 32 Ashadh 2082 | E7: ='[5]3.3'!E30 -> 1 Shrawan 2081
B9: Account Receivables
B10: Advance for Road Construction | C10: 0 | D10: 0 | E10: 1000000
B11: Advance for Land Purchase | C11: 0 | D11: 0 | E11: 20300000
B12: Site Advance | C12: 0 | D12: 0 | E12: 488699
B13: Other Receivables
B14: Bijaya Bista | C14: ='TB update upto 10.18'!G78 -> 5000000 | D14: 4000000
B15: Ellite Powers Pvt.Ltd | C15: 0 | D15: 3000000
B16: Environment Partners Pvt.Ltd | C16: ='TB update upto 10.18'!G94 -> 250000 | D16: 250000
B17: Rajendra Karki- Advance | C17: ='TB update upto 10.18'!G80 -> 5563462 | D17: 5563462
B18: Slesha Engineering Consultancy Pvt.Ltd | C18: ='TB update upto 10.18'!G93 -> 2900000 | D18: 2200000 | E18: 0
B19: Ellite Steel Pvt.ltd | C19: ='TB update upto 10.18'!G84 -> 260000
B20: Buddha Law Associates | C20: ='TB update upto 10.18'!G96 -> 75000
B21: Other Receivables | C21: ='TB update upto 10.18'!G95+'TB update upto 10.18'!G45 -> 133525
B22: Samyak Consulting Pvt. Ltd. | C22: ='TB update upto 10.18'!G92 -> 529624.5
B23: Bahadur Ventures Pvt. Ltd. | C23: ='TB update upto 10.18'!G50 -> 5000000
B24: Pramod Neupane | C24: ='TB update upto 10.18'!G79 -> 500000
B25: kanchan Sherpa | C25: ='TB update upto 10.18'!G90 -> 500000
B27: Deposit
B28: Cash Margin-PB-NEA | C28: ='TB update upto 10.18'!G100 -> 298500 | D28: 298500 | E28: 0
C29: =+C12+SUM(C14:C28) -> 21010112 | D29: =SUM(D10:D28) -> 15311962 | E29: =SUM(E10:E18) -> 21788699
B31: Non-current portion | C31: 0 | D31: 0 | E31: 0
B32: Current portion | C32: =C29 -> 21010112 | D32: =D29 -> 15311962 | E32: =E29 -> 21788699
B34: Provision for impairment of trade receivables: | D34: FY | E34: FY
D35: 2081-82 | E35: 2080-81
B36: Balance at the beginning of the year | D36: 0 | E36: 0
B37: Provided during the year | D37: 0 | E37: 0
B38: Written off during the year | D38: 0 | E38: 0
B39: Unused provisions reversed | D39: 0 | E39: 0
B41: Balance at the end of the year | D41: =SUM(D36:D39) -> 0 | E41: =SUM(E36:E39) -> 0
A43: 3.5 | B43: Inventories
C44: =C6 -> As at | D44: =D6 -> As at | E44: =E6 -> As at
C45: =C7 -> 18 Magh 2082 | D45: =D7 -> 32 Ashadh 2082 | E45: =E7 -> 1 Shrawan 2081
B47: Inventories of goods held for resale | C47: ='3.12 to 3.18 ao 10.18'!D28 -> 0 | D47: 0 | E47: 0
C49: =C47 -> 0 | D49: =D47 -> 0 | E49: =E47 -> 0
A50: 3.6 | B50: Cash and Cash Equivalents
C51: =C44 -> As at | D51: =D44 -> As at | E51: =E44 -> As at
C52: =C45 -> 18 Magh 2082 | D52: =D45 -> 32 Ashadh 2082 | E52: =E45 -> 1 Shrawan 2081
B54: Cash in hand | C54: 0 | D54: 0 | E54: 0
B55: Siddhartha Bank, Ltd | C55: ='TB update upto 10.18'!G103 -> 804 | D55: 40804 | E55: 67329
B56: Laxmi Sunrise Bank, Ltd | C56: ='TB update upto 10.18'!G102 -> 11833.35 | D56: 850393 | E56: 0
C58: =SUM(C54:C56) -> 12637.35 | D58: =SUM(D54:D56) -> 891197 | E58: =SUM(E54:E56) -> 67329
A60: 3.7 | B60: Other current assets
C61: =C51 -> As at | D61: =D51 -> As at | E61: =E51 -> As at
C62: =C52 -> 18 Magh 2082 | D62: =D52 -> 32 Ashadh 2082 | E62: =E52 -> 1 Shrawan 2081
B64: TDS Receivable | D64: 0
B65: VAT Receivable | D65: 0
B66: Prepayments | C66: 0 | D66: 0 | E66: 0
C68: =+SUM(C64:C67) -> 0 | D68: =+SUM(D64:D67) -> 0 | E68: =+SUM(E64:E67) -> 0

Sheet 3.7 to 3.8 10.18
A1: ='[5]3.3'!A1:E1 -> CELER MART PVT. LTD.
B3: Notes to Financial Statements
E5: Figures in NPR
A7: 3.7 | B7: Share Capital
D8: ='3.4 to 3.6 ao 10.18'!D6 -> As at | E8: ='3.4 to 3.6 ao 10.18'!E6 -> As at
D9: ='3.4 to 3.6 ao 10.18'!C7 -> 18 Magh 2082 | E9: ='3.4 to 3.6 ao 10.18'!D7 -> 32 Ashadh 2082
B11: Authorized
B12: 260,000 ordinary shares of NPR 100 each | D12: 26000000 | E12: =D12 -> 26000000
B14: Ordinary Shares Issued and Fully Paid
B15: Ordinary shares of Rs. 100 each
D16: Ordinary | E16: Ordinary
D17: share | E17: share capital
D18: As at | E18: As at
D19: 18 Magh 2082 | E19: 32 Ashadh 2082
B20: Paid up Share capital
B21: Bijay Bista | E21: 3200000
B22: Rajendra Karki | D22: ='TB update upto 10.18'!H10 -> 890000 | E22: 3200000
B23: Kanchan Sherpa | E23: 200000
B24: Lilamani Pathak | E24: 1000000
B25: Bhadra Ventures Pvt.LTD | E25: 5000000
B26: Shivaram Bhandari | D26: ='TB update upto 10.18'!H15 -> 5000000
B27: Indu Bhandari Basnet | D27: ='TB update upto 10.18'!H16 -> 2510000
B28: Nabaraj Tiwari | D28: ='TB update upto 10.18'!H17 -> 1260000
B29: Murali Adhikari | D29: ='TB update upto 10.18'!H18 -> 630000
B31: Total | D31: =SUM(D21:D30) -> 10290000 | E31: =SUM(E21:E30) -> 12600000
D32: As at | E32: As at
B33: Share Advance | D33: 10 Magh 2082 | E33: 32 Ashadh 2082
B34: Shiv Ram Bhandari | D34: ='TB update upto 10.18'!H20 -> 20000000
B35: Bond Construction | D35: ='TB update upto 10.18'!H21 -> 2000000
B36: Uttam Kumar | D36: ='TB update upto 10.18'!H22 -> 500000
B37: Lilamani Pathak
B38: Total | D38: =SUM(D34:D37) -> 22500000 | E38: =SUM(E34:E37) -> 0
A40: 3.8 | B40: Retained Earnings
D42: =D8 -> As at | E42: =E8 -> As at
D43: ='SOFP 10.18'!C6 -> 18 Magh 2082 | E43: ='SOFP 10.18'!D6 -> 32 Ashadh 2082 | G43: New | J43: Old
B45: Opening balance | D45: =+E47 -> -373576 | E45: -196480 | G45: =+E45 -> -196480 | J45: =+E45 -> -196480
B46: Net profit for the year | D46: ='SOI 10.18'!C23 -> -164485.25 | E46: ='SOI 10.18'!D23 -> -177096 | G46: -2368782.9 | J46: =+'SOI 10.18'!E19 -> -2368782.9
B47: Closing balance | D47: =SUM(D45:D46) -> -538061.25 | E47: =SUM(E45:E46) -> -373576 | G47: =SUM(G45:G46) -> -2565262.9 | H47: As per FS | J47: =+J45+J46 -> -2565262.9
G48: =+#REF!+#REF! -> #REF! | H48: AS per Tally
E49: =+E47-G47 -> 2191686.9 | G49: =+G47+G48 -> #REF!

Sheet 3.9 to 3.11 AO 10.18
A1: ='[5]3.3'!A1:E1 -> CELER MART PVT. LTD.
A3: Notes to Financial Statements
F5: Figures in NPR
A7: 3.9 | B7: Loans and Borrowings
C8: As at | D8: ='3.7 to 3.8 10.18'!D8 -> As at | E8: ='3.7 to 3.8 10.18'!E8 -> As at | F8: =E8 -> As at
C9: 15 Asadh 2083 | D9: ='SOFP 10.18'!C6 -> 18 Magh 2082 | E9: ='SOFP 10.18'!D6 -> 32 Ashadh 2082 | F9: ='SOFP 10.18'!E6 -> 1 Shrawan 2081
B10: Total Loans and Borrowings
B11: Bank Overdraft | D11: 0 | E11: 0 | F11: 0
B12: Short Term Payable | D12: 0 | E12: 0 | F12: 20756010
B13: Basudev Dhiktta | D13: ='TB update upto 10.18'!H49 -> 2200000 | E13: 2200000
B14: Bhadra Ventures Pvt.Ltd | D14: 0 | E14: 1300000
B15: Eak Raj Khatiwada | E15: 12000000
B16: Naresh Poudel-Payable | D16: ='TB update upto 10.18'!H40 -> 390000 | E16: 365000
B17: Sandipa Thapa | D17: ='TB update upto 10.18'!H41 -> 200000 | E17: 200000
B18: Shyam Prasad Kuikel | D18: ='TB update upto 10.18'!H42 -> 500000 | E18: 500000
B19: Ellite Wire Pvt.Ltd | D19: ='TB update upto 10.18'!H47 -> 380000 | E19: 600000
B20: Ellite Powers Pvt.Ltd | D20: ='TB update upto 10.18'!H89 -> 200000 | E20: 0
D23: =SUM(D11:D20) -> 3870000 | E23: =SUM(E11:E20) -> 17165000 | F23: =SUM(F11:F19) -> 20756010
B25: Non-current loans and borrowings | D25: =D23-D26 -> 3870000 | E25: =E23-E26 -> 17165000 | F25: =F23-F26 -> 20756010
B26: Current loans and borrowings | D26: =D11 -> 0 | E26: =E11 -> 0 | F26: =F11 -> 0
A29: 3.10 | B29: Provision for Employee Benefits
C31: =C8 -> As at | D31: =D8 -> As at | E31: =E8 -> As at | F31: =F8 -> As at
C32: =C9 -> 15 Asadh 2083 | D32: =D9 -> 18 Magh 2082 | E32: =E9 -> 32 Ashadh 2082 | F32: =F9 -> 1 Shrawan 2081
B34: Provision for Gratuity | D34: 0 | E34: 0
B35: Provision for Leave benefits
D36: =SUM(D34:D35) -> 0 | E36: =SUM(E34:E35) -> 0 | F36: =SUM(F34:F35) -> 0
A38: 3.11 | B38: Trade and other payables
C39: =C31 -> As at | D39: =D31 -> As at | E39: =E31 -> As at | F39: =F31 -> As at
C40: =C32 -> 15 Asadh 2083 | D40: =D32 -> 18 Magh 2082 | E40: =E32 -> 32 Ashadh 2082 | F40: =F32 -> 1 Shrawan 2081
B41: TDS on Audit Fee | D41: ='TB update upto 10.18'!H26 -> 825 | E41: 375 | F41: 375
B42: TDS on Salary (SST) | D42: ='TB update upto 10.18'!H27 -> 29900 | E42: 25750 | F42: 248
B43: TDS on Office Rent | D43: ='TB update upto 10.18'!H30 -> 24000 | E43: 24000 | F43: 0 | G43: Net of TDS
B44: TDS on Labour Wages | D44: ='TB update upto 10.18'!H31 -> 6600 | E44: 6600 | F44: 0
B45: Audit Fee Payable | D45: ='TB update upto 10.18'!H33 -> 61325 | E45: 27875 | F45: 27875
B46: Staff Payable | D46: ='TB update upto 10.18'!H37 -> 222750 | E46: 222750 | F46: 0
B47: Office Rent Payable | D47: ='TB update upto 10.18'!H38 -> 94500 | E47: 94500 | F47: 0
B48: TDS on Meeting Fee | D48: ='TB update upto 10.18'!H28 -> 7275
D49: =SUM(D41:D48) -> 447175 | E49: =SUM(E41:E47) -> 401850 | F49: =SUM(F41:F47) -> 28498
B50: Other payable
B51: =[5]Sheet1!A8 -> Sita Karki | D51: ='TB update upto 10.18'!H44 -> 700000
B52: =[5]Sheet1!A19 -> Mamata Acharya - Payable
B53: Samyak Consulting Engineering Pvt. Ltd. | E53: 0
B54: Baba Gas | D54: ='TB update upto 10.18'!H46 -> 2000
B55: Kamal Karki - Site Visit | E55: 0
B56: Naresh Poudel - Site Visit | E56: 0
B57: Buddha Law Assocites Pvt Ltd
B58: Bhadra Venture
B59: Mohan Bista - Auditor (SST, TDS, Audit Fee)
B60: Shiva Ram Bhandari - Other Advance | D60: ='TB update upto 10.18'!H107 -> 40000
D61: =SUM(D51:D60) -> 742000
A64: 3.12 | B64: Income tax liability
C65: =C39 -> As at | D65: =D39 -> As at | E65: =E39 -> As at | F65: =F39 -> As at
C66: =C40 -> 15 Asadh 2083 | D66: =D40 -> 18 Magh 2082 | E66: =E40 -> 32 Ashadh 2082 | F66: =F40 -> 1 Shrawan 2081
B67: Provision for tax | D67: 0 | E67: 0 | F67: 0
D69: =SUM(D67:D68) -> 0 | E69: =SUM(E67:E68) -> 0 | F69: =SUM(F67:F68) -> 0

Sheet 3.12 to 3.18 ao 10.18
A1: ='[5]3.3'!A1:E1 -> CELER MART PVT. LTD.
A3: Notes to Financial Statements
E5: Figures in NPR
A7: 3.12 | B7: Revenue from Operations
D8: ='SOI 10.18'!C7 -> Upto 18 Magh 2082 | E8: ='SOI 10.18'!D7 -> FY 2081-82
B9: Sale of goods | D9: 0 | E9: 0 | G9: 79597.18 | H9: 1182752.6
B10: Rendering of services
D12: =SUM(D9:D10) -> 0 | E12: =SUM(E9:E10) -> 0
A15: 3.13 | B15: Other income
D16: =D8 -> Upto 18 Magh 2082 | E16: =E8 -> FY 2081-82
B17: Commission and incentive | D17: 0
B18: Discounts Received | D18: 0 | E18: 0
B19: Exchange gain | D19: 0
D21: =SUM(D17:D19) -> 0 | E21: =SUM(E17:E19) -> 0
A24: 3.14 | B24: Material Consumed Expenses
D25: =D8 -> Upto 18 Magh 2082 | E25: =E8 -> FY 2081-82
B26: Balance on 1 Shrawan | D26: =E28 -> 0 | E26: 0
B27: Purchase during the period | D27: 0 | E27: 0 | G27: 120571
B28: Less: Balance on 32 Ashadh | D28: 0 | E28: 0
D30: =D26+D27-D28 -> 0 | E30: =E26+E27-E28 -> 0
A32: 3.15 | B32: Direct Expenses
D33: =D66 -> Upto 18 Magh 2082 | E33: =E66 -> FY 2081-82
B34: Freight
B35: Customs Duty
B36: Other Direct Expenses
D38: =SUM(D34:D36) -> 0 | E38: =SUM(E34:E36) -> 0
A41: 3.16 | B41: Employee Benefit Expenses
D42: =D25 -> Upto 18 Magh 2082 | E42: =E25 -> FY 2081-82
B43: Salary & Allowances | D43: 0 | E43: 0
B44: Dashain Expenses
B45: Staff Welfare
B46: PF & Gratuity expense | G46: =58914+49076 -> 107990
B47: Leave Expense
D50: =SUM(D43:D48) -> 0 | E50: =SUM(E43:E47) -> 0
B52: Key management personnel compensation
B53: Key management personnel are those persons having authority and responsibility for planning, directing and controlling the activities of the entity, including the directors.
D55: =D42 -> Upto 18 Magh 2082 | E55: =E42 -> FY 2081-82
B56: Salary
B57: Other long-term benefits
B58: Total pension and other post-employment benefit costs
B59: Compensations for loss of office
B60: Share based payment expense
D62: =SUM(D60:D60) -> 0 | E62: =SUM(E60:E60) -> 0
A65: 3.17 | B65: Administrative and Other Expenses
D66: =D55 -> Upto 18 Magh 2082 | E66: =E55 -> FY 2081-82
B67: Office Administrative and Running Expenses
B68: Audit Fee | D68: ='TB update upto 10.18'!G106 -> 33900 | E68: 28250
B69: Miscellaneous Expenses | E69: 1132
B70: Electricity and water
B71: Fine & Penalty
B72: Insurance
B73: Lunch and Refreshment Expenses
B74: Telephone, Internet and Hosting Charges
B75: POS and Billing Expenses
B76: Office Expenses
B77: Printing & Stationary
B78: Rates & Taxes
B79: Rent Expenses
B80: Repair and maintenance
D81: =SUM(D68:D80) -> 33900 | E81: =SUM(E68:E80) -> 29382
A83: 3.18 | B83: Interest expenses
D84: =D33 -> Upto 18 Magh 2082 | E84: =E33 -> FY 2081-82
B85: Interest expense
D86: =SUM(D85:D85) -> 0 | E86: =SUM(E85:E85) -> 0

Sheet 3.19 to 3.20 ao.10.18
A1: ='[5]3.3'!A1:E1 -> CELER MART PVT. LTD.
C2: `
A3: Notes to Financial Statements
D5: Figures in NPR
A7: 3.19 | B7: Other Expenses
C8: ='3.12 to 3.18 ao 10.18'!D8 -> Upto 18 Magh 2082 | D8: ='3.12 to 3.18 ao 10.18'!E8 -> FY 2081-82
B9: Loss on sale of investments | D9: 0
C12: =SUM(C10:C10) -> 0 | D12: =SUM(D9:D10) -> 0
A14: 3.2 | B14: Tax Expenses
C15: =C8 -> Upto 18 Magh 2082 | D15: =D8 -> FY 2081-82
B16: Tax on profit for the year | C16: ='Tax Computation 10.18'!C16 -> 0 | D16: ='SOI 10.18'!D21 -> 0
B17: Previous year tax | C17: 0 | D17: ='SOI 10.18'!D22 -> 0
C19: =SUM(C16:C17) -> 0 | D19: =SUM(D16:D17) -> 0
B21: Reconciliation of book profits and taxable profits
C22: =C15 -> Upto 18 Magh 2082 | D22: =D15 -> FY 2081-82
B23: Profit before tax as per books | C23: ='Tax Computation 10.18'!C3 -> -164485.25 | D23: ='SOI 10.18'!D19 -> -177096
B24: Add: Depreciation as per books | C24: ='Tax Computation 10.18'!C4 -> 130585.25 | D24: ='SOI 10.18'!D17 -> 147714
B25: Less: Depreciation as per tax | C25: ='Tax Computation 10.18'!C5 -> 0 | D25: =-D24 -> -147714
B26: Add: Disallowed repairs | C26: ='Tax Computation 10.18'!C6 -> 0 | D26: =-[5]Reco!F23 -> 0
B27: Add: Gratuity expense as per books | C27: ='Tax Computation 10.18'!C7 -> 0 | D27: =-[5]Reco!F15 -> 0
B28: Less: Gratuity paid | C28: ='Tax Computation 10.18'!C8 -> 0 | D28: =-[5]Reco!F14 -> 0
B29: Add: Leave expense as per books | C29: ='Tax Computation 10.18'!C9 -> 0 | D29: =-[5]Reco!F17 -> 0
B30: Less: Leave paid | C30: ='Tax Computation 10.18'!C10 -> 0 | D30: =-[5]Reco!F16 -> 0
B31: Less: Fair value gain on investments | C31: ='Tax Computation 10.18'!C11 -> 0 | D31: =-[5]Reco!F20 -> 0
B32: Add: Exchange loss/(gain) as per books | C32: ='Tax Computation 10.18'!C12 -> 0 | D32: =-[5]Reco!F22 -> 0
B33: Add: Realized exchange gain/(loss) | C33: ='Tax Computation 10.18'!C13 -> 0 | D33: =-[5]Reco!F21 -> 0
B34: Add: Difference in profit on sale of investment | C34: 0 | D34: 270000
B35: Add: Disallowed expenses | C35: ='Tax Computation 10.18'!C14 -> 0 | D35: 0
B36: Taxable profit | C36: =SUM(C23:C35) -> -33900 | D36: =SUM(D23:D35) -> 92904
B37: Income tax expense @ 25% | C37: =C36*25% -> -8475 | D37: =D36*25% -> 23226

Sheet 3.16 to 3.20 ao 10.18
A1: ='[5]3.3'!A1:E1 -> CELER MART PVT. LTD.
A3: Notes to Financial Statements
A5: Figures in NPR
A7: 3.21. Changes in Accounting Policies (If any)
A8: In the current financial year the company changes in accounting policies. This change has been accounted for by restating comparatives and adjusting the opening balance of retained earnings at 01 Shrawan 20XX. The changes in accounting policy, when applied consistently to 20X1 had the follwoing impact: On Opening Retained Earnings; On Net Profit.
A10: 3.18. Contingencies
A11: The company has contingent liabilities in respect of bank and other guarantees and other matters arising in the ordinary course of business. It is not anticipated that any material liablitites will arise from the contingent liabilities.
A13: 3.19. Related Party Transactions
A14: Identity of related parties
A15: The company is controlled by (name of the parent company) which owns xx percent of the company's shares. The remaining xx percent shares are widely held. The ultimate parent company of the company is (name of the ultimate parent company) incorporated in (name of the country)
A16: The following transactions were carried out with related parties (Give details)
A17: Directors of the company and their immediate relatives control xx percent of the voting shares of the company. Loans to directors amounting to NRs xx (20XX: NRs xx) are included in "other receivables". No interest is payable by the directors (for disclose if interest is payable)
A18: In additiona to their salaries, the company also provides non-cash benefits to directors and executive officers, and contributes to a post-employment defined benefit plan on their behalf.
... A27: Prior period errors are ommissions or misstatements in an entity's financial statements. Such ommissions may relate to one or more prior periods. Correction of an error is done by calculating the cumulative effect of the change on the financial statements of the period as if new method or estimate had always been used for all the affected prior years' financial statements. Sometimes, such changes may not be practicable, in such cases it is applied to the latest period possible by making corresponding adjustment to the opening balance of the period.

Sheet Annex 1&2 ao 10.18
A1: ='[5]3.3'!A1:E1 -> CELER MART PVT. LTD.
A3: Notes to Financial Statements
A5: Figures in NPR
A7: Significant Accounting Policies and Notes to Accounts
A9: 1. General information
A10: Give brief information about the legal status, registered address and nature of the business of the company.
A11: The financial statements were authorized to issue by …....... on …........
A13: 2. Significant Accounting Policies
A14: 2.1 Basis of preparation and accounting policies
A15: 2.1.1 Statement of Compliance
A16: These financial statements have been prepared in accordance with Nepal Accounting Standard for Micro Entities (NAS for MEs).
A17: 2.2.2 Basis of Measurement
A18: The financial statements have been prepared on the historical cost basis except investments held-for-trade is measured at fair value.
... A96: Interest expenses are recognized in the statement of income using accrual method.

Sheet Tax Computation 10.18
A1: CALCULATION OF TAXABLE INCOME
A3: Profit before tax as per books | C3: ='SOI 10.18'!C19 -> -164485.25
A4: Add: Depreciation as per books | C4: ='SOI 10.18'!C17 -> 130585.25
A5: Less: Depreciation as per tax | C5: 0
A6: Add: Disallowed repairs
A7: Add: Gratuity expense as per books
A8: Less: Gratuity paid
A9: Add: Leave expense as per books
A10: Less: Leave paid
A11: Less: Fair value gain on investments
A12: Add: Exchange loss as per books
A13: Add: Realized exchange gain
A14: Add: Disallowed expenses
A15: Taxable profit | C15: =SUM(C3:C14) -> -33900
A16: Income tax expense @ 25% | C16: 0

Sheet SOFP  03.15
A1: Magic Arun Hydropower Private Limitd
A2: Statement of Financial Position
A3: As at 15 Asadh 2083
F4: Restated
C5: As at | D5: As at | E5: As at | F5: As at
B6: Notes | C6: 15 Ashadh 2083 | D6: 18 Magh 2082 | E6: 32 Ashadh 2082 | F6: 1 Shrawan 2081
A7: ASSETS
A8: Non-Current Assets
A9: Property, Plant and Equipment | B9: 3.1 | C9: ='3.1 03.15'!I52 -> 473888.75 | D9: ='3.1 10.18'!I44 -> 473888.75 | E9: ='3.1 10.18'!I42 -> 604474 | F9: 0 | H9: =+E9+E11 -> 604474 | I9: =+C9+C11 -> 473888.75
A10: Project in Progress (WIP) | B10: 3.1 | C10: ='3.1 03.15'!C76 -> 17094931 | D10: ='3.1 10.18'!C70 -> 15814476 | E10: ='3.1 10.18'!F70 -> 12985641 | F10: ='3.1 10.18'!G50 -> 12985641
A11: Intangible Assets | B11: 3.2 | C11: ='[5]3.2'!E43 -> 0 | D11: ='[5]3.2'!F43 -> 0 | E11: ='[5]3.2'!E41 -> 0 | F11: ='[5]3.2'!E39 -> 0 | H11: 821236.13 | I11: =+'SOI 10.18'!C17 -> 130585.25
A12: Investments | B12: 3.3 | C12: ='[5]3.3'!C34 -> 0 | D12: ='[5]3.3'!D34 -> 0 | E12: ='[5]3.3'!D34 -> 0 | F12: ='[5]3.3'!E34 -> 0 | H12: =+H9-H11 -> -216762.13 | I12: =SUM(I9:I11) -> 604474
A13: Other Receivables | B13: 3.4 | C13: 0 | D13: 0 | E13: 0 | F13: 0 | I13: 2699634.6 | J13: =+I12-I13 -> -2095160.6
A14: Total Non-Current Assets | C14: =SUM(C9:C13) -> 17568820 | D14: =SUM(D9:D13) -> 16288365 | E14: =SUM(E9:E13) -> 13590115 | F14: =SUM(F9:F13) -> 12985641
A15: Current Assets
A16: Investments | B16: 3.3 | C16: ='[5]3.3'!C35 -> 0 | D16: ='[5]3.3'!D35 -> 0 | E16: ='[5]3.3'!D35 -> 0 | F16: ='[5]3.3'!E35 -> 0
A17: Account receivables | B17: 3.4 | C17: ='3.4 to 3.6 ao 03.15'!C36 -> 25069196 | D17: ='3.4 to 3.6 ao 10.18'!C32 -> 21010112 | E17: ='3.4 to 3.6 ao 10.18'!D32 -> 15311962 | F17: ='3.4 to 3.6 ao 10.18'!E32 -> 21788699 | H17: AS per Tally
A18: Inventories | B18: 3.5 | E18: =+'3.4 to 3.6 ao 10.18'!D47 -> 0 | F18: =+'3.4 to 3.6 ao 10.18'!E47 -> 0 | H18: 10922985
A19: Cash and cash equivalents | B19: 3.6 | C19: ='3.4 to 3.6 ao 03.15'!C62 -> 1615017.4 | D19: ='3.4 to 3.6 ao 10.18'!C58 -> 12637.35 | E19: ='3.4 to 3.6 ao 10.18'!D58 -> 891197 | F19: ='3.4 to 3.6 ao 10.18'!E58 -> 67329
A20: Other current assets | B20: 3.7 | C20: =+'3.4 to 3.6 ao 10.18'!C68 -> 0 | D20: =+'3.4 to 3.6 ao 10.18'!D68 -> 0 | E20: =+'3.4 to 3.6 ao 10.18'!D68 -> 0 | F20: =+'3.4 to 3.6 ao 10.18'!E68 -> 0
A21: Total Current Assets | C21: =SUM(C16:C20) -> 26684214 | D21: =SUM(D16:D20) -> 21022749 | E21: =SUM(E16:E20) -> 16203159 | F21: =SUM(F16:F20) -> 21856028
A22: Total Assets | C22: =C21+C14 -> 44253034 | D22: =D21+D14 -> 37311114 | E22: =E21+E14 -> 29793274 | F22: =F21+F14 -> 34841669
A23: EQUITY AND LIABILITIES
A24: Equity
A25: Share Capital | B25: 3.8 | C25: ='3.7 to 3.8 03.15'!D35 -> 44000000 | D25: ='3.7 to 3.8 10.18'!D31 -> 10290000 | E25: ='3.7 to 3.8 10.18'!E31 -> 12600000 | F25: 0 | H25: 6175421.8 | I25: =+H25+E27 -> 5801845.8
A26: Calls in Advance | C26: ='3.7 to 3.8 03.15'!D42 -> 500000 | D26: ='3.7 to 3.8 10.18'!D38 -> 22500000 | E26: 0 | F26: ='3.7 to 3.8 10.18'!E38 -> 0
A27: Retained Earnings | B27: 3.9 | C27: ='3.7 to 3.8 03.15'!D51 -> -571961.25 | D27: ='3.7 to 3.8 10.18'!D47 -> -538061.25 | E27: ='3.7 to 3.8 10.18'!E47 -> -373576 | F27: ='3.7 to 3.8 10.18'!E45 -> -196480 | H27: -6165121.9 | I27: =+H27-E27 -> -5791545.9
A28: Total Equity | C28: =SUM(C25:C27) -> 43928039 | D28: =SUM(D25:D27) -> 32251939 | E28: =SUM(E25:E27) -> 12226424 | F28: =SUM(F25:F27) -> -196480 | I28: 79025.12
A29: Liabilities
A30: Non-Current Liabilities
A31: Loans and Borrowings | B31: 3.10 | C31: ='3.9 to 3.11 AO 03.15'!C25 -> 40000 | D31: ='3.9 to 3.11 AO 10.18'!D25 -> 3870000 | E31: ='3.9 to 3.11 AO 10.18'!E25 -> 17165000 | F31: ='3.9 to 3.11 AO 10.18'!F25 -> 20756010
A32: Provision for Employee Benefits | C32: ='3.9 to 3.11 AO 10.18'!D36 -> 0 | D32: ='3.9 to 3.11 AO 10.18'!E36 -> 0 | E32: ='3.9 to 3.11 AO 10.18'!E36 -> 0 | F32: ='3.9 to 3.11 AO 10.18'!F36 -> 0
A33: Provisions | E33: 0 | F33: 0
A34: Total Non-Current Liabilities | C34: =SUM(C31:C33) -> 40000 | D34: =SUM(D31:D33) -> 3870000 | E34: =SUM(E31:E33) -> 17165000 | F34: =SUM(F31:F33) -> 20756010
A35: Current Liabilities
A36: Loans and Borrowings | B36: 3.10 | C36: ='3.9 to 3.11 AO 10.18'!D26 -> 0 | D36: ='3.9 to 3.11 AO 10.18'!E26 -> 0 | E36: ='3.9 to 3.11 AO 10.18'!E26 -> 0 | F36: ='3.9 to 3.11 AO 10.18'!F26 -> 0
A37: Trade and other payables | B37: 3.11 | C37: ='3.9 to 3.11 AO 03.15'!C50+'3.9 to 3.11 AO 03.15'!C63 -> 284995.2 | D37: ='3.9 to 3.11 AO 10.18'!D49+'3.9 to 3.11 AO 10.18'!D61 -> 1189175 | E37: ='3.9 to 3.11 AO 10.18'!E49 -> 401850 | F37: ='3.9 to 3.11 AO 10.18'!F49 -> 28498
A38: Income Tax Liability | C38: ='3.9 to 3.11 AO 10.18'!D69 -> 0 | D38: ='3.9 to 3.11 AO 10.18'!E69 -> 0 | E38: ='3.9 to 3.11 AO 10.18'!E69 -> 0 | F38: ='3.9 to 3.11 AO 10.18'!F69 -> 0
A39: Provision for Employee Benefits | C39: 0 | D39: 0 | E39: 0 | F39: 0
A40: Provisions | C40: 0 | D40: 0 | E40: 0 | F40: 0
A41: Total Current Liabilities | C41: =SUM(C36:C40) -> 284995.2 | D41: =SUM(D36:D40) -> 1189175 | E41: =SUM(E36:E40) -> 401850 | F41: =SUM(F36:F40) -> 28498
A42: Total Liabilities | C42: =C34+C41 -> 324995.2 | D42: =D34+D41 -> 5059175 | E42: =E34+E41 -> 17566850 | F42: =F34+F41 -> 20784508
A43: Total Equity and Liabilities | C43: =C42+C28 -> 44253034 | D43: =D42+D28 -> 37311114 | E43: =E42+E28 -> 29793274 | F43: =F42+F28 -> 20588028
C49: =B22-B43 -> 0 | D49: =C22-C43 -> 0 | E49: =E22-E43 -> 0.15 | F49: =F22-F43 -> 14253641

Sheet SOI 03.15
A1: ='SOFP 10.18'!A1 -> Magic Arun Hydropower Private Limitd
A3: Statement of Income
A4: For the Year Ended 15 Asadh 2083
E5: Figures in NPR
E6: Restated
A7: Particulars | B7: Notes | C7: Upto 15 Asadh 2083 | D7: Upto 10 Magh 2082 | E7: FY 2081-82
A8: Revenue from Operations | B8: 3.12 | D8: ='3.12 to 3.18 ao 10.18'!D12 -> 0 | E8: ='3.12 to 3.18 ao 10.18'!E12 -> 0 | H8: =D8-E8 -> 0 | I8: =H8/E8 -> #DIV/0!
A9: Interest Income | D9: 0 | E9: 0
A10: Other Income | B10: 3.13 | D10: ='3.12 to 3.18 ao 10.18'!D21 -> 0 | E10: ='3.12 to 3.18 ao 10.18'!E21 -> 0
A11: Total Income | D11: =SUM(D8:D10) -> 0 | E11: =SUM(E8:E10) -> 0
A12: Material Consumed Expenses | B12: 3.14 | D12: ='3.12 to 3.18 ao 10.18'!D30 -> 0 | E12: ='3.12 to 3.18 ao 10.18'!E30 -> 0 | F12: =(D12+D13)/D8 -> #DIV/0! | G12: =(E12+E13)/E8 -> #DIV/0! | H12: =D12-E12 -> 0 | I12: =H12/E12 -> #DIV/0!
A13: Direct Expenses | B13: 3.15 | D13: =+'3.12 to 3.18 ao 10.18'!D38 -> 0 | E13: =+'3.12 to 3.18 ao 10.18'!E38 -> 0 | H13: =D13-E13 -> 0 | I13: =H13/E13 -> #DIV/0!
A14: Employee Benefit Expenses | B14: 3.16 | D14: =+'3.12 to 3.18 ao 10.18'!D50 -> 0 | E14: =+'3.12 to 3.18 ao 10.18'!E50 -> 0 | H14: =D14-E14 -> 0 | I14: =H14/E14 -> #DIV/0!
A15: Administrative and Other Expenses | B15: 3.17 | D15: ='3.12 to 3.18 ao 10.18'!D81 -> 33900 | E15: ='3.12 to 3.18 ao 10.18'!E81 -> 29382 | H15: =D15-E15 -> 4518 | I15: =H15/E15 -> 0.15376761
A16: Interest Expenses | B16: 3.18 | D16: ='3.12 to 3.18 ao 10.18'!D86 -> 0 | E16: ='3.12 to 3.18 ao 10.18'!E86 -> 0 | H16: =D16-E16 -> 0 | I16: =H16/E16 -> #DIV/0!
A17: Depreciation and Amortization Expenses | B17: 3.1 & 3.2 | D17: 0 | E17: =+'3.1 10.18'!I28+'[5]3.2'!E30 -> 147714 | F17: 187078.71 | G17: =+E17-F17 -> -39364.71 | H17: =D17-E17 -> -147714 | I17: =H17/E17 -> -1
A18: Total Expenses | D18: =SUM(D12:D17) -> 33900 | E18: =SUM(E12:E17) -> 177096
A19: Profit Before Tax | D19: =D11-D18 -> -33900 | E19: =E11-E18 -> -177096 | F19: -2368782.9 | G19: =+E19-F19 -> 2191686.9
A20: Income Tax Expense | D20: =SUM(D21:D22) -> 0 | E20: =SUM(E21:E22) -> 0
A21: Current year | D21: 0 | E21: 0
A22: Previous years | D22: 0 | E22: 0
A23: Net Profit for the year | D23: =D19-D20 -> -33900 | E23: =E19-E20 -> -177096

Sheet SOCE 03.15
A1: ='SOI 10.18'!A1 -> Magic Arun Hydropower Private Limitd
A3: Statement of Changes in Equity
A4: ='SOI 10.18'!A4 -> For the Year Ended 18 Magh 2082
G6: Figures in NPR
A7: Particulars | C7: Share Capital | D7: Calls in Advance | E7: Retained Earnings | F7: Other Reserves | G7: Total
A8: Balance at 1 Shrawan 2081 | C8: =+'SOFP 10.18'!E25 -> 0 | D8: 7600000 | E8: =+'3.7 to 3.8 10.18'!E45 -> -196480 | F8: 0 | G8: =SUM(C8:F8) -> 7403520
A9: Restatements on transition to NAS for MEs | C9: 0 | D9: 0 | E9: =SUM([5]Reco!F5:F8) -> 0 | F9: 0 | G9: =SUM(C9:F9) -> 0
A10: Balance at 1 Shrawan 2081 (restated) | C10: =SUM(C8:C9) -> 0 | D10: =SUM(D8:D9) -> 7600000 | E10: =SUM(E8:E9) -> -196480 | F10: =SUM(F8:F9) -> 0 | G10: =SUM(G8:G9) -> 7403520 | H10: ='SOFP 10.18'!E28 -> -196480 | I10: =G10-H10 -> 7600000
A11: Profit for the year | C11: 0 | D11: 0 | E11: ='SOI 10.18'!D23 -> -177096 | F11: 0 | G11: =+SUM(C11:F11) -> -177096
A12: Issue of Shares | C12: 12600000 | D12: -7600000 | E12: 0 | F12: 0 | G12: =+SUM(C12:F12) -> 5000000
A13: Dividends to Shareholders | C13: 0 | D13: 0 | E13: 0 | F13: 0 | G13: =+SUM(C13:F13) -> 0
A14: Other Changes | C14: 0 | D14: 0 | E14: 0 | F14: 0 | G14: =+SUM(C14:F14) -> 0
A15: Balance at 32 Ashad 2082 | C15: =SUM(C10:C14) -> 12600000 | D15: =SUM(D10:D14) -> 0 | E15: =SUM(E10:E14) -> -373576 | F15: =SUM(F10:F14) -> 0 | G15: =SUM(G10:G14) -> 12226424 | H15: ='SOFP 10.18'!D28 -> 12226424 | I15: =G15-H15 -> 0
A16: Profit for the year | C16: 0 | D16: 0 | E16: =+'SOI 10.18'!C23 -> -164485.25 | F16: 0 | G16: =+SUM(C16:F16) -> -164485.25
A17: Issue of Shares | C17: 0 | D17: 0 | E17: 0 | F17: 0 | G17: =+SUM(C17:F17) -> 0
A18: Dividends to Shareholders | C18: 0 | D18: 0 | E18: 0 | F18: 0 | G18: =+SUM(C18:F18) -> 0
A19: Other Changes | C19: 0 | D19: 0 | E19: 0 | F19: 0 | G19: =+SUM(C19:F19) -> 0
A20: Balance at 32 Ashad 2083 | C20: =SUM(C15:C19) -> 12600000 | D20: =SUM(D15:D19) -> 0 | E20: =SUM(E15:E19) -> -538061.25 | F20: =SUM(F15:F19) -> 0 | G20: =SUM(G15:G19) -> 12061939 | H20: ='SOFP 10.18'!C28 -> 32251939 | I20: =G20-H20 -> -20190000

Sheet SCF 03.15
A1: ='SOCE 10.18'!A1 -> Magic Arun Hydropower Private Limitd
A3: Statement of Cash Flows
A4: ='SOCE 10.18'!A4 -> For the Year Ended 18 Magh 2082
C5: Figures in NPR
A6: Particulars | B6: ='SOI 10.18'!C7 -> Upto 18 Magh 2082 | C6: ='SOI 10.18'!D7 -> FY 2081-82
A7: CASH FLOWS FROM OPERATING ACTIVITIES
A8: Profit for the year | B8: ='SOI 10.18'!C19 -> -164485.25 | C8: ='SOI 10.18'!D19 -> -177096 | D8: =B8-'SOFP 10.18'!J27 -> -164485.25
A9: Adjustment for:
A10: Depreciation/Impairment on Property, Plant and Equipment | B10: ='SOI 10.18'!C17 -> 130585.25 | C10: ='SOI 10.18'!D17 -> 147714
A11: Interest Income
A12: Interest Expense | B12: ='SOI 10.18'!C16 -> 0 | C12: ='SOI 10.18'!D16 -> 0
A13: Loss/(gain) on sale of Property, Plant and Equipment
A14: Income Tax expense charged to statement of income
A15: Working Capital Adjustments
A16: Decrease/(Increase) in trade and other receivables | B16: ='SOFP 10.18'!J17+'SOFP 10.18'!J20 -> 0 | C16: ='SOFP 10.18'!E17-'SOFP 10.18'!D17 -> 6476737
A17: Decrease/(Increase) in Inventories | B17: ='SOFP 10.18'!J18 -> 0 | C17: ='SOFP 10.18'!K18 -> 0
A18: Increase/(Decrease) in trade and other payables | B18: ='SOFP 10.18'!J37 -> 0 | C18: ='SOFP 10.18'!K37 -> 0
A19: Increase/(Decrease) Loan and Borrowings | C19: ='SOFP 10.18'!D31-'SOFP 10.18'!E31 -> -3591010
A20: Increase/(Decrease) in other liabilities | C20: 0
A21: Cash Generated from Operations | B21: =SUM(B8:B20) -> -33900 | C21: =SUM(C8:C20) -> 2856345
A22: Interest paid | C22: 0
A23: Income tax paid | C23: 0
A24: NET CASH FLOWS FROM OPERATING ACTIVITIES (A) | B24: =SUM(B21:B23) -> -33900 | C24: =SUM(C21:C23) -> 2856345
A25: CASH FLOW FROM INVESTING ACTIVITIES
A26: Proceeds from sale of PPE, Investments/Financial Assets | C26: =-'3.1 10.18'!I8 -> 0
A27: Increase in project WIP | B27: ='SOFP 10.18'!J12 -> 0 | C27: =-'SOFP 10.18'!D10+'SOFP 10.18'!E10 -> 0
A28: Acquisition of Property, Plant and Equipment | B28: =-'3.1 10.18'!I15-'[5]3.2'!E17 -> 0 | C28: =-'3.1 10.18'!I10-'[5]3.2'!E12 -> -752188
A29: NET CASH FLOWS FROM INVESTING ACTIVITIES (B) | B29: =SUM(B25:B28) -> 0 | C29: =SUM(C25:C28) -> -752188
A30: CASH FLOW FROM FINANCING ACTIVITIES
A31: Proceeds from the issue of Equity and Preference Share | C31: ='SOFP 10.18'!D25-'SOFP 10.18'!E26 -> 12600000
A32: Proceeds from loans and borrowings borrowings | B32: ='SOFP 10.18'!J36 -> 0 | C32: ='SOFP 10.18'!K36 -> 0
A33: Interest Expenses | B33: =-B12 -> 0 | C33: =-C12 -> 0
A34: Dividend Paid
A35: NET CASH FLOW FROM FINANCING ACTIVITIES (C) | B35: =SUM(B31:B34) -> 0 | C35: =SUM(C31:C34) -> 12600000
A36: Net Increase in Cash and Cash Equivalents | B36: =B24+B29+B35 -> -33900 | C36: =C24+C29+C35 -> 14704157
A37: Cash and Cash Equivalents at the beginning | B37: ='SOFP 10.18'!D19 -> 891197 | C37: ='SOFP 10.18'!E19 -> 67329
A38: Exchange gains/(losses) in cash and cash equivalents
A39: Cash and Cash Equivalents at the end | B39: =B36+B37 -> 857297 | C39: =C36+C37 -> 14771486
B40: ='3.4 to 3.6 ao 10.18'!C58 -> 12637.35 | C40: ='3.4 to 3.6 ao 10.18'!D58 -> 891197
B41: =B39-B40 -> 844659.65 | C41: =C39-C40 -> 13880289

Sheet 3.1 03.15
A1: ='SOFP 10.18'!A1 -> Magic Arun Hydropower Private Limitd
A2: Notes to Financial Statements
I3: Figures in NPR
A4: 3.1 | B4: Property, Plant and Equipment
C5: Furniture & Fixtures | D5: Computer | E5: Office Equipments | F5: Vehicles | G5: Plant and Machinery | H5: Office Furnishing | I5: Total
B6: Cost
B8: Balance at 1 Shrawan 2081 | C8: 0 | D8: 0 | E8: 0 | F8: 0 | G8: 0 | I8: =SUM(C8:G8) -> 0
I9: =SUM(C9:G9) -> 0
B10: Additions | C10: 532188 | D10: 0 | E10: 0 | F10: 220000 | G10: 0 | I10: =SUM(C10:G10) -> 752188
B11: Disposals | C11: 0 | D11: 0 | E11: 0 | F11: 0 | G11: 0 | I11: =SUM(C11:G11) -> 0
B13: Balance at 32 Ashadh 2082 | C13: =SUM(C8:C11) -> 532188 | D13: =SUM(D8:D11) -> 0 | E13: =SUM(E8:E11) -> 0 | F13: =SUM(F8:F11) -> 220000 | G13: =SUM(G8:G11) -> 0 | I13: =SUM(I8:I11) -> 752188
B15: Additions | C15: 0 | E15: 0 | G15: 0 | I15: =SUM(C15:G15) -> 0
B16: Disposals | C16: 0 | D16: 0 | E16: 0 | F16: 0 | G16: 0 | I16: =SUM(C16:G16) -> 0
B18: Balance at 18 Magh 2082 | C18: =SUM(C13:C16) -> 532188 | D18: =SUM(D13:D16) -> 0 | E18: =SUM(E13:E16) -> 0 | F18: =SUM(F13:F16) -> 220000 | G18: =SUM(G13:G16) -> 0 | H18: =SUM(H13:H16) -> 0 | I18: =SUM(C18:G18) -> 752188
B20: Additions
B21: Disposals
B23: Balance at 15 Asadh 2083 | C23: =SUM(C18:C21) -> 532188 | D23: =SUM(D18:D21) -> 0 | E23: =SUM(E18:E21) -> 0 | F23: =SUM(F18:F21) -> 220000 | G23: =SUM(G18:G21) -> 0 | H23: =SUM(H18:H21) -> 0 | I23: =SUM(I18:I21) -> 752188
B25: Accumulated depreciation
B27: =B8 -> Balance at 1 Shrawan 2081 | C27: 0 | D27: 0 | E27: 0 | F27: 0 | G27: 0 | I27: =SUM(C27:G27) -> 0
B29: Charge for the year | C29: 133047 | D29: 0 | E29: 0 | F29: 14667 | G29: 0 | H29: 0 | I29: =SUM(C29:H29) -> 147714
B30: Disposals
B32: =B13 -> Balance at 32 Ashadh 2082 | C32: =SUM(C27:C30) -> 133047 | D32: =SUM(D27:D30) -> 0 | E32: =SUM(E27:E30) -> 0 | F32: =SUM(F27:F30) -> 14667 | G32: =SUM(G27:G30) -> 0 | H32: =SUM(H27:H30) -> 0 | I32: =SUM(I27:I30) -> 147714
B34: Charge for the year | C34: =(C13-C29)*25% -> 99785.25 | E34: 0 | F34: 30800 | G34: 0 | H34: =(H18-H32)*15% -> 0 | I34: =SUM(C34:G34) -> 130585.25
B35: Disposals
B37: =B18 -> Balance at 18 Magh 2082 | C37: =C34+C32 -> 232832.25 | D37: =SUM(D32:D35) -> 0 | E37: =SUM(E32:E35) -> 0 | F37: =F34+F32 -> 45467 | G37: =SUM(G32:G35) -> 0 | H37: =SUM(H32:H35) -> 0 | I37: =SUM(C37:G37) -> 278299.25
B39: Charge for the year
B40: Disposals
B42: Balance at 15 Asadh 2083 | C42: =C39+C37 -> 232832.25 | D42: =D39+D37 -> 0 | E42: =E39+E37 -> 0 | F42: =F39+F37 -> 45467 | G42: =G39+G37 -> 0 | H42: =H39+H37 -> 0 | I42: =I39+I37 -> 278299.25
B44: Net Book Value
B46: As at 1st Shrawan 2081 | C46: =C8-C27 -> 0 | D46: =D8-D27 -> 0 | E46: =E8-E27 -> 0 | F46: =F8-F27 -> 0 | G46: =G8-G27 -> 0 | H46: =H8-H27 -> 0 | I46: =I8-I27 -> 0
B48: As at 32nd Ashad 2082 | C48: =C13-C32 -> 399141 | D48: =D13-D32 -> 0 | E48: =E13-E32 -> 0 | F48: =F13-F32 -> 205333 | G48: =G13-G32 -> 0 | H48: =H13-H32 -> 0 | I48: =SUM(C48:G48) -> 604474
B50: As at 18 Magh 2082 | C50: =C18-C37 -> 299355.75 | D50: =D18-D37 -> 0 | E50: =E18-E37 -> 0 | F50: =F18-F37 -> 174533 | G50: =G18-G37 -> 0 | H50: =H18-H37 -> 0 | I50: =SUM(C50:G50) -> 473888.75
B52: As at 15 Asadh 2083 | C52: =C23-C42 -> 299355.75 | D52: =D23-D42 -> 0 | E52: =E23-E42 -> 0 | F52: =F23-F42 -> 174533 | G52: =G23-G42 -> 0 | H52: =H23-H42 -> 0 | I52: =I23-I42 -> 473888.75
B54: 3.1.2 Project in Progress (WIP)
B55: Particulars | C55: As on 10 Magh 2082 | E55: During the period | G55: 2080.081
B56: Project Initial Expenses | C56: =C76 -> 17094931 | E56: =D76 -> 1280455.2 | G56: =F76 -> 15814476
C58: As on 15 Asadh 2083 | D58: During the period | F58: As on 10 Magh 2082
B59: Survey License Fee | C59: =F59+D59 -> 8000000 | D59: ='TB update upto 10.18'!I59 -> 0 | F59: ='TB update upto 10.18'!G59 -> 8000000
B60: License Renewal Fee | C60: =F60+D60 -> 2000000 | D60: ='TB update upto 10.18'!I60 -> 0 | F60: ='TB update upto 10.18'!G60 -> 2000000
B61: PPA Fee | C61: =F61+D61 -> 300000 | D61: ='TB update upto 10.18'!I61 -> 0 | F61: ='TB update upto 10.18'!G61 -> 300000
B62: Grid Impat Study Expenses (NEA) | C62: =F62+D62 -> 102000 | D62: ='TB update upto 10.18'!I62 -> 0 | F62: ='TB update upto 10.18'!G62 -> 102000
B63: Bank Charges | C63: =F63+D63 -> 275027.15 | D63: ='TB update upto 10.18'!I63 -> 370 | F63: ='TB update upto 10.18'!G63 -> 274657.15
B64: ERC Approval | C64: =F64+D64 -> 197000 | D64: ='TB update upto 10.18'!I64 -> 0 | F64: ='TB update upto 10.18'!G64 -> 197000
B65: Salary Expenses | C65: =F65+D65 -> 3917020.2 | D65: ='TB update upto 10.18'!I65 -> 927020.2 | F65: ='TB update upto 10.18'!G65 -> 2990000
B66: Travelling & Site Visit Expenses | C66: =F66+D66 -> 808129 | D66: ='TB update upto 10.18'!I66 -> 0 | F66: ='TB update upto 10.18'!G66 -> 808129
B67: Labour Wages | C67: =F67+D67 -> 660000 | D67: ='TB update upto 10.18'!I67 -> 0 | F67: ='TB update upto 10.18'!G67 -> 660000
B68: Office Rent | C68: =F68+D68 -> 240000 | D68: ='TB update upto 10.18'!I68 -> 0 | F68: ='TB update upto 10.18'!G68 -> 240000
B69: Repair & Maintenance Expenses | C69: =F69+D69 -> 37700 | D69: ='TB update upto 10.18'!I69 -> 0 | F69: ='TB update upto 10.18'!G69 -> 37700
B70: Printing & Stationary Expenses | C70: =F70+D70 -> 60880 | D70: ='TB update upto 10.18'!I70 -> 11565 | F70: ='TB update upto 10.18'!G70 -> 49315
... B75: TADA | C75: =F75+D75 -> 0 | D75: ='TB update upto 10.18'!I75 -> 0 | F75: ='TB update upto 10.18'!G75 -> 0
C76: =SUM(C59:C75) -> 17094931 | D76: =SUM(D59:D75) -> 1280455.2 | F76: =SUM(F59:F75) -> 15814476

Sheet TB update upto 10.18
E1: =E108-F108 -> 0
B2: Particulars | C2: Opening as on 2082.04.01 | D2: Opening as on 04.01 | E2: During the Year | G2: Closing as on 2082.10.18 | H2: Closing as on 2082.10.18 | I2: During 10.19 to 03.15 | J2: During 10.19 to 03.15 | K2: Closing as on 03.15 | M2: During 03.15 to 03.32 | O2: Closing as on 03.32 | P2: Cosing as on 03.32
C3: Dr | D3: Cr | E3: Dr | F3: Cr | G3: Dr | H3: Cr | I3: Dr. | J3: Cr. | K3: Dr. | L3: Cr. | M3: Dr. | N3: Cr | O3: Dr. | P3: Cr.
B4: Reserve & Surplus | C4: 373575.67 | G4: =C4-D4+E4-F4 -> 373575.67 | K4: =G4-H4+I4-J4 -> 373575.67 | O4: =K4-L4+M4-N4 -> 373575.67
B5: Share Capital
B6: I.B. Multipurpose Pvt Ltd | I6: ='TB 10.18 to 03.15'!B9 -> 0 | J6: ='TB 10.18 to 03.15'!C9 -> 15000000 | L6: =H6-G6+J6-I6 -> 15000000 | P6: =L6-K6+N6-M6 -> 15000000
B7: Happy Nepal Investment | I7: ='TB 10.18 to 03.15'!B10 -> 0 | J7: ='TB 10.18 to 03.15'!C10+D137 -> 25000000 | L7: =H7-G7+J7-I7 -> 25000000 | P7: =L7-K7+N7-M7 -> 25000000
B8: Indra Bahadur Bista | I8: ='TB 10.18 to 03.15'!B21 -> 0 | J8: ='TB 10.18 to 03.15'!C21 -> 1500000 | L8: =H8-G8+J8-I8 -> 1500000 | P8: =L8-K8+N8-M8 -> 1500000
B9: Tanka Prasad Pandey | I9: ='TB 10.18 to 03.15'!B22 -> 0 | J9: ='TB 10.18 to 03.15'!C22 -> 2500000 | L9: =H9-G9+J9-I9 -> 2500000 | P9: =L9-K9+N9-M9 -> 2500000
B10: Rajendra Karki | D10: 3200000 | E10: ='TB 2082.04.01-10.18'!D6 -> 2310000 | F10: ='TB 2082.04.01-10.18'!E6 -> 0 | H10: =D10-C10+F10-E10 -> 890000 | I10: ='TB 10.18 to 03.15'!B7 -> 2380000 | J10: ='TB 10.18 to 03.15'!C7 -> 0 | K10: =G10-H10+I10-J10 -> 1490000 | O10: =K10-L10+M10-N10 -> 1490000
B11: Bijay Bista | D11: 3200000 | E11: =+C119 -> 3200000 | F11: ='TB 2082.04.01-10.18'!E7 -> 0 | G11: =C11-D11+E11-F11 -> 0 | H11: =D11-C11+F11-E11 -> 0
B12: Kanchan Sherpa | D12: 200000 | E12: =C120 -> 200000 | G12: =C12-D12+E12-F12 -> 0 | H12: =D12-C12+F12-E12 -> 0
B13: Lilamani Pathak | D13: 1000000 | E13: =C121 -> 1000000 | G13: =C13-D13+E13-F13 -> 0 | H13: =D13-C13+F13-E13 -> 0
B14: Bhadra Ventures Pvt. Ltd. | D14: 5000000 | E14: =C122 -> 5000000 | G14: =C14-D14+E14-F14 -> 0 | H14: =D14-C14+F14-E14 -> 0
B15: Share - Shivaram Bhandari | F15: =D123 -> 5000000 | H15: =D15-C15+F15-E15 -> 5000000 | I15: =C133 -> 5000000 | L15: =H15-G15+J15-I15 -> 0 | P15: =L15-K15+N15-M15 -> 0
B16: Share - Indu Bhandari Basnet | F16: =D124 -> 2510000 | H16: =D16-C16+F16-E16 -> 2510000 | I16: =C134 -> 2510000 | L16: =H16-G16+J16-I16 -> 0 | P16: =L16-K16+N16-M16 -> 0
B17: Share - Nabaraj Tiwari | F17: =D125 -> 1260000 | H17: =D17-C17+F17-E17 -> 1260000 | I17: =C135 -> 1260000 | L17: =H17-G17+J17-I17 -> 0 | P17: =L17-K17+N17-M17 -> 0
B18: Share - Murali Adhikari | F18: =D126 -> 630000 | H18: =D18-C18+F18-E18 -> 630000 | I18: =C136 -> 630000 | L18: =H18-G18+J18-I18 -> 0 | P18: =L18-K18+N18-M18 -> 0
B19: Advance for Share Capital
B20: Share Advance - Shiv Ram Bhandari | E20: ='TB 2082.04.01-10.18'!D36 -> 0 | F20: ='TB 2082.04.01-10.18'!E36 -> 20000000 | H20: =D20-C20+F20-E20 -> 20000000 | I20: =C151+C162 -> 20600000 | J20: =D168 -> 600000 | L20: =H20-G20+J20-I20 -> 0 | P20: =L20-K20+N20-M20 -> 0
B21: Share Advance - Bond Construction | E21: ='TB 2082.04.01-10.18'!D38 -> 0 | F21: ='TB 2082.04.01-10.18'!E38 -> 2000000 | H21: =D21-C21+F21-E21 -> 2000000 | I21: =C171 -> 2000000 | L21: =H21-G21+J21-I21 -> 0 | P21: =L21-K21+N21-M21 -> 0
B22: Share Advance - Uttam Kumar | F22: ='TB 2082.04.01-10.18'!E28 -> 500000 | H22: =D22-C22+F22-E22 -> 500000 | L22: =H22-G22+J22-I22 -> 500000 | P22: =L22-K22+N22-M22 -> 500000
B23: Share Advance - Naresh Paudel | H23: 0 | L23: =H23-G23+J23-I23 -> 0 | P23: =L23-K23+N23-M23 -> 0
B24: Current Liabilities
B25: Duties & Taxes
B26: TDS on Audit fee | D26: 375 | F26: 450 | H26: =D26-C26+F26-E26 -> 825 | I26: =C141 -> 375 | J26: 450 | L26: =H26-G26+J26-I26 -> 900 | P26: =L26-K26+N26-M26 -> 900
B27: TDS on Salary (SST) | D27: 25750 | E27: ='TB 2082.04.01-10.18'!D13 -> 0 | F27: ='TB 2082.04.01-10.18'!E13 -> 4150 | H27: =D27-C27+F27-E27 -> 29900 | I27: =C142 -> 25750 | J27: ='TB 10.18 to 03.15'!C16+D181+D202 -> 9270.202 | L27: =H27-G27+J27-I27 -> 13420.202 | P27: =L27-K27+N27-M27 -> 13420.202
B28: TDS 15% | E28: ='TB 2082.04.01-10.18'!D31 -> 0 | F28: ='TB 2082.04.01-10.18'!E31 -> 7275 | H28: =D28-C28+F28-E28 -> 7275 | L28: =H28-G28+J28-I28 -> 7275 | M28: ='TB After 03.15'!B12 -> 0 | N28: ='TB After 03.15'!C12 -> 2250 | P28: =L28-K28+N28-M28 -> 9525
B29: TDS Pvt Ltd | E29: ='TB 2082.04.01-10.18'!D24 -> 0 | F29: ='TB 2082.04.01-10.18'!E24 -> 0 | I29: ='TB 10.18 to 03.15'!B20 -> 0 | J29: ='TB 10.18 to 03.15'!C20 -> 4500 | L29: =H29-G29+J29-I29 -> 4500 | M29: ='TB After 03.15'!B3 -> 0 | N29: ='TB After 03.15'!C3 -> 7235.625 | P29: =L29-K29+N29-M29 -> 11735.625
B30: TDS on office Rent | D30: 24000 | H30: =D30-C30+F30-E30 -> 24000 | I30: =C143 -> 24000 | L30: =H30-G30+J30-I30 -> 0 | P30: =L30-K30+N30-M30 -> 0
B31: TDS on Labour Wages | D31: 6600 | H31: =D31-C31+F31-E31 -> 6600 | I31: =C144 -> 6600 | L31: =H31-G31+J31-I31 -> 0 | P31: =L31-K31+N31-M31 -> 0
B32: Expenses Payable
B33: Audit Fee payable | D33: 27875 | F33: 33450 | H33: =D33-C33+F33-E33 -> 61325 | I33: =C145 -> 27875 | J33: 33450 | L33: =H33-G33+J33-I33 -> 66900 | P33: =L33-K33+N33-M33 -> 66900
B34: Gajulkot Engineering And Construction Pvt. Ltd. | M34: ='TB After 03.15'!B4 -> 0 | N34: ='TB After 03.15'!C4 -> 537848.12 | P34: =L34-K34+N34-M34 -> 537848.12
B35: Pragya Travels And Tours Pvt Ltd | M35: ='TB After 03.15'!B8 -> 0 | N35: ='TB After 03.15'!C8 -> 115990 | P35: =L35-K35+N35-M35 -> 115990
B36: Samyog Bashyal | M36: ='TB After 03.15'!B13 -> 0 | N36: ='TB After 03.15'!C13 -> 22061 | P36: =L36-K36+N36-M36 -> 22061
B37: Staff Payable | D37: 222750 | H37: =D37-C37+F37-E37 -> 222750 | I37: =C185 -> 222750 | L37: =H37-G37+J37-I37 -> 0 | P37: =L37-K37+N37-M37 -> 0
B38: Office Rent Payable | D38: 94500 | H38: =D38-C38+F38-E38 -> 94500 | I38: =C186 -> 94500 | L38: =H38-G38+J38-I38 -> 0 | P38: =L38-K38+N38-M38 -> 0
B39: Loan & Borrowings
B40: Naresh Poudel-Payable | D40: 365000 | F40: ='TB 2082.04.01-10.18'!E21 -> 25000 | H40: =D40-C40+F40-E40 -> 390000 | I40: =C190 -> 350000 | L40: =H40-G40+J40-I40 -> 40000 | P40: =L40-K40+N40-M40 -> 40000
B41: Sandip Thapa | D41: 200000 | H41: =D41-C41+F41-E41 -> 200000 | I41: =C191 -> 200000 | L41: =H41-G41+J41-I41 -> 0 | P41: =L41-K41+N41-M41 -> 0
B42: Shyam Prasad Kuikel | D42: 500000 | H42: =D42-C42+F42-E42 -> 500000 | I42: =C192 -> 500000 | L42: =H42-G42+J42-I42 -> 0 | P42: =L42-K42+N42-M42 -> 0
B43: Uttam Karki | I43: =C193 -> 500000 | K43: =G43-H43+I43-J43 -> 500000 | O43: =K43-L43+M43-N43 -> 500000
B44: Sita Karki | E44: ='TB 2082.04.01-10.18'!D8 -> 0 | F44: ='TB 2082.04.01-10.18'!E8 -> 700000 | H44: =D44-C44+F44-E44 -> 700000 | I44: =C167+C194 -> 700000 | L44: =H44-G44+J44-I44 -> 0 | P44: =L44-K44+N44-M44 -> 0
B45: Mamata Acharya - Payables | E45: ='TB 2082.04.01-10.18'!D19 -> 9225 | F45: ='TB 2082.04.01-10.18'!E19 -> 0 | G45: =C45-D45+E45-F45 -> 9225 | I45: ='TB 10.18 to 03.15'!B4+C195 -> 2350 | J45: ='TB 10.18 to 03.15'!C4+D148 -> 9365 | K45: =G45-H45+I45-J45 -> 2210 | M45: ='TB After 03.15'!B6 -> 0 | N45: ='TB After 03.15'!C6 -> 2210 | O45: =K45-L45+M45-N45 -> 0 | P45: =L45-K45+N45-M45 -> 0
B46: Baba Gas | E46: ='TB 2082.04.01-10.18'!D25 -> 0 | F46: ='TB 2082.04.01-10.18'!E25 -> 2000 | H46: =D46-C46+F46-E46 -> 2000 | L46: =H46-G46+J46-I46 -> 2000 | P46: =L46-K46+N46-M46 -> 2000
B47: Elite Wire Pvt. Ltd. | D47: 600000 | E47: ='TB 2082.04.01-10.18'!D43 -> 220000 | F47: ='TB 2082.04.01-10.18'!E43 -> 0 | H47: =D47-C47+F47-E47 -> 380000 | I47: =C154 -> 380000 | L47: =H47-G47+J47-I47 -> 0 | P47: =L47-K47+N47-M47 -> 0
B48: Sky Bridge Tours and Travels Pvt Ltd | E48: ='TB 2082.04.01-10.18'!D34 -> 0 | F48: ='TB 2082.04.01-10.18'!E34 -> 0 | H48: =D48-C48+F48-E48 -> 0
B49: Basudev Dhiktta | D49: 2200000 | H49: =D49-C49+F49-E49 -> 2200000 | I49: =C175 -> 2200000 | L49: =H49-G49+J49-I49 -> 0 | P49: =L49-K49+N49-M49 -> 0
B50: Bhadra Ventures Pvt. Ltd | D50: 1300000 | E50: ='TB 2082.04.01-10.18'!D33 -> 6300000 | F50: ='TB 2082.04.01-10.18'!E33 -> 0 | G50: =C50-D50+E50-F50 -> 5000000 | J50: =D152 -> 5000000 | K50: =G50-H50+I50-J50 -> 0 | O50: =K50-L50+M50-N50 -> 0
B51: Eak Raj Khatiwada | D51: 12000000 | E51: ='TB 2082.04.01-10.18'!D40 -> 12000000 | F51: ='TB 2082.04.01-10.18'!E40 -> 0 | G51: =C51-D51+E51-F51 -> 0 | H51: =D51-C51+F51-E51 -> 0
B52: Assets
B53: Non Current Assets
B54: PPE
B55: Furniture & Fixtures | C55: 399141 | G55: =C55-D55+E55-F55 -> 399141 | K55: =G55-H55+I55-J55 -> 399141 | O55: =K55-L55+M55-N55 -> 399141
B56: Vehicles | C56: 205333.33 | G56: =C56-D56+E56-F56 -> 205333.33 | K56: =G56-H56+I56-J56 -> 205333.33 | O56: =K56-L56+M56-N56 -> 205333.33
B57: Office Renovation Exp (Pool E) | M57: ='TB After 03.15'!B2 -> 545083.75 | N57: ='TB After 03.15'!C2 -> 0 | O57: =K57-L57+M57-N57 -> 545083.75
B58: CWIP
B59: Survey License Fee | C59: 8000000 | G59: =C59-D59+E59-F59 -> 8000000 | K59: =G59-H59+I59-J59 -> 8000000 | O59: =K59-L59+M59-N59 -> 8000000
B60: License Renewal Fee | E60: ='TB 2082.04.01-10.18'!D39 -> 2000000 | G60: =C60-D60+E60-F60 -> 2000000 | K60: =G60-H60+I60-J60 -> 2000000 | O60: =K60-L60+M60-N60 -> 2000000
B61: PPA Fee | C61: 300000 | G61: =C61-D61+E61-F61 -> 300000 | K61: =G61-H61+I61-J61 -> 300000 | O61: =K61-L61+M61-N61 -> 300000
B62: Grid Impat Study Expenses (NEA) | C62: 102000 | G62: =C62-D62+E62-F62 -> 102000 | K62: =G62-H62+I62-J62 -> 102000 | O62: =K62-L62+M62-N62 -> 102000
B63: Bank Charges | C63: 274657.15 | G63: =C63-D63+E63-F63 -> 274657.15 | I63: ='TB 10.18 to 03.15'!B5 -> 370 | J63: ='TB 10.18 to 03.15'!C5 -> 0 | K63: =G63-H63+I63-J63 -> 275027.15 | M63: ='TB After 03.15'!B9 -> 2101 | N63: ='TB After 03.15'!C9 -> 0 | O63: =K63-L63+M63-N63 -> 277128.15
B64: ERC Approval | C64: 197000 | G64: =C64-D64+E64-F64 -> 197000 | K64: =G64-H64+I64-J64 -> 197000 | O64: =K64-L64+M64-N64 -> 197000
B65: Salary Expenses | C65: 2575000 | E65: ='TB 2082.04.01-10.18'!D9+'TB 2082.04.01-10.18'!D10+'TB 2082.04.01-10.18'!D11+'TB 2082.04.01-10.18'!D12 -> 415000 | G65: =C65-D65+E65-F65 -> 2990000 | I65: ='TB 10.18 to 03.15'!B15+C180+C201 -> 927020.2 | J65: ='TB 10.18 to 03.15'!C15 -> 0 | K65: =G65-H65+I65-J65 -> 3917020.2 | O65: =K65-L65+M65-N65 -> 3917020.2
B66: Travelling & Site Visit Expenses | C66: 464344 | E66: ='TB 2082.04.01-10.18'!D35+'TB 2082.04.01-10.18'!D26+'TB 2082.04.01-10.18'!D27 -> 343785 | F66: ='TB 2082.04.01-10.18'!E35 -> 0 | G66: =C66-D66+E66-F66 -> 808129 | K66: =G66-H66+I66-J66 -> 808129 | M66: ='TB After 03.15'!B7 -> 125301 | N66: ='TB After 03.15'!C7 -> 0 | O66: =K66-L66+M66-N66 -> 933430
B67: Labour Wages | C67: 660000 | G67: =C67-D67+E67-F67 -> 660000 | K67: =G67-H67+I67-J67 -> 660000 | O67: =K67-L67+M67-N67 -> 660000
B68: Office Rent | C68: 240000 | G68: =C68-D68+E68-F68 -> 240000 | K68: =G68-H68+I68-J68 -> 240000 | O68: =K68-L68+M68-N68 -> 240000
B69: Repair & Maintenance Expenses | C69: 37700 | G69: =C69-D69+E69-F69 -> 37700 | K69: =G69-H69+I69-J69 -> 37700 | O69: =K69-L69+M69-N69 -> 37700
B70: Printing & Stationary Expenses | C70: 42350 | E70: ='TB 2082.04.01-10.18'!D14 -> 6965 | G70: =C70-D70+E70-F70 -> 49315 | I70: ='TB 10.18 to 03.15'!B2 -> 11565 | J70: ='TB 10.18 to 03.15'!C2 -> 0 | K70: =G70-H70+I70-J70 -> 60880 | M70: ='TB After 03.15'!B5 -> 2210 | N70: ='TB After 03.15'!C5 -> 0 | O70: =K70-L70+M70-N70 -> 63090
B71: Local Conveyances | C71: 7360 | E71: ='TB 2082.04.01-10.18'!D15+'TB 2082.04.01-10.18'!D16+'TB 2082.04.01-10.18'!D17+'TB 2082.04.01-10.18'!D18+'TB 2082.04.01-10.18'!D32+'TB 2082.04.01-10.18'!D44 -> 14585 | G71: =C71-D71+E71-F71 -> 21945 | I71: ='TB 10.18 to 03.15'!B3+'TB 10.18 to 03.15'!B8 -> 2500 | J71: ='TB 10.18 to 03.15'!C3+'TB 10.18 to 03.15'!C8 -> 0 | K71: =G71-H71+I71-J71 -> 24445 | O71: =K71-L71+M71-N71 -> 24445
B72: Office Tiffin Expenses | C72: 85230 | G72: =C72-D72+E72-F72 -> 85230 | K72: =G72-H72+I72-J72 -> 85230 | O72: =K72-L72+M72-N72 -> 85230
B73: Meeting Allowance - Presentation feasibility | E73: ='TB 2082.04.01-10.18'!D30 -> 48500 | F73: ='TB 2082.04.01-10.18'!E30 -> 0 | G73: =C73-D73+E73-F73 -> 48500 | K73: =G73-H73+I73-J73 -> 48500 | O73: =K73-L73+M73-N73 -> 48500
B74: IEE Study Expenses | I74: ='TB 10.18 to 03.15'!B19 -> 339000 | J74: ='TB 10.18 to 03.15'!C19 -> 0 | K74: =G74-H74+I74-J74 -> 339000 | O74: =K74-L74+M74-N74 -> 339000
B75: TADA | M75: ='TB After 03.15'!B11 -> 15000 | N75: ='TB After 03.15'!C11 -> 0 | O75: =K75-L75+M75-N75 -> 15000
B76: Current Assets
B77: Account Receivables | G77: =C77-D77+E77-F77 -> 0
B78: Bijaya bista | C78: 4000000 | E78: ='TB 2082.04.01-10.18'!D7 -> 1000000 | G78: =C78-D78+E78-F78 -> 5000000 | K78: =G78-H78+I78-J78 -> 5000000 | O78: =K78-L78+M78-N78 -> 5000000
B79: Pramod Neupane - (Bijay Bista Share Return) | E79: ='TB 2082.04.01-10.18'!D42 -> 500000 | F79: ='TB 2082.04.01-10.18'!E42 -> 0 | G79: =C79-D79+E79-F79 -> 500000 | J79: =D198 -> 352350 | K79: =G79-H79+I79-J79 -> 147650 | O79: =K79-L79+M79-N79 -> 147650
B80: Rajendra Karki-Advance | C80: 5563462 | G80: =C80-D80+E80-F80 -> 5563462 | J80: =D159+D172+D182+D187 -> 2916750 | K80: =G80-H80+I80-J80 -> 2646712 | O80: =K80-L80+M80-N80 -> 2646712
B81: Hem Raj Bhattarai - Advance Return | I81: ='TB 10.18 to 03.15'!B12 -> 1800000 | J81: ='TB 10.18 to 03.15'!C12 -> 0 | K81: =G81-H81+I81-J81 -> 1800000 | O81: =K81-L81+M81-N81 -> 1800000
B82: Ambe Hydropower Pvt Ltd | I82: ='TB 10.18 to 03.15'!B13 -> 2000000 | J82: ='TB 10.18 to 03.15'!C13 -> 0 | K82: =G82-H82+I82-J82 -> 2000000 | O82: =K82-L82+M82-N82 -> 2000000
B83: Bidhya Rai - Advance Return | I83: ='TB 10.18 to 03.15'!B11 -> 8700000 | J83: =+C175 -> 2200000 | K83: =G83-H83+I83-J83 -> 6500000 | O83: =K83-L83+M83-N83 -> 6500000
B84: Elite Steel Pvt. Ltd. | E84: ='TB 2082.04.01-10.18'!D5 -> 260000 | F84: ='TB 2082.04.01-10.18'!E5 -> 0 | G84: =C84-D84+E84-F84 -> 260000 | J84: =D156 -> 260000 | K84: =G84-H84+I84-J84 -> 0 | O84: =K84-L84+M84-N84 -> 0
B85: Babita Katwal | I85: ='TB 10.18 to 03.15'!B23 -> 0 | J85: ='TB 10.18 to 03.15'!C23 -> 0
B86: Divya Jyoti Construction Pvt. Ltd. - Advance Return | I86: ='TB 10.18 to 03.15'!B14 -> 15600000 | J86: =D163 -> 15600000 | K86: =G86-H86+I86-J86 -> 0 | O86: =K86-L86+M86-N86 -> 0
B87: Bikram Bista | I87: ='TB 10.18 to 03.15'!B24 -> 800000 | J87: =D196 -> 800000 | K87: =G87-H87+I87-J87 -> 0 | O87: =K87-L87+M87-N87 -> 0
B88: Raj Kumar Mishra | I88: ='TB 10.18 to 03.15'!B25 -> 200000 | J88: =D203 -> 200000 | K88: =G88-H88+I88-J88 -> 0 | O88: =K88-L88+M88-N88 -> 0
B89: Elite Power Pvt. Ltd. | C89: 3000000 | E89: ='TB 2082.04.01-10.18'!D3 -> 0 | F89: ='TB 2082.04.01-10.18'!E3 -> 3200000 | H89: =D89-C89+F89-E89 -> 200000 | I89: =C155 -> 200000 | L89: =H89-G89+J89-I89 -> 0 | P89: =L89-K89+N89-M89 -> 0
B90: Kanchan Sherpa -(Bijay Bista Share Return) | E90: ='TB 2082.04.01-10.18'!D41 -> 500000 | F90: ='TB 2082.04.01-10.18'!E41 -> 0 | G90: =C90-D90+E90-F90 -> 500000 | H90: 0 | J90: =D197 -> 500000 | K90: =G90-H90+I90-J90 -> 0 | O90: =K90-L90+M90-N90 -> 0
B91: Consultant Advance
B92: Samyak Consulting Engineering Pvt. Ltd. | E92: ='TB 2082.04.01-10.18'!D22 -> 529624.5 | F92: ='TB 2082.04.01-10.18'!E22 -> 0 | G92: =C92-D92+E92-F92 -> 529624.5 | K92: =G92-H92+I92-J92 -> 529624.5 | O92: =K92-L92+M92-N92 -> 529624.5
B93: Slesha Engineering Consultancy Pvt. Ltd | C93: 2200000 | E93: ='TB 2082.04.01-10.18'!D45 -> 700000 | F93: ='TB 2082.04.01-10.18'!E45 -> 0 | G93: =C93-D93+E93-F93 -> 2900000 | I93: ='TB 10.18 to 03.15'!B17 -> 1000000 | J93: ='TB 10.18 to 03.15'!C17 -> 0 | K93: =G93-H93+I93-J93 -> 3900000 | O93: =K93-L93+M93-N93 -> 3900000
B94: Enviromental Partners Pvt.Ltd | C94: 250000 | G94: =C94-D94+E94-F94 -> 250000 | I94: ='TB 10.18 to 03.15'!B18 -> 4500 | J94: ='TB 10.18 to 03.15'!C18 -> 0 | K94: =G94-H94+I94-J94 -> 254500 | O94: =K94-L94+M94-N94 -> 254500
B95: Mohan Bista (for Audit) | E95: ='TB 2082.04.01-10.18'!D37 -> 124300 | F95: ='TB 2082.04.01-10.18'!E37 -> 0 | G95: =C95-D95+E95-F95 -> 124300 | J95: =D147 -> 124300 | K95: =G95-H95+I95-J95 -> 0 | L95: =H95-G95+J95-I95 -> 0 | O95: =K95-L95+M95-N95 -> 0
B96: Buddha Law Assocites Pvt Ltd | E96: ='TB 2082.04.01-10.18'!D29 -> 75000 | F96: ='TB 2082.04.01-10.18'!E29 -> 0 | G96: =C96-D96+E96-F96 -> 75000 | J96: =D158 -> 75000 | K96: =G96-H96+I96-J96 -> 0 | O96: =K96-L96+M96-N96 -> 0
B97: Staff Advance Site
B98: Kamal Karki | G98: =C98-D98+E98-F98 -> 0 | J98: =D157 -> 190000 | L98: =H98-G98+J98-I98 -> 190000 | P98: =L98 -> 190000
B99: Deposit & Margins
B100: Cash Margin-PB-NEA | C100: 298500 | G100: =C100-D100+E100-F100 -> 298500 | K100: =G100-H100+I100-J100 -> 298500 | O100: =K100-L100+M100-N100 -> 298500
...

Sheet 3.9 to 3.11 AO 03.15
A1: ='[5]3.3'!A1:E1 -> CELER MART PVT. LTD.
A3: Notes to Financial Statements
F5: Figures in NPR
A7: 3.9 | B7: Loans and Borrowings
C8: As at | D8: ='3.7 to 3.8 10.18'!D8 -> As at | E8: ='3.7 to 3.8 10.18'!E8 -> As at | F8: =E8 -> As at
C9: 15 Asadh 2083 | D9: ='SOFP 10.18'!C6 -> 18 Magh 2082 | E9: ='SOFP 10.18'!D6 -> 32 Ashadh 2082 | F9: ='SOFP 10.18'!E6 -> 1 Shrawan 2081
B10: Total Loans and Borrowings
B11: Bank Overdraft | D11: 0 | E11: 0 | F11: 0
B12: Short Term Payable | D12: 0 | E12: 0 | F12: 20756010
B13: Basudev Dhiktta | D13: ='TB update upto 10.18'!H49 -> 2200000 | E13: 2200000
B14: Bhadra Ventures Pvt.Ltd | D14: 0 | E14: 1300000
B15: Eak Raj Khatiwada | E15: 12000000
B16: Naresh Poudel-Payable | C16: ='TB update upto 10.18'!L40 -> 40000 | D16: ='TB update upto 10.18'!H40 -> 390000 | E16: 365000
B17: Sandipa Thapa | D17: ='TB update upto 10.18'!H41 -> 200000 | E17: 200000
B18: Shyam Prasad Kuikel | D18: ='TB update upto 10.18'!H42 -> 500000 | E18: 500000
B19: Ellite Wire Pvt.Ltd | D19: ='TB update upto 10.18'!H47 -> 380000 | E19: 600000
B20: Ellite Powers Pvt.Ltd | D20: ='TB update upto 10.18'!H89 -> 200000 | E20: 0
C23: =SUM(C11:C20) -> 40000 | D23: =SUM(D11:D20) -> 3870000 | E23: =SUM(E11:E20) -> 17165000 | F23: =SUM(F11:F19) -> 20756010
B25: Non-current loans and borrowings | C25: =C23-C26 -> 40000 | D25: =D23-D26 -> 3870000 | E25: =E23-E26 -> 17165000 | F25: =F23-F26 -> 20756010
B26: Current loans and borrowings | C26: =C11 -> 0 | D26: =D11 -> 0 | E26: =E11 -> 0 | F26: =F11 -> 0
A29: 3.10 | B29: Provision for Employee Benefits
C31: =C8 -> As at | D31: =D8 -> As at | E31: =E8 -> As at | F31: =F8 -> As at
C32: =C9 -> 15 Asadh 2083 | D32: =D9 -> 18 Magh 2082 | E32: =E9 -> 32 Ashadh 2082 | F32: =F9 -> 1 Shrawan 2081
B34: Provision for Gratuity | D34: 0 | E34: 0
B35: Provision for Leave benefits
C36: =SUM(C34:C35) -> 0 | D36: =SUM(D34:D35) -> 0 | E36: =SUM(E34:E35) -> 0 | F36: =SUM(F34:F35) -> 0
A38: 3.11 | B38: Trade and other payables
C39: =C31 -> As at | D39: =D31 -> As at | E39: =E31 -> As at | F39: =F31 -> As at
C40: =C32 -> 15 Asadh 2083 | D40: =D32 -> 18 Magh 2082 | E40: =E32 -> 32 Ashadh 2082 | F40: =F32 -> 1 Shrawan 2081
B41: TDS on Audit Fee | C41: ='TB update upto 10.18'!L26 -> 900 | D41: ='TB update upto 10.18'!H26 -> 825 | E41: 375 | F41: 375
B42: TDS on Salary (SST) | C42: ='TB update upto 10.18'!L27 -> 13420.202 | D42: ='TB update upto 10.18'!H27 -> 29900 | E42: 25750 | F42: 248
B43: TDS on Office Rent | D43: ='TB update upto 10.18'!H30 -> 24000 | E43: 24000 | F43: 0 | G43: Net of TDS
B44: TDS on Labour Wages | D44: ='TB update upto 10.18'!H31 -> 6600 | E44: 6600 | F44: 0
B45: Audit Fee Payable | C45: ='TB update upto 10.18'!L33 -> 66900 | D45: ='TB update upto 10.18'!H33 -> 61325 | E45: 27875 | F45: 27875
B46: Staff Payable | D46: ='TB update upto 10.18'!H37 -> 222750 | E46: 222750 | F46: 0
B47: Office Rent Payable | D47: ='TB update upto 10.18'!H38 -> 94500 | E47: 94500 | F47: 0
B48: TDS on Meeting Fee | C48: ='TB update upto 10.18'!L28 -> 7275 | D48: ='TB update upto 10.18'!H28 -> 7275
B49: TDS Pvt. Ltd. | C49: ='TB update upto 10.18'!L29 -> 4500
C50: =SUM(C41:C49) -> 92995.202 | D50: =SUM(D41:D49) -> 447175 | E50: =SUM(E41:E47) -> 401850 | F50: =SUM(F41:F47) -> 28498
B51: Other payable
B52: =[5]Sheet1!A8 -> Sita Karki | C52: ='TB update upto 10.18'!L44 -> 0 | D52: ='TB update upto 10.18'!H44 -> 700000
B53: =[5]Sheet1!A19 -> Mamata Acharya - Payable
B54: Samyak Consulting Engineering Pvt. Ltd. | E54: 0
B55: Baba Gas | C55: ='TB update upto 10.18'!L46 -> 2000 | D55: ='TB update upto 10.18'!H46 -> 2000
B56: Kamal Karki - Site Visit | E56: 0
B57: Naresh Poudel - Site Visit | E57: 0
B58: Buddha Law Assocites Pvt Ltd
B59: Bhadra Venture
B60: Mohan Bista - Auditor (SST, TDS, Audit Fee)
B61: Shiva Ram Bhandari - Other Advance | D61: ='TB update upto 10.18'!H107 -> 40000
B62: Kamal Karki advance | C62: ='TB update upto 10.18'!L98 -> 190000
C63: =SUM(C52:C62) -> 192000 | D63: =SUM(D52:D62) -> 742000
A66: 3.12 | B66: Income tax liability
D67: =D39 -> As at | E67: =E39 -> As at | F67: =F39 -> As at
D68: =D40 -> 18 Magh 2082 | E68: =E40 -> 32 Ashadh 2082 | F68: =F40 -> 1 Shrawan 2081
B69: Provision for tax | D69: 0 | E69: 0 | F69: 0
D71: =SUM(D69:D70) -> 0 | E71: =SUM(E69:E70) -> 0 | F71: =SUM(F69:F70) -> 0

Sheet 3.7 to 3.8 03.15
A1: ='[5]3.3'!A1:E1 -> CELER MART PVT. LTD.
B3: Notes to Financial Statements
F5: Figures in NPR
A7: 3.7 | B7: Share Capital
D8: As at | E8: ='3.4 to 3.6 ao 10.18'!D6 -> As at | F8: ='3.4 to 3.6 ao 10.18'!E6 -> As at
D9: 15 Asadh 2083 | E9: ='3.4 to 3.6 ao 10.18'!C7 -> 18 Magh 2082 | F9: ='3.4 to 3.6 ao 10.18'!D7 -> 32 Ashadh 2082
B11: Authorized
B12: 260,000 ordinary shares of NPR 100 each | E12: 26000000 | F12: =E12 -> 26000000
B14: Ordinary Shares Issued and Fully Paid
B15: Ordinary shares of Rs. 100 each
E16: Ordinary | F16: Ordinary
E17: share | F17: share capital
D18: As at | E18: As at | F18: As at
D19: 15 Asadh 2083 | E19: 10 Magh 2082 | F19: 32 Ashadh 2082
B20: Paid up Share capital
B21: Bijay Bista | F21: 3200000
B22: Rajendra Karki | E22: ='TB update upto 10.18'!H10 -> 890000 | F22: 3200000
B23: Kanchan Sherpa | F23: 200000
B24: Lilamani Pathak | F24: 1000000
B25: Bhadra Ventures Pvt.LTD | F25: 5000000
B26: Shivaram Bhandari | E26: ='TB update upto 10.18'!H15 -> 5000000
B27: Indu Bhandari Basnet | E27: ='TB update upto 10.18'!H16 -> 2510000
B28: Nabaraj Tiwari | E28: ='TB update upto 10.18'!H17 -> 1260000
B29: Murali Adhikari | E29: ='TB update upto 10.18'!H18 -> 630000
B30: I.B. Multipurpose Pvt Ltd | D30: ='TB update upto 10.18'!L6 -> 15000000
B31: Happy Nepal Investment | D31: ='TB update upto 10.18'!L7 -> 25000000
B32: Indra Bahadur Bista | D32: ='TB update upto 10.18'!L8 -> 1500000
B33: Tanka Prasad Pandey | D33: ='TB update upto 10.18'!L9 -> 2500000
B35: Total | D35: =SUM(D30:D34) -> 44000000 | E35: =SUM(E21:E34) -> 10290000 | F35: =SUM(F21:F34) -> 12600000
D36: As at | E36: As at | F36: As at
B37: Share Advance | D37: 15 Asadh 2083 | E37: 10 Magh 2082 | F37: 32 Ashadh 2082
B38: Shiv Ram Bhandari | D38: ='TB update upto 10.18'!L20 -> 0 | E38: ='TB update upto 10.18'!H20 -> 20000000
B39: Bond Construction | D39: ='TB update upto 10.18'!L21 -> 0 | E39: ='TB update upto 10.18'!H21 -> 2000000
B40: Uttam Kumar | D40: ='TB update upto 10.18'!L22 -> 500000 | E40: ='TB update upto 10.18'!H22 -> 500000
B41: Lilamani Pathak
B42: Total | D42: =SUM(D38:D41) -> 500000 | E42: =SUM(E38:E41) -> 22500000 | F42: =SUM(F38:F41) -> 0
A44: 3.8 | B44: Retained Earnings
D46: As at | E46: =E8 -> As at | F46: =F8 -> As at
D47: 15 Asadh 2083 | E47: ='SOFP 10.18'!C6 -> 18 Magh 2082 | F47: ='SOFP 10.18'!D6 -> 32 Ashadh 2082 | H47: New | K47: Old
B49: Opening balance | D49: =+E51 -> -538061.25 | E49: =+F51 -> -373576 | F49: -196480 | H49: =+F49 -> -196480 | K49: =+F49 -> -196480
B50: Net profit for the year | D50: ='SOI 03.15'!D23 -> -33900 | E50: ='SOI 10.18'!C23 -> -164485.25 | F50: ='SOI 10.18'!D23 -> -177096 | H50: -2368782.9 | K50: =+'SOI 10.18'!E19 -> -2368782.9
B51: Closing balance | D51: =SUM(D49:D50) -> -571961.25 | E51: =SUM(E49:E50) -> -538061.25 | F51: =SUM(F49:F50) -> -373576 | H51: =SUM(H49:H50) -> -2565262.9 | I51: As per FS | K51: =+K49+K50 -> -2565262.9
H52: =+#REF!+#REF! -> #REF! | I52: AS per Tally
F53: =+F51-H51 -> 2191686.9 | H53: =+H51+H52 -> #REF!

Sheet 3.4 to 3.6 ao 03.15
A1: ='SOFP 10.18'!A1 -> Magic Arun Hydropower Private Limitd
A2: Notes to Financial Statements
D4: Figures in NPR
A6: 3.4 | B6: Account Receivables | C6: As at | D6: ='[5]3.3'!C29 -> As at | E6: ='[5]3.3'!D29 -> As at | F6: ='[5]3.3'!E29 -> As at
C7: 15 Asadh 2083 | D7: 10 Magh 2082 | E7: ='[5]3.3'!D30 -> 32 Ashadh 2082 | F7: ='[5]3.3'!E30 -> 1 Shrawan 2081
B9: Account Receivables
B10: Advance for Road Construction | D10: 0 | E10: 0 | F10: 1000000
B11: Advance for Land Purchase | D11: 0 | E11: 0 | F11: 20300000
B12: Site Advance | D12: 0 | E12: 0 | F12: 488699
B13: Other Receivables
B14: Bijaya Bista | C14: ='TB update upto 10.18'!K78 -> 5000000 | D14: ='TB update upto 10.18'!G78 -> 5000000 | E14: 4000000
B15: Ellite Powers Pvt.Ltd | C15: 0 | D15: 0 | E15: 3000000
B16: Environment Partners Pvt.Ltd | C16: ='TB update upto 10.18'!K94 -> 254500 | D16: ='TB update upto 10.18'!G94 -> 250000 | E16: 250000
B17: Rajendra Karki- Advance | C17: ='TB update upto 10.18'!K80+'TB update upto 10.18'!K10 -> 4136712 | D17: ='TB update upto 10.18'!G80 -> 5563462 | E17: 5563462
B18: Slesha Engineering Consultancy Pvt.Ltd | C18: ='TB update upto 10.18'!K93 -> 3900000 | D18: ='TB update upto 10.18'!G93 -> 2900000 | E18: 2200000 | F18: 0
B19: Ellite Steel Pvt.ltd | C19: ='TB update upto 10.18'!K84 -> 0 | D19: ='TB update upto 10.18'!G84 -> 260000
B20: Buddha Law Associates | C20: ='TB update upto 10.18'!K96 -> 0 | D20: ='TB update upto 10.18'!G96 -> 75000
B21: Other Receivables | C21: ='TB update upto 10.18'!K95+'TB update upto 10.18'!K45 -> 2210 | D21: ='TB update upto 10.18'!G95+'TB update upto 10.18'!G45 -> 133525
B22: Samyak Consulting Pvt. Ltd. | C22: ='TB update upto 10.18'!K92 -> 529624.5 | D22: ='TB update upto 10.18'!G92 -> 529624.5
B23: Bahadur Ventures Pvt. Ltd. | C23: ='TB update upto 10.18'!K50 -> 0 | D23: ='TB update upto 10.18'!G50 -> 5000000
B24: Pramod Neupane | C24: ='TB update upto 10.18'!K79 -> 147650 | D24: ='TB update upto 10.18'!G79 -> 500000
B25: kanchan Sherpa | C25: ='TB update upto 10.18'!K90 -> 0 | D25: ='TB update upto 10.18'!G90 -> 500000
B26: Uttam Karki | C26: ='TB update upto 10.18'!K43 -> 500000
B27: Hem raj Bhattarai | C27: ='TB update upto 10.18'!K81 -> 1800000 | D27: ='TB update upto 10.18'!G81 -> 0
B28: Ambe Hydropower pvt. Ltd | C28: ='TB update upto 10.18'!K82 -> 2000000 | D28: 0
B29: Bidhya Rai | C29: ='TB update upto 10.18'!K83 -> 6500000 | D29: ='TB update upto 10.18'!G83 -> 0
B31: Deposit
B32: Cash Margin-PB-NEA | C32: ='TB update upto 10.18'!K100 -> 298500 | D32: ='TB update upto 10.18'!G100 -> 298500 | E32: 298500 | F32: 0
C33: =+C12+SUM(C14:C32) -> 25069196 | D33: =+D12+SUM(D14:D32) -> 21010112 | E33: =SUM(E10:E32) -> 15311962 | F33: =SUM(F10:F18) -> 21788699
B35: Non-current portion | C35: 0 | D35: 0 | E35: 0 | F35: 0
B36: Current portion | C36: =C33 -> 25069196 | D36: =D33 -> 21010112 | E36: =E33 -> 15311962 | F36: =F33 -> 21788699
B38: Provision for impairment of trade receivables: | E38: FY | F38: FY
E39: 2081-82 | F39: 2080-81
B40: Balance at the beginning of the year | E40: 0 | F40: 0
B41: Provided during the year | E41: 0 | F41: 0
B42: Written off during the year | E42: 0 | F42: 0
B43: Unused provisions reversed | E43: 0 | F43: 0
B45: Balance at the end of the year | E45: =SUM(E40:E43) -> 0 | F45: =SUM(F40:F43) -> 0
A47: 3.5 | B47: Inventories
C48: =C6 -> As at | D48: =D6 -> As at | E48: =E6 -> As at | F48: =F6 -> As at
C49: =C7 -> 15 Asadh 2083 | D49: =D7 -> 10 Magh 2082 | E49: =E7 -> 32 Ashadh 2082 | F49: =F7 -> 1 Shrawan 2081
B51: Inventories of goods held for resale | C51: ='3.12 to 3.18 ao 10.18'!C28 -> 0 | D51: ='3.12 to 3.18 ao 10.18'!D28 -> 0 | E51: 0 | F51: 0
D53: =D51 -> 0 | E53: =E51 -> 0 | F53: =F51 -> 0
A54: 3.6 | B54: Cash and Cash Equivalents
C55: =C48 -> As at | D55: =D48 -> As at | E55: =E48 -> As at | F55: =F48 -> As at
C56: =C49 -> 15 Asadh 2083 | D56: =D49 -> 10 Magh 2082 | E56: =E49 -> 32 Ashadh 2082 | F56: =F49 -> 1 Shrawan 2081
B58: Cash in hand | D58: 0 | E58: 0 | F58: 0
B59: Siddhartha Bank, Ltd | C59: ='TB update upto 10.18'!K103 -> 804 | D59: ='TB update upto 10.18'!G103 -> 804 | E59: 40804 | F59: 67329
B60: Laxmi Sunrise Bank, Ltd | C60: ='TB update upto 10.18'!K102 -> 1614213.4 | D60: ='TB update upto 10.18'!G102 -> 11833.35 | E60: 850393 | F60: 0
C62: =SUM(C58:C60) -> 1615017.4 | D62: =SUM(D58:D60) -> 12637.35 | E62: =SUM(E58:E60) -> 891197 | F62: =SUM(F58:F60) -> 67329
A64: 3.7 | B64: Other current assets
C65: =C55 -> As at | D65: =D55 -> As at | E65: =E55 -> As at | F65: =F55 -> As at
C66: =C56 -> 15 Asadh 2083 | D66: =D56 -> 10 Magh 2082 | E66: =E56 -> 32 Ashadh 2082 | F66: =F56 -> 1 Shrawan 2081
B68: TDS Receivable | E68: 0
B69: VAT Receivable | E69: 0
B70: Prepayments | D70: 0 | E70: 0 | F70: 0
C72: =+SUM(C68:C71) -> 0 | D72: =+SUM(D68:D71) -> 0 | E72: =+SUM(E68:E71) -> 0 | F72: =+SUM(F68:F71) -> 0

Sheet 3.12 to 3.18 ao 03.15
A1: ='[5]3.3'!A1:E1 -> CELER MART PVT. LTD.
A3: Notes to Financial Statements
E5: Figures in NPR
A7: 3.12 | B7: Revenue from Operations
D8: Upto 15 Asadh 2083 | E8: ='SOI 10.18'!C7 -> Upto 18 Magh 2082 | F8: ='SOI 10.18'!D7 -> FY 2081-82
B9: Sale of goods | E9: 0 | F9: 0 | H9: 79597.18 | I9: 1182752.6
B10: Rendering of services
E12: =SUM(E9:E10) -> 0 | F12: =SUM(F9:F10) -> 0
A15: 3.13 | B15: Other income
D16: =D8 -> Upto 15 Asadh 2083 | E16: =E8 -> Upto 18 Magh 2082 | F16: =F8 -> FY 2081-82
B17: Commission and incentive | D17: 0 | E17: 0
B18: Discounts Received | D18: 0 | E18: 0 | F18: 0
B19: Exchange gain | D19: 0 | E19: 0
D21: =SUM(D17:D19) -> 0 | E21: =SUM(E17:E19) -> 0 | F21: =SUM(F17:F19) -> 0
A24: 3.14 | B24: Material Consumed Expenses
D25: =D8 -> Upto 15 Asadh 2083 | E25: =E8 -> Upto 18 Magh 2082 | F25: =F8 -> FY 2081-82
B26: Balance on 1 Shrawan | D26: =E28 -> 0 | E26: =F28 -> 0 | F26: 0
B27: Purchase during the period | D27: 0 | E27: 0 | F27: 0 | H27: 120571
B28: Less: Balance on 32 Ashadh | D28: 0 | E28: 0 | F28: 0
D30: =D26+D27-D28 -> 0 | E30: =E26+E27-E28 -> 0 | F30: =F26+F27-F28 -> 0
A32: 3.15 | B32: Direct Expenses
D33: =D25 -> Upto 15 Asadh 2083 | E33: =E66 -> Upto 18 Magh 2082 | F33: =F66 -> FY 2081-82
B34: Freight
B35: Customs Duty
B36: Other Direct Expenses
D38: =SUM(D34:D36) -> 0 | E38: =SUM(E34:E36) -> 0 | F38: =SUM(F34:F36) -> 0
A41: 3.16 | B41: Employee Benefit Expenses
D42: =D25 -> Upto 15 Asadh 2083 | E42: =E25 -> Upto 18 Magh 2082 | F42: =F25 -> FY 2081-82
B43: Salary & Allowances | D43: 0 | E43: 0 | F43: 0
B44: Dashain Expenses
B45: Staff Welfare
B46: PF & Gratuity expense | H46: =58914+49076 -> 107990
B47: Leave Expense
D50: =SUM(D43:D48) -> 0 | E50: =SUM(E43:E47) -> 0 | F50: =SUM(F43:F47) -> 0
B52: Key management personnel compensation
B53: Key management personnel are those persons having authority and responsibility for planning, directing and controlling the activities of the entity, including the directors.
E55: =E42 -> Upto 18 Magh 2082 | F55: =F42 -> FY 2081-82
B56: Salary
B57: Other long-term benefits
B58: Total pension and other post-employment benefit costs
B59: Compensations for loss of office
B60: Share based payment expense
E62: =SUM(E60:E60) -> 0 | F62: =SUM(F60:F60) -> 0
A65: 3.17 | B65: Administrative and Other Expenses
D66: =D42 -> Upto 15 Asadh 2083 | E66: =E55 -> Upto 18 Magh 2082 | F66: =F55 -> FY 2081-82
B67: Office Administrative and Running Expenses
B68: Audit Fee | D68: ='TB update upto 10.18'!F106 -> 0 | E68: ='TB update upto 10.18'!G106 -> 33900 | F68: 28250
B69: Miscellaneous Expenses | F69: 1132
B70: Electricity and water
B71: Fine & Penalty
B72: Insurance
B73: Lunch and Refreshment Expenses
B74: Telephone, Internet and Hosting Charges
B75: POS and Billing Expenses
B76: Office Expenses
B77: Printing & Stationary
B78: Rates & Taxes
B79: Rent Expenses
B80: Repair and maintenance
D81: =SUM(D68:D80) -> 0 | E81: =SUM(E68:E80) -> 33900 | F81: =SUM(F68:F80) -> 29382
A83: 3.18 | B83: Interest expenses
D84: =D33 -> Upto 15 Asadh 2083 | E84: =E33 -> Upto 18 Magh 2082 | F84: =F33 -> FY 2081-82
B85: Interest expense
D86: =SUM(D85:D85) -> 0 | E86: =SUM(E85:E85) -> 0 | F86: =SUM(F85:F85) -> 0

Sheet 3.19 to 3.20 ao.03.15
A1: ='[5]3.3'!A1:E1 -> CELER MART PVT. LTD.
A3: Notes to Financial Statements
D5: Figures in NPR
A7: 3.19 | B7: Other Expenses
C8: ='3.12 to 3.18 ao 10.18'!D8 -> Upto 18 Magh 2082 | D8: ='3.12 to 3.18 ao 10.18'!E8 -> FY 2081-82
B9: Loss on sale of investments | D9: 0
C12: =SUM(C10:C10) -> 0 | D12: =SUM(D9:D10) -> 0
A14: 3.2 | B14: Tax Expenses
C15: =C8 -> Upto 18 Magh 2082 | D15: =D8 -> FY 2081-82
B16: Tax on profit for the year | C16: ='Tax Computation 10.18'!C16 -> 0 | D16: ='SOI 10.18'!D21 -> 0
B17: Previous year tax | C17: 0 | D17: ='SOI 10.18'!D22 -> 0
C19: =SUM(C16:C17) -> 0 | D19: =SUM(D16:D17) -> 0
B21: Reconciliation of book profits and taxable profits
C22: =C15 -> Upto 18 Magh 2082 | D22: =D15 -> FY 2081-82
B23: Profit before tax as per books | C23: ='Tax Computation 10.18'!C3 -> -164485.25 | D23: ='SOI 10.18'!D19 -> -177096
B24: Add: Depreciation as per books | C24: ='Tax Computation 10.18'!C4 -> 130585.25 | D24: ='SOI 10.18'!D17 -> 147714
B25: Less: Depreciation as per tax | C25: ='Tax Computation 10.18'!C5 -> 0 | D25: =-D24 -> -147714
B26: Add: Disallowed repairs | C26: ='Tax Computation 10.18'!C6 -> 0 | D26: =-[5]Reco!F23 -> 0
B27: Add: Gratuity expense as per books | C27: ='Tax Computation 10.18'!C7 -> 0 | D27: =-[5]Reco!F15 -> 0
B28: Less: Gratuity paid | C28: ='Tax Computation 10.18'!C8 -> 0 | D28: =-[5]Reco!F14 -> 0
B29: Add: Leave expense as per books | C29: ='Tax Computation 10.18'!C9 -> 0 | D29: =-[5]Reco!F17 -> 0
B30: Less: Leave paid | C30: ='Tax Computation 10.18'!C10 -> 0 | D30: =-[5]Reco!F16 -> 0
B31: Less: Fair value gain on investments | C31: ='Tax Computation 10.18'!C11 -> 0 | D31: =-[5]Reco!F20 -> 0
B32: Add: Exchange loss/(gain) as per books | C32: ='Tax Computation 10.18'!C12 -> 0 | D32: =-[5]Reco!F22 -> 0
B33: Add: Realized exchange gain/(loss) | C33: ='Tax Computation 10.18'!C13 -> 0 | D33: =-[5]Reco!F21 -> 0
B34: Add: Difference in profit on sale of investment | C34: 0 | D34: 270000
B35: Add: Disallowed expenses | C35: ='Tax Computation 10.18'!C14 -> 0 | D35: 0
B36: Taxable profit | C36: =SUM(C23:C35) -> -33900 | D36: =SUM(D23:D35) -> 92904
B37: Income tax expense @ 25% | C37: =C36*25% -> -8475 | D37: =D36*25% -> 23226

Sheet 3.16 to 3.20 ao 03.15
A1: ='[5]3.3'!A1:E1 -> CELER MART PVT. LTD.
A3: Notes to Financial Statements
A5: Figures in NPR
A7: 3.21. Changes in Accounting Policies (If any)
A8: In the current financial year the company changes in accounting policies. This change has been accounted for by restating comparatives and adjusting the opening balance of retained earnings at 01 Shrawan 20XX. The changes in accounting policy, when applied consistently to 20X1 had the follwoing impact: On Opening Retained Earnings; On Net Profit.
A10: 3.18. Contingencies
A11: The company has contingent liabilities in respect of bank and other guarantees and other matters arising in the ordinary course of business. It is not anticipated that any material liablitites will arise from the contingent liabilities.
A13: 3.19. Related Party Transactions
A14: Identity of related parties
A15: The company is controlled by (name of the parent company) which owns xx percent of the company's shares. The remaining xx percent shares are widely held. The ultimate parent company of the company is (name of the ultimate parent company) incorporated in (name of the country)
A16: The following transactions were carried out with related parties (Give details)
A17: Directors of the company and their immediate relatives control xx percent of the voting shares of the company. Loans to directors amounting to NRs xx (20XX: NRs xx) are included in "other receivables". No interest is payable by the directors (for disclose if interest is payable)
A18: In additiona to their salaries, the company also provides non-cash benefits to directors and executive officers, and contributes to a post-employment defined benefit plan on their behalf.
... A27: Prior period errors are ommissions or misstatements in an entity's financial statements. Such ommissions may relate to one or more prior periods. Correction of an error is done by calculating the cumulative effect of the change on the financial statements of the period as if new method or estimate had always been used for all the affected prior years' financial statements. Sometimes, such changes may not be practicable, in such cases it is applied to the latest period possible by making corresponding adjustment to the opening balance of the period.

Sheet Annex 1&2 ao 03.15
A1: ='[5]3.3'!A1:E1 -> CELER MART PVT. LTD.
A3: Notes to Financial Statements
A5: Figures in NPR
A7: Significant Accounting Policies and Notes to Accounts
A9: 1. General information
A10: Give brief information about the legal status, registered address and nature of the business of the company.
A11: The financial statements were authorized to issue by …....... on …........
A13: 2. Significant Accounting Policies
A14: 2.1 Basis of preparation and accounting policies
A15: 2.1.1 Statement of Compliance
A16: These financial statements have been prepared in accordance with Nepal Accounting Standard for Micro Entities (NAS for MEs).
A17: 2.2.2 Basis of Measurement
A18: The financial statements have been prepared on the historical cost basis except investments held-for-trade is measured at fair value.
... A96: Interest expenses are recognized in the statement of income using accrual method.

Sheet Tax Computation 03.15
A1: CALCULATION OF TAXABLE INCOME
A3: Profit before tax as per books | C3: ='SOI 10.18'!C19 -> -164485.25
A4: Add: Depreciation as per books | C4: ='SOI 10.18'!C17 -> 130585.25
A5: Less: Depreciation as per tax | C5: 0
A6: Add: Disallowed repairs
A7: Add: Gratuity expense as per books
A8: Less: Gratuity paid
A9: Add: Leave expense as per books
A10: Less: Leave paid
A11: Less: Fair value gain on investments
A12: Add: Exchange loss as per books
A13: Add: Realized exchange gain
A14: Add: Disallowed expenses
A15: Taxable profit | C15: =SUM(C3:C14) -> -33900
A16: Income tax expense @ 25% | C16: 0

Sheet SOFP  03.32
A1: Magic Arun Hydropower Private Limitd
A2: Statement of Financial Position
A3: As at 32 Asadh 2083
F4: Restated
C5: As at | D5: As at | E5: As at | F5: As at
B6: Notes | C6: 32 Ashadh 2083 | D6: 18 Magh 2082 | E6: 32 Ashadh 2082 | F6: 1 Shrawan 2081
A7: ASSETS
A8: Non-Current Assets
A9: Property, Plant and Equipment | B9: 3.1 | C9: ='3.1 03.32'!I52 -> 473888.75 | D9: ='3.1 10.18'!I44 -> 473888.75 | E9: ='3.1 10.18'!I42 -> 604474 | F9: 0 | H9: =+E9+E11 -> 604474 | I9: =+C9+C11 -> 473888.75
A10: Project in Progress (WIP) | B10: 3.1 | C10: ='3.1 03.32'!C76 -> 17094931 | D10: ='3.1 10.18'!C70 -> 15814476 | E10: ='3.1 10.18'!F70 -> 12985641 | F10: ='3.1 10.18'!G50 -> 12985641
A11: Intangible Assets | B11: 3.2 | C11: ='[5]3.2'!E43 -> 0 | D11: ='[5]3.2'!F43 -> 0 | E11: ='[5]3.2'!E41 -> 0 | F11: ='[5]3.2'!E39 -> 0 | H11: 821236.13 | I11: =+'SOI 10.18'!C17 -> 130585.25
A12: Investments | B12: 3.3 | C12: ='[5]3.3'!C34 -> 0 | D12: ='[5]3.3'!D34 -> 0 | E12: ='[5]3.3'!D34 -> 0 | F12: ='[5]3.3'!E34 -> 0 | H12: =+H9-H11 -> -216762.13 | I12: =SUM(I9:I11) -> 604474
A13: Other Receivables | B13: 3.4 | C13: 0 | D13: 0 | E13: 0 | F13: 0 | I13: 2699634.6 | J13: =+I12-I13 -> -2095160.6
A14: Total Non-Current Assets | C14: =SUM(C9:C13) -> 17568820 | D14: =SUM(D9:D13) -> 16288365 | E14: =SUM(E9:E13) -> 13590115 | F14: =SUM(F9:F13) -> 12985641
A15: Current Assets
A16: Investments | B16: 3.3 | C16: ='[5]3.3'!C35 -> 0 | D16: ='[5]3.3'!D35 -> 0 | E16: ='[5]3.3'!D35 -> 0 | F16: ='[5]3.3'!E35 -> 0
A17: Account receivables | B17: 3.4 | C17: ='3.4 to 3.6 ao 03.32'!C36 -> 25069196 | D17: ='3.4 to 3.6 ao 10.18'!C32 -> 21010112 | E17: ='3.4 to 3.6 ao 10.18'!D32 -> 15311962 | F17: ='3.4 to 3.6 ao 10.18'!E32 -> 21788699 | H17: AS per Tally
A18: Inventories | B18: 3.5 | E18: =+'3.4 to 3.6 ao 10.18'!D47 -> 0 | F18: =+'3.4 to 3.6 ao 10.18'!E47 -> 0 | H18: 10922985
A19: Cash and cash equivalents | B19: 3.6 | C19: ='3.4 to 3.6 ao 03.32'!C62 -> 1615017.4 | D19: ='3.4 to 3.6 ao 10.18'!C58 -> 12637.35 | E19: ='3.4 to 3.6 ao 10.18'!D58 -> 891197 | F19: ='3.4 to 3.6 ao 10.18'!E58 -> 67329
A20: Other current assets | B20: 3.7 | C20: =+'3.4 to 3.6 ao 10.18'!C68 -> 0 | D20: =+'3.4 to 3.6 ao 10.18'!D68 -> 0 | E20: =+'3.4 to 3.6 ao 10.18'!D68 -> 0 | F20: =+'3.4 to 3.6 ao 10.18'!E68 -> 0
A21: Total Current Assets | C21: =SUM(C16:C20) -> 26684214 | D21: =SUM(D16:D20) -> 21022749 | E21: =SUM(E16:E20) -> 16203159 | F21: =SUM(F16:F20) -> 21856028
A22: Total Assets | C22: =C21+C14 -> 44253034 | D22: =D21+D14 -> 37311114 | E22: =E21+E14 -> 29793274 | F22: =F21+F14 -> 34841669
A23: EQUITY AND LIABILITIES
A24: Equity
A25: Share Capital | B25: 3.8 | C25: ='3.7 to 3.8 03.32'!D35 -> 44000000 | D25: ='3.7 to 3.8 10.18'!D31 -> 10290000 | E25: ='3.7 to 3.8 10.18'!E31 -> 12600000 | F25: 0 | H25: 6175421.8 | I25: =+H25+E27 -> 5801845.8
A26: Calls in Advance | C26: ='3.7 to 3.8 03.32'!D42 -> 500000 | D26: ='3.7 to 3.8 10.18'!D38 -> 22500000 | E26: 0 | F26: ='3.7 to 3.8 10.18'!E38 -> 0
A27: Retained Earnings | B27: 3.9 | C27: ='3.7 to 3.8 03.32'!D51 -> -571961.25 | D27: ='3.7 to 3.8 10.18'!D47 -> -538061.25 | E27: ='3.7 to 3.8 10.18'!E47 -> -373576 | F27: ='3.7 to 3.8 10.18'!E45 -> -196480 | H27: -6165121.9 | I27: =+H27-E27 -> -5791545.9
A28: Total Equity | C28: =SUM(C25:C27) -> 43928039 | D28: =SUM(D25:D27) -> 32251939 | E28: =SUM(E25:E27) -> 12226424 | F28: =SUM(F25:F27) -> -196480 | I28: 79025.12
A29: Liabilities
A30: Non-Current Liabilities
A31: Loans and Borrowings | B31: 3.10 | C31: ='3.9 to 3.11 AO 03.32'!C25 -> 40000 | D31: ='3.9 to 3.11 AO 10.18'!D25 -> 3870000 | E31: ='3.9 to 3.11 AO 10.18'!E25 -> 17165000 | F31: ='3.9 to 3.11 AO 10.18'!F25 -> 20756010
A32: Provision for Employee Benefits | C32: ='3.9 to 3.11 AO 10.18'!D36 -> 0 | D32: ='3.9 to 3.11 AO 10.18'!E36 -> 0 | E32: ='3.9 to 3.11 AO 10.18'!E36 -> 0 | F32: ='3.9 to 3.11 AO 10.18'!F36 -> 0
A33: Provisions | E33: 0 | F33: 0
A34: Total Non-Current Liabilities | C34: =SUM(C31:C33) -> 40000 | D34: =SUM(D31:D33) -> 3870000 | E34: =SUM(E31:E33) -> 17165000 | F34: =SUM(F31:F33) -> 20756010
A35: Current Liabilities
A36: Loans and Borrowings | B36: 3.10 | C36: ='3.9 to 3.11 AO 10.18'!D26 -> 0 | D36: ='3.9 to 3.11 AO 10.18'!E26 -> 0 | E36: ='3.9 to 3.11 AO 10.18'!E26 -> 0 | F36: ='3.9 to 3.11 AO 10.18'!F26 -> 0
A37: Trade and other payables | B37: 3.11 | C37: ='3.9 to 3.11 AO 03.32'!C50+'3.9 to 3.11 AO 03.32'!C63 -> 284995.2 | D37: ='3.9 to 3.11 AO 10.18'!D49+'3.9 to 3.11 AO 10.18'!D61 -> 1189175 | E37: ='3.9 to 3.11 AO 10.18'!E49 -> 401850 | F37: ='3.9 to 3.11 AO 10.18'!F49 -> 28498
A38: Income Tax Liability | C38: ='3.9 to 3.11 AO 10.18'!D69 -> 0 | D38: ='3.9 to 3.11 AO 10.18'!E69 -> 0 | E38: ='3.9 to 3.11 AO 10.18'!E69 -> 0 | F38: ='3.9 to 3.11 AO 10.18'!F69 -> 0
A39: Provision for Employee Benefits | C39: 0 | D39: 0 | E39: 0 | F39: 0
A40: Provisions | C40: 0 | D40: 0 | E40: 0 | F40: 0
A41: Total Current Liabilities | C41: =SUM(C36:C40) -> 284995.2 | D41: =SUM(D36:D40) -> 1189175 | E41: =SUM(E36:E40) -> 401850 | F41: =SUM(F36:F40) -> 28498
A42: Total Liabilities | C42: =C34+C41 -> 324995.2 | D42: =D34+D41 -> 5059175 | E42: =E34+E41 -> 17566850 | F42: =F34+F41 -> 20784508
A43: Total Equity and Liabilities | C43: =C42+C28 -> 44253034 | D43: =D42+D28 -> 37311114 | E43: =E42+E28 -> 29793274 | F43: =F42+F28 -> 20588028
C49: =B22-B43 -> 0 | D49: =C22-C43 -> 0 | E49: =E22-E43 -> 0.15 | F49: =F22-F43 -> 14253641

Sheet SOI 03.32
A1: ='SOFP 10.18'!A1 -> Magic Arun Hydropower Private Limitd
A3: Statement of Income
A4: For the Year Ended 32 Asadh 2083
E5: Figures in NPR
E6: Restated
A7: Particulars | B7: Notes | C7: Upto 32 Asadh 2083 | D7: Upto 10 Magh 2082 | E7: FY 2081-82
A8: Revenue from Operations | B8: 3.12 | D8: ='3.12 to 3.18 ao 10.18'!D12 -> 0 | E8: ='3.12 to 3.18 ao 10.18'!E12 -> 0 | H8: =D8-E8 -> 0 | I8: =H8/E8 -> #DIV/0!
A9: Interest Income | D9: 0 | E9: 0
A10: Other Income | B10: 3.13 | D10: ='3.12 to 3.18 ao 10.18'!D21 -> 0 | E10: ='3.12 to 3.18 ao 10.18'!E21 -> 0
A11: Total Income | D11: =SUM(D8:D10) -> 0 | E11: =SUM(E8:E10) -> 0
A12: Material Consumed Expenses | B12: 3.14 | D12: ='3.12 to 3.18 ao 10.18'!D30 -> 0 | E12: ='3.12 to 3.18 ao 10.18'!E30 -> 0 | F12: =(D12+D13)/D8 -> #DIV/0! | G12: =(E12+E13)/E8 -> #DIV/0! | H12: =D12-E12 -> 0 | I12: =H12/E12 -> #DIV/0!
A13: Direct Expenses | B13: 3.15 | D13: =+'3.12 to 3.18 ao 10.18'!D38 -> 0 | E13: =+'3.12 to 3.18 ao 10.18'!E38 -> 0 | H13: =D13-E13 -> 0 | I13: =H13/E13 -> #DIV/0!
A14: Employee Benefit Expenses | B14: 3.16 | D14: =+'3.12 to 3.18 ao 10.18'!D50 -> 0 | E14: =+'3.12 to 3.18 ao 10.18'!E50 -> 0 | H14: =D14-E14 -> 0 | I14: =H14/E14 -> #DIV/0!
A15: Administrative and Other Expenses | B15: 3.17 | D15: ='3.12 to 3.18 ao 10.18'!D81 -> 33900 | E15: ='3.12 to 3.18 ao 10.18'!E81 -> 29382 | H15: =D15-E15 -> 4518 | I15: =H15/E15 -> 0.15376761
A16: Interest Expenses | B16: 3.18 | D16: ='3.12 to 3.18 ao 10.18'!D86 -> 0 | E16: ='3.12 to 3.18 ao 10.18'!E86 -> 0 | H16: =D16-E16 -> 0 | I16: =H16/E16 -> #DIV/0!
A17: Depreciation and Amortization Expenses | B17: 3.1 & 3.2 | D17: 0 | E17: =+'3.1 10.18'!I28+'[5]3.2'!E30 -> 147714 | F17: 187078.71 | G17: =+E17-F17 -> -39364.71 | H17: =D17-E17 -> -147714 | I17: =H17/E17 -> -1
A18: Total Expenses | D18: =SUM(D12:D17) -> 33900 | E18: =SUM(E12:E17) -> 177096
A19: Profit Before Tax | D19: =D11-D18 -> -33900 | E19: =E11-E18 -> -177096 | F19: -2368782.9 | G19: =+E19-F19 -> 2191686.9
A20: Income Tax Expense | D20: =SUM(D21:D22) -> 0 | E20: =SUM(E21:E22) -> 0
A21: Current year | D21: 0 | E21: 0
A22: Previous years | D22: 0 | E22: 0
A23: Net Profit for the year | D23: =D19-D20 -> -33900 | E23: =E19-E20 -> -177096

Sheet SOCE 03.32
A1: ='SOI 10.18'!A1 -> Magic Arun Hydropower Private Limitd
A3: Statement of Changes in Equity
A4: ='SOI 10.18'!A4 -> For the Year Ended 18 Magh 2082
G6: Figures in NPR
A7: Particulars | C7: Share Capital | D7: Calls in Advance | E7: Retained Earnings | F7: Other Reserves | G7: Total
A8: Balance at 1 Shrawan 2081 | C8: =+'SOFP 10.18'!E25 -> 0 | D8: 7600000 | E8: =+'3.7 to 3.8 10.18'!E45 -> -196480 | F8: 0 | G8: =SUM(C8:F8) -> 7403520
A9: Restatements on transition to NAS for MEs | C9: 0 | D9: 0 | E9: =SUM([5]Reco!F5:F8) -> 0 | F9: 0 | G9: =SUM(C9:F9) -> 0
A10: Balance at 1 Shrawan 2081 (restated) | C10: =SUM(C8:C9) -> 0 | D10: =SUM(D8:D9) -> 7600000 | E10: =SUM(E8:E9) -> -196480 | F10: =SUM(F8:F9) -> 0 | G10: =SUM(G8:G9) -> 7403520 | H10: ='SOFP 10.18'!E28 -> -196480 | I10: =G10-H10 -> 7600000
A11: Profit for the year | C11: 0 | D11: 0 | E11: ='SOI 10.18'!D23 -> -177096 | F11: 0 | G11: =+SUM(C11:F11) -> -177096
A12: Issue of Shares | C12: 12600000 | D12: -7600000 | E12: 0 | F12: 0 | G12: =+SUM(C12:F12) -> 5000000
A13: Dividends to Shareholders | C13: 0 | D13: 0 | E13: 0 | F13: 0 | G13: =+SUM(C13:F13) -> 0
A14: Other Changes | C14: 0 | D14: 0 | E14: 0 | F14: 0 | G14: =+SUM(C14:F14) -> 0
A15: Balance at 32 Ashad 2082 | C15: =SUM(C10:C14) -> 12600000 | D15: =SUM(D10:D14) -> 0 | E15: =SUM(E10:E14) -> -373576 | F15: =SUM(F10:F14) -> 0 | G15: =SUM(G10:G14) -> 12226424 | H15: ='SOFP 10.18'!D28 -> 12226424 | I15: =G15-H15 -> 0
A16: Profit for the year | C16: 0 | D16: 0 | E16: =+'SOI 10.18'!C23 -> -164485.25 | F16: 0 | G16: =+SUM(C16:F16) -> -164485.25
A17: Issue of Shares | C17: 0 | D17: 0 | E17: 0 | F17: 0 | G17: =+SUM(C17:F17) -> 0
A18: Dividends to Shareholders | C18: 0 | D18: 0 | E18: 0 | F18: 0 | G18: =+SUM(C18:F18) -> 0
A19: Other Changes | C19: 0 | D19: 0 | E19: 0 | F19: 0 | G19: =+SUM(C19:F19) -> 0
A20: Balance at 32 Ashad 2083 | C20: =SUM(C15:C19) -> 12600000 | D20: =SUM(D15:D19) -> 0 | E20: =SUM(E15:E19) -> -538061.25 | F20: =SUM(F15:F19) -> 0 | G20: =SUM(G15:G19) -> 12061939 | H20: ='SOFP 10.18'!C28 -> 32251939 | I20: =G20-H20 -> -20190000

Sheet SCF 03.32
A1: ='SOCE 10.18'!A1 -> Magic Arun Hydropower Private Limitd
A3: Statement of Cash Flows
A4: ='SOCE 10.18'!A4 -> For the Year Ended 18 Magh 2082
C5: Figures in NPR
A6: Particulars | B6: ='SOI 10.18'!C7 -> Upto 18 Magh 2082 | C6: ='SOI 10.18'!D7 -> FY 2081-82
A7: CASH FLOWS FROM OPERATING ACTIVITIES
A8: Profit for the year | B8: ='SOI 10.18'!C19 -> -164485.25 | C8: ='SOI 10.18'!D19 -> -177096 | D8: =B8-'SOFP 10.18'!J27 -> -164485.25
A9: Adjustment for:
A10: Depreciation/Impairment on Property, Plant and Equipment | B10: ='SOI 10.18'!C17 -> 130585.25 | C10: ='SOI 10.18'!D17 -> 147714
A11: Interest Income
A12: Interest Expense | B12: ='SOI 10.18'!C16 -> 0 | C12: ='SOI 10.18'!D16 -> 0
A13: Loss/(gain) on sale of Property, Plant and Equipment
A14: Income Tax expense charged to statement of income
A15: Working Capital Adjustments
A16: Decrease/(Increase) in trade and other receivables | B16: ='SOFP 10.18'!J17+'SOFP 10.18'!J20 -> 0 | C16: ='SOFP 10.18'!E17-'SOFP 10.18'!D17 -> 6476737
A17: Decrease/(Increase) in Inventories | B17: ='SOFP 10.18'!J18 -> 0 | C17: ='SOFP 10.18'!K18 -> 0
A18: Increase/(Decrease) in trade and other payables | B18: ='SOFP 10.18'!J37 -> 0 | C18: ='SOFP 10.18'!K37 -> 0
A19: Increase/(Decrease) Loan and Borrowings | C19: ='SOFP 10.18'!D31-'SOFP 10.18'!E31 -> -3591010
A20: Increase/(Decrease) in other liabilities | C20: 0
A21: Cash Generated from Operations | B21: =SUM(B8:B20) -> -33900 | C21: =SUM(C8:C20) -> 2856345
A22: Interest paid | C22: 0
A23: Income tax paid | C23: 0
A24: NET CASH FLOWS FROM OPERATING ACTIVITIES (A) | B24: =SUM(B21:B23) -> -33900 | C24: =SUM(C21:C23) -> 2856345
A25: CASH FLOW FROM INVESTING ACTIVITIES
A26: Proceeds from sale of PPE, Investments/Financial Assets | C26: =-'3.1 10.18'!I8 -> 0
A27: Increase in project WIP | B27: ='SOFP 10.18'!J12 -> 0 | C27: =-'SOFP 10.18'!D10+'SOFP 10.18'!E10 -> 0
A28: Acquisition of Property, Plant and Equipment | B28: =-'3.1 10.18'!I15-'[5]3.2'!E17 -> 0 | C28: =-'3.1 10.18'!I10-'[5]3.2'!E12 -> -752188
A29: NET CASH FLOWS FROM INVESTING ACTIVITIES (B) | B29: =SUM(B25:B28) -> 0 | C29: =SUM(C25:C28) -> -752188
A30: CASH FLOW FROM FINANCING ACTIVITIES
A31: Proceeds from the issue of Equity and Preference Share | C31: ='SOFP 10.18'!D25-'SOFP 10.18'!E26 -> 12600000
A32: Proceeds from loans and borrowings borrowings | B32: ='SOFP 10.18'!J36 -> 0 | C32: ='SOFP 10.18'!K36 -> 0
A33: Interest Expenses | B33: =-B12 -> 0 | C33: =-C12 -> 0
A34: Dividend Paid
A35: NET CASH FLOW FROM FINANCING ACTIVITIES (C) | B35: =SUM(B31:B34) -> 0 | C35: =SUM(C31:C34) -> 12600000
A36: Net Increase in Cash and Cash Equivalents | B36: =B24+B29+B35 -> -33900 | C36: =C24+C29+C35 -> 14704157
A37: Cash and Cash Equivalents at the beginning | B37: ='SOFP 10.18'!D19 -> 891197 | C37: ='SOFP 10.18'!E19 -> 67329
A38: Exchange gains/(losses) in cash and cash equivalents
A39: Cash and Cash Equivalents at the end | B39: =B36+B37 -> 857297 | C39: =C36+C37 -> 14771486
B40: ='3.4 to 3.6 ao 10.18'!C58 -> 12637.35 | C40: ='3.4 to 3.6 ao 10.18'!D58 -> 891197
B41: =B39-B40 -> 844659.65 | C41: =C39-C40 -> 13880289

Sheet 3.1 03.32
A1: ='SOFP 10.18'!A1 -> Magic Arun Hydropower Private Limitd
A2: Notes to Financial Statements
I3: Figures in NPR
A4: 3.1 | B4: Property, Plant and Equipment
C5: Furniture & Fixtures | D5: Computer | E5: Office Equipments | F5: Vehicles | G5: Plant and Machinery | H5: Office Furnishing | I5: Total
B6: Cost
B8: Balance at 1 Shrawan 2081 | C8: 0 | D8: 0 | E8: 0 | F8: 0 | G8: 0 | I8: =SUM(C8:G8) -> 0
I9: =SUM(C9:G9) -> 0
B10: Additions | C10: 532188 | D10: 0 | E10: 0 | F10: 220000 | G10: 0 | I10: =SUM(C10:G10) -> 752188
B11: Disposals | C11: 0 | D11: 0 | E11: 0 | F11: 0 | G11: 0 | I11: =SUM(C11:G11) -> 0
B13: Balance at 32 Ashadh 2082 | C13: =SUM(C8:C11) -> 532188 | D13: =SUM(D8:D11) -> 0 | E13: =SUM(E8:E11) -> 0 | F13: =SUM(F8:F11) -> 220000 | G13: =SUM(G8:G11) -> 0 | I13: =SUM(I8:I11) -> 752188
B15: Additions | C15: 0 | E15: 0 | G15: 0 | I15: =SUM(C15:G15) -> 0
B16: Disposals | C16: 0 | D16: 0 | E16: 0 | F16: 0 | G16: 0 | I16: =SUM(C16:G16) -> 0
B18: Balance at 18 Magh 2082 | C18: =SUM(C13:C16) -> 532188 | D18: =SUM(D13:D16) -> 0 | E18: =SUM(E13:E16) -> 0 | F18: =SUM(F13:F16) -> 220000 | G18: =SUM(G13:G16) -> 0 | H18: =SUM(H13:H16) -> 0 | I18: =SUM(C18:G18) -> 752188
B20: Additions
B21: Disposals
B23: Balance at 32 Asadh 2083 | C23: =SUM(C18:C21) -> 532188 | D23: =SUM(D18:D21) -> 0 | E23: =SUM(E18:E21) -> 0 | F23: =SUM(F18:F21) -> 220000 | G23: =SUM(G18:G21) -> 0 | H23: =SUM(H18:H21) -> 0 | I23: =SUM(I18:I21) -> 752188
B25: Accumulated depreciation
B27: =B8 -> Balance at 1 Shrawan 2081 | C27: 0 | D27: 0 | E27: 0 | F27: 0 | G27: 0 | I27: =SUM(C27:G27) -> 0
B29: Charge for the year | C29: 133047 | D29: 0 | E29: 0 | F29: 14667 | G29: 0 | H29: 0 | I29: =SUM(C29:H29) -> 147714
B30: Disposals
B32: =B13 -> Balance at 32 Ashadh 2082 | C32: =SUM(C27:C30) -> 133047 | D32: =SUM(D27:D30) -> 0 | E32: =SUM(E27:E30) -> 0 | F32: =SUM(F27:F30) -> 14667 | G32: =SUM(G27:G30) -> 0 | H32: =SUM(H27:H30) -> 0 | I32: =SUM(I27:I30) -> 147714
B34: Charge for the year | C34: =(C13-C29)*25% -> 99785.25 | E34: 0 | F34: 30800 | G34: 0 | H34: =(H18-H32)*15% -> 0 | I34: =SUM(C34:G34) -> 130585.25
B35: Disposals
B37: =B18 -> Balance at 18 Magh 2082 | C37: =C34+C32 -> 232832.25 | D37: =SUM(D32:D35) -> 0 | E37: =SUM(E32:E35) -> 0 | F37: =F34+F32 -> 45467 | G37: =SUM(G32:G35) -> 0 | H37: =SUM(H32:H35) -> 0 | I37: =SUM(C37:G37) -> 278299.25
B39: Charge for the year
B40: Disposals
B42: Balance at 32 Asadh 2083 | C42: =C39+C37 -> 232832.25 | D42: =D39+D37 -> 0 | E42: =E39+E37 -> 0 | F42: =F39+F37 -> 45467 | G42: =G39+G37 -> 0 | H42: =H39+H37 -> 0 | I42: =I39+I37 -> 278299.25
B44: Net Book Value
B46: As at 1st Shrawan 2081 | C46: =C8-C27 -> 0 | D46: =D8-D27 -> 0 | E46: =E8-E27 -> 0 | F46: =F8-F27 -> 0 | G46: =G8-G27 -> 0 | H46: =H8-H27 -> 0 | I46: =I8-I27 -> 0
B48: As at 32nd Ashad 2082 | C48: =C13-C32 -> 399141 | D48: =D13-D32 -> 0 | E48: =E13-E32 -> 0 | F48: =F13-F32 -> 205333 | G48: =G13-G32 -> 0 | H48: =H13-H32 -> 0 | I48: =SUM(C48:G48) -> 604474
B50: As at 18 Magh 2082 | C50: =C18-C37 -> 299355.75 | D50: =D18-D37 -> 0 | E50: =E18-E37 -> 0 | F50: =F18-F37 -> 174533 | G50: =G18-G37 -> 0 | H50: =H18-H37 -> 0 | I50: =SUM(C50:G50) -> 473888.75
B52: As at 32 Asadh 2083 | C52: =C23-C42 -> 299355.75 | D52: =D23-D42 -> 0 | E52: =E23-E42 -> 0 | F52: =F23-F42 -> 174533 | G52: =G23-G42 -> 0 | H52: =H23-H42 -> 0 | I52: =I23-I42 -> 473888.75
B54: 3.1.2 Project in Progress (WIP)
B55: Particulars | C55: As on 10 Magh 2082 | E55: During the period | G55: 2080.081
B56: Project Initial Expenses | C56: =C76 -> 17094931 | E56: =D76 -> 1280455.2 | G56: =F76 -> 15814476
C58: As on 32 Asadh 2083 | D58: During the period | F58: As on 10 Magh 2082
B59: Survey License Fee | C59: =F59+D59 -> 8000000 | D59: ='TB update upto 10.18'!I59 -> 0 | F59: ='TB update upto 10.18'!G59 -> 8000000
B60: License Renewal Fee | C60: =F60+D60 -> 2000000 | D60: ='TB update upto 10.18'!I60 -> 0 | F60: ='TB update upto 10.18'!G60 -> 2000000
B61: PPA Fee | C61: =F61+D61 -> 300000 | D61: ='TB update upto 10.18'!I61 -> 0 | F61: ='TB update upto 10.18'!G61 -> 300000
B62: Grid Impat Study Expenses (NEA) | C62: =F62+D62 -> 102000 | D62: ='TB update upto 10.18'!I62 -> 0 | F62: ='TB update upto 10.18'!G62 -> 102000
B63: Bank Charges | C63: =F63+D63 -> 275027.15 | D63: ='TB update upto 10.18'!I63 -> 370 | F63: ='TB update upto 10.18'!G63 -> 274657.15
B64: ERC Approval | C64: =F64+D64 -> 197000 | D64: ='TB update upto 10.18'!I64 -> 0 | F64: ='TB update upto 10.18'!G64 -> 197000
B65: Salary Expenses | C65: =F65+D65 -> 3917020.2 | D65: ='TB update upto 10.18'!I65 -> 927020.2 | F65: ='TB update upto 10.18'!G65 -> 2990000
B66: Travelling & Site Visit Expenses | C66: =F66+D66 -> 808129 | D66: ='TB update upto 10.18'!I66 -> 0 | F66: ='TB update upto 10.18'!G66 -> 808129
B67: Labour Wages | C67: =F67+D67 -> 660000 | D67: ='TB update upto 10.18'!I67 -> 0 | F67: ='TB update upto 10.18'!G67 -> 660000
B68: Office Rent | C68: =F68+D68 -> 240000 | D68: ='TB update upto 10.18'!I68 -> 0 | F68: ='TB update upto 10.18'!G68 -> 240000
B69: Repair & Maintenance Expenses | C69: =F69+D69 -> 37700 | D69: ='TB update upto 10.18'!I69 -> 0 | F69: ='TB update upto 10.18'!G69 -> 37700
B70: Printing & Stationary Expenses | C70: =F70+D70 -> 60880 | D70: ='TB update upto 10.18'!I70 -> 11565 | F70: ='TB update upto 10.18'!G70 -> 49315
... B75: TADA | C75: =F75+D75 -> 0 | D75: ='TB update upto 10.18'!I75 -> 0 | F75: ='TB update upto 10.18'!G75 -> 0
C76: =SUM(C59:C75) -> 17094931 | D76: =SUM(D59:D75) -> 1280455.2 | F76: =SUM(F59:F75) -> 15814476

Sheet 3.9 to 3.11 AO 03.32
A1: ='[5]3.3'!A1:E1 -> CELER MART PVT. LTD.
A3: Notes to Financial Statements
F5: Figures in NPR
A7: 3.9 | B7: Loans and Borrowings
C8: As at | D8: ='3.7 to 3.8 10.18'!D8 -> As at | E8: ='3.7 to 3.8 10.18'!E8 -> As at | F8: =E8 -> As at
C9: 32 Asadh 2083 | D9: ='SOFP 10.18'!C6 -> 18 Magh 2082 | E9: ='SOFP 10.18'!D6 -> 32 Ashadh 2082 | F9: ='SOFP 10.18'!E6 -> 1 Shrawan 2081
B10: Total Loans and Borrowings
B11: Bank Overdraft | D11: 0 | E11: 0 | F11: 0
B12: Short Term Payable | D12: 0 | E12: 0 | F12: 20756010
B13: Basudev Dhiktta | D13: ='TB update upto 10.18'!H49 -> 2200000 | E13: 2200000
B14: Bhadra Ventures Pvt.Ltd | D14: 0 | E14: 1300000
B15: Eak Raj Khatiwada | E15: 12000000
B16: Naresh Poudel-Payable | C16: ='TB update upto 10.18'!L40 -> 40000 | D16: ='TB update upto 10.18'!H40 -> 390000 | E16: 365000
B17: Sandipa Thapa | D17: ='TB update upto 10.18'!H41 -> 200000 | E17: 200000
B18: Shyam Prasad Kuikel | D18: ='TB update upto 10.18'!H42 -> 500000 | E18: 500000
B19: Ellite Wire Pvt.Ltd | D19: ='TB update upto 10.18'!H47 -> 380000 | E19: 600000
B20: Ellite Powers Pvt.Ltd | D20: ='TB update upto 10.18'!H89 -> 200000 | E20: 0
C23: =SUM(C11:C20) -> 40000 | D23: =SUM(D11:D20) -> 3870000 | E23: =SUM(E11:E20) -> 17165000 | F23: =SUM(F11:F19) -> 20756010
B25: Non-current loans and borrowings | C25: =C23-C26 -> 40000 | D25: =D23-D26 -> 3870000 | E25: =E23-E26 -> 17165000 | F25: =F23-F26 -> 20756010
B26: Current loans and borrowings | C26: =C11 -> 0 | D26: =D11 -> 0 | E26: =E11 -> 0 | F26: =F11 -> 0
A29: 3.10 | B29: Provision for Employee Benefits
C31: =C8 -> As at | D31: =D8 -> As at | E31: =E8 -> As at | F31: =F8 -> As at
C32: =C9 -> 15 Asadh 2083 | D32: =D9 -> 18 Magh 2082 | E32: =E9 -> 32 Ashadh 2082 | F32: =F9 -> 1 Shrawan 2081
B34: Provision for Gratuity | D34: 0 | E34: 0
B35: Provision for Leave benefits
C36: =SUM(C34:C35) -> 0 | D36: =SUM(D34:D35) -> 0 | E36: =SUM(E34:E35) -> 0 | F36: =SUM(F34:F35) -> 0
A38: 3.11 | B38: Trade and other payables
C39: =C31 -> As at | D39: =D31 -> As at | E39: =E31 -> As at | F39: =F31 -> As at
C40: =C32 -> 15 Asadh 2083 | D40: =D32 -> 18 Magh 2082 | E40: =E32 -> 32 Ashadh 2082 | F40: =F32 -> 1 Shrawan 2081
B41: TDS on Audit Fee | C41: ='TB update upto 10.18'!L26 -> 900 | D41: ='TB update upto 10.18'!H26 -> 825 | E41: 375 | F41: 375
B42: TDS on Salary (SST) | C42: ='TB update upto 10.18'!L27 -> 13420.202 | D42: ='TB update upto 10.18'!H27 -> 29900 | E42: 25750 | F42: 248
B43: TDS on Office Rent | D43: ='TB update upto 10.18'!H30 -> 24000 | E43: 24000 | F43: 0 | G43: Net of TDS
B44: TDS on Labour Wages | D44: ='TB update upto 10.18'!H31 -> 6600 | E44: 6600 | F44: 0
B45: Audit Fee Payable | C45: ='TB update upto 10.18'!L33 -> 66900 | D45: ='TB update upto 10.18'!H33 -> 61325 | E45: 27875 | F45: 27875
B46: Staff Payable | D46: ='TB update upto 10.18'!H37 -> 222750 | E46: 222750 | F46: 0
B47: Office Rent Payable | D47: ='TB update upto 10.18'!H38 -> 94500 | E47: 94500 | F47: 0
B48: TDS on Meeting Fee | C48: ='TB update upto 10.18'!L28 -> 7275 | D48: ='TB update upto 10.18'!H28 -> 7275
B49: TDS Pvt. Ltd. | C49: ='TB update upto 10.18'!L29 -> 4500
C50: =SUM(C41:C49) -> 92995.202 | D50: =SUM(D41:D49) -> 447175 | E50: =SUM(E41:E47) -> 401850 | F50: =SUM(F41:F47) -> 28498
B51: Other payable
B52: =[5]Sheet1!A8 -> Sita Karki | C52: ='TB update upto 10.18'!L44 -> 0 | D52: ='TB update upto 10.18'!H44 -> 700000
B53: =[5]Sheet1!A19 -> Mamata Acharya - Payable
B54: Samyak Consulting Engineering Pvt. Ltd. | E54: 0
B55: Baba Gas | C55: ='TB update upto 10.18'!L46 -> 2000 | D55: ='TB update upto 10.18'!H46 -> 2000
B56: Kamal Karki - Site Visit | E56: 0
B57: Naresh Poudel - Site Visit | E57: 0
B58: Buddha Law Assocites Pvt Ltd
B59: Bhadra Venture
B60: Mohan Bista - Auditor (SST, TDS, Audit Fee)
B61: Shiva Ram Bhandari - Other Advance | D61: ='TB update upto 10.18'!H107 -> 40000
B62: Kamal Karki advance | C62: ='TB update upto 10.18'!L98 -> 190000
C63: =SUM(C52:C62) -> 192000 | D63: =SUM(D52:D62) -> 742000
A66: 3.12 | B66: Income tax liability
D67: =D39 -> As at | E67: =E39 -> As at | F67: =F39 -> As at
D68: =D40 -> 18 Magh 2082 | E68: =E40 -> 32 Ashadh 2082 | F68: =F40 -> 1 Shrawan 2081
B69: Provision for tax | D69: 0 | E69: 0 | F69: 0
D71: =SUM(D69:D70) -> 0 | E71: =SUM(E69:E70) -> 0 | F71: =SUM(F69:F70) -> 0

Sheet 3.7 to 3.8 03.32
A1: ='[5]3.3'!A1:E1 -> CELER MART PVT. LTD.
B3: Notes to Financial Statements
F5: Figures in NPR
A7: 3.7 | B7: Share Capital
D8: As at | E8: ='3.4 to 3.6 ao 10.18'!D6 -> As at | F8: ='3.4 to 3.6 ao 10.18'!E6 -> As at
D9: 32 Asadh 2083 | E9: ='3.4 to 3.6 ao 10.18'!C7 -> 18 Magh 2082 | F9: ='3.4 to 3.6 ao 10.18'!D7 -> 32 Ashadh 2082
B11: Authorized
B12: 260,000 ordinary shares of NPR 100 each | E12: 26000000 | F12: =E12 -> 26000000
B14: Ordinary Shares Issued and Fully Paid
B15: Ordinary shares of Rs. 100 each
E16: Ordinary | F16: Ordinary
E17: share | F17: share capital
D18: As at | E18: As at | F18: As at
D19: 32 Asadh 2083 | E19: 10 Magh 2082 | F19: 32 Ashadh 2082
B20: Paid up Share capital
B21: Bijay Bista | F21: 3200000
B22: Rajendra Karki | E22: ='TB update upto 10.18'!H10 -> 890000 | F22: 3200000
B23: Kanchan Sherpa | F23: 200000
B24: Lilamani Pathak | F24: 1000000
B25: Bhadra Ventures Pvt.LTD | F25: 5000000
B26: Shivaram Bhandari | E26: ='TB update upto 10.18'!H15 -> 5000000
B27: Indu Bhandari Basnet | E27: ='TB update upto 10.18'!H16 -> 2510000
B28: Nabaraj Tiwari | E28: ='TB update upto 10.18'!H17 -> 1260000
B29: Murali Adhikari | E29: ='TB update upto 10.18'!H18 -> 630000
B30: I.B. Multipurpose Pvt Ltd | D30: ='TB update upto 10.18'!L6 -> 15000000
B31: Happy Nepal Investment | D31: ='TB update upto 10.18'!L7 -> 25000000
B32: Indra Bahadur Bista | D32: ='TB update upto 10.18'!L8 -> 1500000
B33: Tanka Prasad Pandey | D33: ='TB update upto 10.18'!L9 -> 2500000
B35: Total | D35: =SUM(D30:D34) -> 44000000 | E35: =SUM(E21:E34) -> 10290000 | F35: =SUM(F21:F34) -> 12600000
D36: As at | E36: As at | F36: As at
B37: Share Advance | D37: 32 Asadh 2083 | E37: 10 Magh 2082 | F37: 32 Ashadh 2082
B38: Shiv Ram Bhandari | D38: ='TB update upto 10.18'!L20 -> 0 | E38: ='TB update upto 10.18'!H20 -> 20000000
B39: Bond Construction | D39: ='TB update upto 10.18'!L21 -> 0 | E39: ='TB update upto 10.18'!H21 -> 2000000
B40: Uttam Kumar | D40: ='TB update upto 10.18'!L22 -> 500000 | E40: ='TB update upto 10.18'!H22 -> 500000
B41: Lilamani Pathak
B42: Total | D42: =SUM(D38:D41) -> 500000 | E42: =SUM(E38:E41) -> 22500000 | F42: =SUM(F38:F41) -> 0
A44: 3.8 | B44: Retained Earnings
D46: As at | E46: =E8 -> As at | F46: =F8 -> As at
D47: 32 Asadh 2083 | E47: ='SOFP 10.18'!C6 -> 18 Magh 2082 | F47: ='SOFP 10.18'!D6 -> 32 Ashadh 2082 | H47: New | K47: Old
B49: Opening balance | D49: =+E51 -> -538061.25 | E49: =+F51 -> -373576 | F49: -196480 | H49: =+F49 -> -196480 | K49: =+F49 -> -196480
B50: Net profit for the year | D50: ='SOI 03.32'!D23 -> -33900 | E50: ='SOI 10.18'!C23 -> -164485.25 | F50: ='SOI 10.18'!D23 -> -177096 | H50: -2368782.9 | K50: =+'SOI 10.18'!E19 -> -2368782.9
B51: Closing balance | D51: =SUM(D49:D50) -> -571961.25 | E51: =SUM(E49:E50) -> -538061.25 | F51: =SUM(F49:F50) -> -373576 | H51: =SUM(H49:H50) -> -2565262.9 | I51: As per FS | K51: =+K49+K50 -> -2565262.9
H52: =+#REF!+#REF! -> #REF! | I52: AS per Tally
F53: =+F51-H51 -> 2191686.9 | H53: =+H51+H52 -> #REF!

Sheet 3.4 to 3.6 ao 03.32
A1: ='SOFP 10.18'!A1 -> Magic Arun Hydropower Private Limitd
A2: Notes to Financial Statements
D4: Figures in NPR
A6: 3.4 | B6: Account Receivables | C6: As at | D6: ='[5]3.3'!C29 -> As at | E6: ='[5]3.3'!D29 -> As at | F6: ='[5]3.3'!E29 -> As at
C7: 32 Asadh 2083 | D7: 10 Magh 2082 | E7: ='[5]3.3'!D30 -> 32 Ashadh 2082 | F7: ='[5]3.3'!E30 -> 1 Shrawan 2081
B9: Account Receivables
B10: Advance for Road Construction | D10: 0 | E10: 0 | F10: 1000000
B11: Advance for Land Purchase | D11: 0 | E11: 0 | F11: 20300000
B12: Site Advance | D12: 0 | E12: 0 | F12: 488699
B13: Other Receivables
B14: Bijaya Bista | C14: ='TB update upto 10.18'!K78 -> 5000000 | D14: ='TB update upto 10.18'!G78 -> 5000000 | E14: 4000000
B15: Ellite Powers Pvt.Ltd | C15: 0 | D15: 0 | E15: 3000000
B16: Environment Partners Pvt.Ltd | C16: ='TB update upto 10.18'!K94 -> 254500 | D16: ='TB update upto 10.18'!G94 -> 250000 | E16: 250000
B17: Rajendra Karki- Advance | C17: ='TB update upto 10.18'!K80+'TB update upto 10.18'!K10 -> 4136712 | D17: ='TB update upto 10.18'!G80 -> 5563462 | E17: 5563462
B18: Slesha Engineering Consultancy Pvt.Ltd | C18: ='TB update upto 10.18'!K93 -> 3900000 | D18: ='TB update upto 10.18'!G93 -> 2900000 | E18: 2200000 | F18: 0
B19: Ellite Steel Pvt.ltd | C19: ='TB update upto 10.18'!K84 -> 0 | D19: ='TB update upto 10.18'!G84 -> 260000
B20: Buddha Law Associates | C20: ='TB update upto 10.18'!K96 -> 0 | D20: ='TB update upto 10.18'!G96 -> 75000
B21: Other Receivables | C21: ='TB update upto 10.18'!K95+'TB update upto 10.18'!K45 -> 2210 | D21: ='TB update upto 10.18'!G95+'TB update upto 10.18'!G45 -> 133525
B22: Samyak Consulting Pvt. Ltd. | C22: ='TB update upto 10.18'!K92 -> 529624.5 | D22: ='TB update upto 10.18'!G92 -> 529624.5
B23: Bahadur Ventures Pvt. Ltd. | C23: ='TB update upto 10.18'!K50 -> 0 | D23: ='TB update upto 10.18'!G50 -> 5000000
B24: Pramod Neupane | C24: ='TB update upto 10.18'!K79 -> 147650 | D24: ='TB update upto 10.18'!G79 -> 500000
B25: kanchan Sherpa | C25: ='TB update upto 10.18'!K90 -> 0 | D25: ='TB update upto 10.18'!G90 -> 500000
B26: Uttam Karki | C26: ='TB update upto 10.18'!K43 -> 500000
B27: Hem raj Bhattarai | C27: ='TB update upto 10.18'!K81 -> 1800000 | D27: ='TB update upto 10.18'!G81 -> 0
B28: Ambe Hydropower pvt. Ltd | C28: ='TB update upto 10.18'!K82 -> 2000000 | D28: 0
B29: Bidhya Rai | C29: ='TB update upto 10.18'!K83 -> 6500000 | D29: ='TB update upto 10.18'!G83 -> 0
B31: Deposit
B32: Cash Margin-PB-NEA | C32: ='TB update upto 10.18'!K100 -> 298500 | D32: ='TB update upto 10.18'!G100 -> 298500 | E32: 298500 | F32: 0
C33: =+C12+SUM(C14:C32) -> 25069196 | D33: =+D12+SUM(D14:D32) -> 21010112 | E33: =SUM(E10:E32) -> 15311962 | F33: =SUM(F10:F18) -> 21788699
B35: Non-current portion | C35: 0 | D35: 0 | E35: 0 | F35: 0
B36: Current portion | C36: =C33 -> 25069196 | D36: =D33 -> 21010112 | E36: =E33 -> 15311962 | F36: =F33 -> 21788699
B38: Provision for impairment of trade receivables: | E38: FY | F38: FY
E39: 2081-82 | F39: 2080-81
B40: Balance at the beginning of the year | E40: 0 | F40: 0
B41: Provided during the year | E41: 0 | F41: 0
B42: Written off during the year | E42: 0 | F42: 0
B43: Unused provisions reversed | E43: 0 | F43: 0
B45: Balance at the end of the year | E45: =SUM(E40:E43) -> 0 | F45: =SUM(F40:F43) -> 0
A47: 3.5 | B47: Inventories
C48: =C6 -> As at | D48: =D6 -> As at | E48: =E6 -> As at | F48: =F6 -> As at
C49: =C7 -> 15 Asadh 2083 | D49: =D7 -> 10 Magh 2082 | E49: =E7 -> 32 Ashadh 2082 | F49: =F7 -> 1 Shrawan 2081
B51: Inventories of goods held for resale | C51: ='3.12 to 3.18 ao 10.18'!C28 -> 0 | D51: ='3.12 to 3.18 ao 10.18'!D28 -> 0 | E51: 0 | F51: 0
D53: =D51 -> 0 | E53: =E51 -> 0 | F53: =F51 -> 0
A54: 3.6 | B54: Cash and Cash Equivalents
C55: =C48 -> As at | D55: =D48 -> As at | E55: =E48 -> As at | F55: =F48 -> As at
C56: =C49 -> 15 Asadh 2083 | D56: =D49 -> 10 Magh 2082 | E56: =E49 -> 32 Ashadh 2082 | F56: =F49 -> 1 Shrawan 2081
B58: Cash in hand | D58: 0 | E58: 0 | F58: 0
B59: Siddhartha Bank, Ltd | C59: ='TB update upto 10.18'!K103 -> 804 | D59: ='TB update upto 10.18'!G103 -> 804 | E59: 40804 | F59: 67329
B60: Laxmi Sunrise Bank, Ltd | C60: ='TB update upto 10.18'!K102 -> 1614213.4 | D60: ='TB update upto 10.18'!G102 -> 11833.35 | E60: 850393 | F60: 0
C62: =SUM(C58:C60) -> 1615017.4 | D62: =SUM(D58:D60) -> 12637.35 | E62: =SUM(E58:E60) -> 891197 | F62: =SUM(F58:F60) -> 67329
A64: 3.7 | B64: Other current assets
C65: =C55 -> As at | D65: =D55 -> As at | E65: =E55 -> As at | F65: =F55 -> As at
C66: =C56 -> 15 Asadh 2083 | D66: =D56 -> 10 Magh 2082 | E66: =E56 -> 32 Ashadh 2082 | F66: =F56 -> 1 Shrawan 2081
B68: TDS Receivable | E68: 0
B69: VAT Receivable | E69: 0
B70: Prepayments | D70: 0 | E70: 0 | F70: 0
C72: =+SUM(C68:C71) -> 0 | D72: =+SUM(D68:D71) -> 0 | E72: =+SUM(E68:E71) -> 0 | F72: =+SUM(F68:F71) -> 0

Sheet 3.12 to 3.18 ao 03.32
A1: ='[5]3.3'!A1:E1 -> CELER MART PVT. LTD.
A3: Notes to Financial Statements
E5: Figures in NPR
A7: 3.12 | B7: Revenue from Operations
D8: Upto 32 Asadh 2083 | E8: ='SOI 10.18'!C7 -> Upto 18 Magh 2082 | F8: ='SOI 10.18'!D7 -> FY 2081-82
B9: Sale of goods | E9: 0 | F9: 0 | H9: 79597.18 | I9: 1182752.6
B10: Rendering of services
E12: =SUM(E9:E10) -> 0 | F12: =SUM(F9:F10) -> 0
A15: 3.13 | B15: Other income
D16: =D8 -> Upto 15 Asadh 2083 | E16: =E8 -> Upto 18 Magh 2082 | F16: =F8 -> FY 2081-82
B17: Commission and incentive | D17: 0 | E17: 0
B18: Discounts Received | D18: 0 | E18: 0 | F18: 0
B19: Exchange gain | D19: 0 | E19: 0
D21: =SUM(D17:D19) -> 0 | E21: =SUM(E17:E19) -> 0 | F21: =SUM(F17:F19) -> 0
A24: 3.14 | B24: Material Consumed Expenses
D25: =D8 -> Upto 15 Asadh 2083 | E25: =E8 -> Upto 18 Magh 2082 | F25: =F8 -> FY 2081-82
B26: Balance on 1 Shrawan | D26: =E28 -> 0 | E26: =F28 -> 0 | F26: 0
B27: Purchase during the period | D27: 0 | E27: 0 | F27: 0 | H27: 120571
B28: Less: Balance on 32 Ashadh | D28: 0 | E28: 0 | F28: 0
D30: =D26+D27-D28 -> 0 | E30: =E26+E27-E28 -> 0 | F30: =F26+F27-F28 -> 0
A32: 3.15 | B32: Direct Expenses
D33: =D25 -> Upto 15 Asadh 2083 | E33: =E66 -> Upto 18 Magh 2082 | F33: =F66 -> FY 2081-82
B34: Freight
B35: Customs Duty
B36: Other Direct Expenses
D38: =SUM(D34:D36) -> 0 | E38: =SUM(E34:E36) -> 0 | F38: =SUM(F34:F36) -> 0
A41: 3.16 | B41: Employee Benefit Expenses
D42: =D25 -> Upto 15 Asadh 2083 | E42: =E25 -> Upto 18 Magh 2082 | F42: =F25 -> FY 2081-82
B43: Salary & Allowances | D43: 0 | E43: 0 | F43: 0
B44: Dashain Expenses
B45: Staff Welfare
B46: PF & Gratuity expense | H46: =58914+49076 -> 107990
B47: Leave Expense
D50: =SUM(D43:D48) -> 0 | E50: =SUM(E43:E47) -> 0 | F50: =SUM(F43:F47) -> 0
B52: Key management personnel compensation
B53: Key management personnel are those persons having authority and responsibility for planning, directing and controlling the activities of the entity, including the directors.
E55: =E42 -> Upto 18 Magh 2082 | F55: =F42 -> FY 2081-82
B56: Salary
B57: Other long-term benefits
B58: Total pension and other post-employment benefit costs
B59: Compensations for loss of office
B60: Share based payment expense
E62: =SUM(E60:E60) -> 0 | F62: =SUM(F60:F60) -> 0
A65: 3.17 | B65: Administrative and Other Expenses
D66: =D42 -> Upto 15 Asadh 2083 | E66: =E55 -> Upto 18 Magh 2082 | F66: =F55 -> FY 2081-82
B67: Office Administrative and Running Expenses
B68: Audit Fee | D68: ='TB update upto 10.18'!F106 -> 0 | E68: ='TB update upto 10.18'!G106 -> 33900 | F68: 28250
B69: Miscellaneous Expenses | F69: 1132
B70: Electricity and water
B71: Fine & Penalty
B72: Insurance
B73: Lunch and Refreshment Expenses
B74: Telephone, Internet and Hosting Charges
B75: POS and Billing Expenses
B76: Office Expenses
B77: Printing & Stationary
B78: Rates & Taxes
B79: Rent Expenses
B80: Repair and maintenance
D81: =SUM(D68:D80) -> 0 | E81: =SUM(E68:E80) -> 33900 | F81: =SUM(F68:F80) -> 29382
A83: 3.18 | B83: Interest expenses
D84: =D33 -> Upto 15 Asadh 2083 | E84: =E33 -> Upto 18 Magh 2082 | F84: =F33 -> FY 2081-82
B85: Interest expense
D86: =SUM(D85:D85) -> 0 | E86: =SUM(E85:E85) -> 0 | F86: =SUM(F85:F85) -> 0

Sheet 3.19 to 3.20 ao.03.32
A1: ='[5]3.3'!A1:E1 -> CELER MART PVT. LTD.
A3: Notes to Financial Statements
D5: Figures in NPR
A7: 3.19 | B7: Other Expenses
C8: ='3.12 to 3.18 ao 10.18'!D8 -> Upto 18 Magh 2082 | D8: ='3.12 to 3.18 ao 10.18'!E8 -> FY 2081-82
B9: Loss on sale of investments | D9: 0
C12: =SUM(C10:C10) -> 0 | D12: =SUM(D9:D10) -> 0
A14: 3.2 | B14: Tax Expenses
C15: =C8 -> Upto 18 Magh 2082 | D15: =D8 -> FY 2081-82
B16: Tax on profit for the year | C16: ='Tax Computation 10.18'!C16 -> 0 | D16: ='SOI 10.18'!D21 -> 0
B17: Previous year tax | C17: 0 | D17: ='SOI 10.18'!D22 -> 0
C19: =SUM(C16:C17) -> 0 | D19: =SUM(D16:D17) -> 0
B21: Reconciliation of book profits and taxable profits
C22: =C15 -> Upto 18 Magh 2082 | D22: =D15 -> FY 2081-82
B23: Profit before tax as per books | C23: ='Tax Computation 10.18'!C3 -> -164485.25 | D23: ='SOI 10.18'!D19 -> -177096
B24: Add: Depreciation as per books | C24: ='Tax Computation 10.18'!C4 -> 130585.25 | D24: ='SOI 10.18'!D17 -> 147714
B25: Less: Depreciation as per tax | C25: ='Tax Computation 10.18'!C5 -> 0 | D25: =-D24 -> -147714
B26: Add: Disallowed repairs | C26: ='Tax Computation 10.18'!C6 -> 0 | D26: =-[5]Reco!F23 -> 0
B27: Add: Gratuity expense as per books | C27: ='Tax Computation 10.18'!C7 -> 0 | D27: =-[5]Reco!F15 -> 0
B28: Less: Gratuity paid | C28: ='Tax Computation 10.18'!C8 -> 0 | D28: =-[5]Reco!F14 -> 0
B29: Add: Leave expense as per books | C29: ='Tax Computation 10.18'!C9 -> 0 | D29: =-[5]Reco!F17 -> 0
B30: Less: Leave paid | C30: ='Tax Computation 10.18'!C10 -> 0 | D30: =-[5]Reco!F16 -> 0
B31: Less: Fair value gain on investments | C31: ='Tax Computation 10.18'!C11 -> 0 | D31: =-[5]Reco!F20 -> 0
B32: Add: Exchange loss/(gain) as per books | C32: ='Tax Computation 10.18'!C12 -> 0 | D32: =-[5]Reco!F22 -> 0
B33: Add: Realized exchange gain/(loss) | C33: ='Tax Computation 10.18'!C13 -> 0 | D33: =-[5]Reco!F21 -> 0
B34: Add: Difference in profit on sale of investment | C34: 0 | D34: 270000
B35: Add: Disallowed expenses | C35: ='Tax Computation 10.18'!C14 -> 0 | D35: 0
B36: Taxable profit | C36: =SUM(C23:C35) -> -33900 | D36: =SUM(D23:D35) -> 92904
B37: Income tax expense @ 25% | C37: =C36*25% -> -8475 | D37: =D36*25% -> 23226

Sheet 3.16 to 3.20 ao 03.32
A1: ='[5]3.3'!A1:E1 -> CELER MART PVT. LTD.
A3: Notes to Financial Statements
A5: Figures in NPR
A7: 3.21. Changes in Accounting Policies (If any)
A8: In the current financial year the company changes in accounting policies. This change has been accounted for by restating comparatives and adjusting the opening balance of retained earnings at 01 Shrawan 20XX. The changes in accounting policy, when applied consistently to 20X1 had the follwoing impact: On Opening Retained Earnings; On Net Profit.
A10: 3.18. Contingencies
A11: The company has contingent liabilities in respect of bank and other guarantees and other matters arising in the ordinary course of business. It is not anticipated that any material liablitites will arise from the contingent liabilities.
A13: 3.19. Related Party Transactions
A14: Identity of related parties
A15: The company is controlled by (name of the parent company) which owns xx percent of the company's shares. The remaining xx percent shares are widely held. The ultimate parent company of the company is (name of the ultimate parent company) incorporated in (name of the country)
A16: The following transactions were carried out with related parties (Give details)
A17: Directors of the company and their immediate relatives control xx percent of the voting shares of the company. Loans to directors amounting to NRs xx (20XX: NRs xx) are included in "other receivables". No interest is payable by the directors (for disclose if interest is payable)
A18: In additiona to their salaries, the company also provides non-cash benefits to directors and executive officers, and contributes to a post-employment defined benefit plan on their behalf.
... A27: Prior period errors are ommissions or misstatements in an entity's financial statements. Such ommissions may relate to one or more prior periods. Correction of an error is done by calculating the cumulative effect of the change on the financial statements of the period as if new method or estimate had always been used for all the affected prior years' financial statements. Sometimes, such changes may not be practicable, in such cases it is applied to the latest period possible by making corresponding adjustment to the opening balance of the period.

Sheet Annex 1&2 ao 03.32
A1: ='[5]3.3'!A1:E1 -> CELER MART PVT. LTD.
A3: Notes to Financial Statements
A5: Figures in NPR
A7: Significant Accounting Policies and Notes to Accounts
A9: 1. General information
A10: Give brief information about the legal status, registered address and nature of the business of the company.
A11: The financial statements were authorized to issue by …....... on …........
A13: 2. Significant Accounting Policies
A14: 2.1 Basis of preparation and accounting policies
A15: 2.1.1 Statement of Compliance
A16: These financial statements have been prepared in accordance with Nepal Accounting Standard for Micro Entities (NAS for MEs).
A17: 2.2.2 Basis of Measurement
A18: The financial statements have been prepared on the historical cost basis except investments held-for-trade is measured at fair value.
... A96: Interest expenses are recognized in the statement of income using accrual method.

Sheet Tax Computation 03.32
A1: CALCULATION OF TAXABLE INCOME
A3: Profit before tax as per books | C3: ='SOI 10.18'!C19 -> -164485.25
A4: Add: Depreciation as per books | C4: ='SOI 10.18'!C17 -> 130585.25
A5: Less: Depreciation as per tax | C5: 0
A6: Add: Disallowed repairs
A7: Add: Gratuity expense as per books
A8: Less: Gratuity paid
A9: Add: Leave expense as per books
A10: Less: Leave paid
A11: Less: Fair value gain on investments
A12: Add: Exchange loss as per books
A13: Add: Realized exchange gain
A14: Add: Disallowed expenses
A15: Taxable profit | C15: =SUM(C3:C14) -> -33900
A16: Income tax expense @ 25% | C16: 0

Sheet Sheet1
A1: Date | B1: Particulars | C1: Dr | D1: Cr
A2: 2082.04.04 | B2: Elite Power Pvt Ltd | C2: 820000
A3: 2082.04.04 | B3: Laxmi Sunrise Bank | D3: =+C2 -> 820000
A4: 2082.04.03 | B4: Laxmi Sunrise Bank | C4: 220000
A5: 2082.04.03 | B5: Elite Power Pvt Ltd | D5: =+C4 -> 220000
A6: 2082.04.13 | B6: Laxmi Sunrise Bank | C6: 780000
A7: 2082.04.13 | B7: Elite Steel Pvt Ltd | D7: =+C6 -> 780000
A8: 2082.04.14 | B8: Rajendra Karki | C8: 25000
A9: 2082.04.14 | B9: Laxmi Sunrise Bank | D9: 25000
A10: 2082.04.14 | B10: Bijay Bista | C10: 1000000
A11: 2082.04.14 | B11: Laxmi Sunrise Bank | D11: =+C10 -> 1000000
A12: 2082.04.16 | B12: Laxmi Sunrise Bank | C12: 700000
A13: 2082.04.16 | B13: Sita Karki | D13: =+C12 -> 700000
A14: 2082.04.20 | B14: Mamata Acharya Salary | C14: 25000
A15: 2082.04.20 | B15: Kamal Karki Salary | C15: 25000
A16: 2082.04.20 | B16: Ashmita B.K. Salary | C16: 15000
A17: 2082.04.20 | B17: Prem Prasad Tiwasena Salary | C17: 20000
A18: 2082.04.20 | B18: SST | D18: 850
A19: 2082.04.20 | B19: Laxmi Sunrise Bank | D19: =+C14+C15+C16+C17-D18 -> 84150
A20: 2082.04.23 | B20: Rajendra Karki | C20: 50000
A21: 2082.04.23 | B21: Laxmi Sunrise Bank | D21: =+C20 -> 50000
A22: 2082.04.23 | B22: Elite Steel Pvt Ltd | C22: 100000
A23: 2082.04.23 | B23: Laxmi Sunrise Bank | D23: =+C22 -> 100000
A24: 2082.04.23 | B24: Elite Steel Pvt Ltd | C24: 160000
A25: 2082.04.23 | B25: Laxmi Sunrise Bank | D25: =+C24 -> 160000
A26: 2082.04.30 | B26: Stationary | C26: =3475+3000 -> 6475
A27: 2082.04.30 | B27: Grocery | C27: 1030
A28: 2082.04.30 | B28: Kitchen | C28: 760
A29: 2082.04.30 | B29: Other Office Expenses | C29: 4000
A30: 2082.04.30 | B30: Fuel | C30: 3090
A31: 2082.04.30 | B31: Mamata Acharya - Payable | D31: =SUM(C26:C30) -> 15355
A32: 2082.05.05 | B32: Mamata Acharya - Payable | C32: 10000
A33: 2082.05.05 | B33: Laxmi Sunrise Bank | D33: 10000
A34: 2082.05.05 | B34: Rajendra Karki | C34: 100000
A35: 2082.05.05 | B35: Laxmi Sunrise Bank | D35: =+C34 -> 100000
A36: 2082.05.09 | B36: Laxmi Sunrise Bank | C36: 40000
A37: 2082.05.09 | B37: Siddhartha Bank | D37: =+C36 -> 40000
A38: 2082.05.09 | B38: Laxmi Sunrise Bank | C38: 25000
A39: 2082.05.09 | B39: Share Advance -Naresh Poudel | D39: =+C38 -> 25000
A40: 2082.05.09 | B40: Samyak Consulting Engineering Pvt. Ltd. | C40: 264812.5
A41: 2082.05.09 | B41: Laxmi Sunrise Bank | D41: =+C40 -> 264812.5
A42: 2082.05.09 | B42: Due Diligence Expense | C42: 0
A43: 2082.05.09 | B43: TDS PVT LTD | D43: =+C42/1.13*1.5% -> 0
A44: 2082.05.09 | B44: Samyak Consulting Engineering Pvt. Ltd. | D44: =+C42-D43 -> 0
A45: 2082.05.18 | B45: Laxmi Sunrise Bank | C45: 200000
A46: 2082.05.18 | B46: Baba Gas | D46: 200000
A47: 2082.05.19 | B47: Kamal Karki - Site Visit | C47: 160000
A48: 2082.05.19 | B48: Laxmi Sunrise Bank | D48: =+C47 -> 160000
A49: 2082.05.19 | B49: Naresh Poudel - Site Visit | C49: 40000
A50: 2082.05.19 | B50: Laxmi Sunrise Bank | D50: =+C49 -> 40000
A51: 2082.06.12 | B51: Laxmi Sunrise Bank | C51: 500000
A52: 2082.06.12 | B52: Share Advance - Uttam Kumar | D52: =+C51 -> 500000
A53: 2082.06.12 | B53: Rajendra Karki | C53: 200000
A54: 2082.06.12 | B54: Laxmi Sunrise Bank | D54: =+C53 -> 200000
A55: 2082.06.12 | B55: Stationary | C55: 400
A56: 2082.06.12 | B56: Grocery | C56: 110
A57: 2082.06.12 | B57: Kitchen | C57: 770
A58: 2082.06.12 | B58: Mamata Acharya - Payable | D58: =+C55+C56+C57 -> 1280
A59: 2082.06.12 | B59: Mamata Acharya Salary | C59: 50000
A60: 2082.06.12 | B60: Kamal Karki Salary | C60: 50000
A61: 2082.06.12 | B61: Ashmita B.K. Salary | C61: 30000
A62: 2082.06.12 | B62: SST | D62: 1300
A63: 2082.06.12 | B63: Laxmi Sunrise Bank | D63: =+C59+C60+C61-D62 -> 128700
A64: 2082.06.15 | B64: Buddha Law Assocites Pvt Ltd | C64: 75000
A65: 2082.06.15 | B65: Laxmi Sunrise Bank | D65: =+C64 -> 75000
A66: 2082.06.25 | B66: Mamata Acharya Salary | C66: 25000
A67: 2082.06.25 | B67: Kamal Karki Salary | C67: 25000
A68: 2082.06.25 | B68: SST | D68: 500
A69: 2082.06.25 | B69: Laxmi Sunrise Bank | D69: 49500
A70: 2082.06.30 | B70: Stationary | C70: 90
A71: 2082.06.30 | B71: Kitchen | C71: 775
A72: 2082.06.30 | B72: Mamata Acharya - Payable | D72: =+C70+C71 -> 865
A73: 2082.07.23 | B73: Mamata Acharya - Payable | C73: 20000
A74: 2082.07.23 | B74: Laxmi Sunrise Bank | D74: =+C73 -> 20000
A75: 2082.07.24 | B75: Meeting Allowance - Presentation feasibility | C75: 11500
A76: 2082.07.24 | B76: TDS 15% | D76: =+C75*15% -> 1725
A77: 2082.07.24 | B77: Mamata Acharya - Payable | D77: =+C75-D76 -> 9775
A78: 2082.07.24 | B78: Fuel | C78: 1500
A79: 2082.07.24 | B79: Misceallaneous | C79: 550
A80: 2082.07.24 | B80: Mamata Acharya - Payable | D80: =+C78+C79 -> 2050
A81: 2082.08.02 | B81: Laxmi Sunrise Bank | C81: 3800000
A82: 2082.08.02 | B82: Elite Power Pvt Ltd | D82: =+C81 -> 3800000
A83: 2082.08.02 | B83: Bhadra Venture | C83: 3700000
A84: 2082.08.02 | B84: Laxmi Sunrise Bank | D84: =+C83 -> 3700000
A85: 2082.08.02 | B85: Sky Bridge Tours and Travels Pvt Ltd | C85: 113785
A86: 2082.08.02 | B86: Laxmi Sunrise Bank | D86: =+C85 -> 113785
A87: 2082.08.02 | B87: Travelling | C87: 113785
A88: 2082.08.02 | B88: Sky Bridge Tours and Travels Pvt Ltd | D88: =+C87 -> 113785
A89: 2082.08.10 | B89: Laxmi Sunrise Bank | C89: 200000
A90: 2082.08.10 | B90: Share Advance - Shiv Ram Bhandari | D90: =+C89 -> 200000
A91: 2082.08.10 | B91: Mamata Acharya Salary | C91: 25000
A92: 2082.08.10 | B92: Kamal Karki Salary | C92: 25000
A93: 2082.08.10 | B93: SST | D93: 500
A94: 2082.08.10 | B94: Laxmi Sunrise Bank | D94: 49500
A95: 2082.08.10 | B95: Mohan Bista - Auditor (SST, TDS, Audit Fee) | C95: 124300
A96: 2082.08.10 | B96: Laxmi Sunrise Bank | D96: =+C95 -> 124300
A97: 2082.08.21 | B97: Kamal Karki - Site Visit | C97: 30000
A98: 2082.08.21 | B98: Laxmi Sunrise Bank | D98: =+C97 -> 30000
A99: 2082.09.11 | B99: Laxmi Sunrise Bank | C99: 1800000 | D99: =+C100 -> 0
A100: 2082.09.11 | B100: Share Advance - Bond Construction | C100: 0 | D100: =+C99 -> 1800000
...

Sheet 10.18 to 03.15
B1: Date | C1: Particulars | D1: Dr | E1: Cr
B2: 2082.12.01 | C2: Stationary | D2: 390
B3: 2082.12.01 | C3: Fuel | D3: 1500
B4: 2082.12.01 | C4: Mamata Acharya - Payable | E4: =+D2+D3 -> 1890
B5: 2082.10.26 | C5: Bank Charge | D5: 170
B6: 2082.10.26 | C6: Laxmi Sunrise Bank | E6: 170
B7: 2082.12.25 | C7: Mamata Acharya - Payable | D7: 5000
B8: 2082.12.25 | C8: Rajendra Karki | E8: =+D7 -> 5000
B9: 2082.12.30 | C9: Stationary | D9: 11175
B10: 2082.12.30 | C10: Fuel | D10: 500
B11: 2082.12.30 | C11: Other Office Expenses | D11: 500
B12: 2082.12.30 | C12: Mamata Acharya - Payable | E12: =+D9+D10+D11 -> 12175
B13: 2082.03.04 | C13: Laxmi Sunrise Bank | D13: 5000000
B14: 2082.03.04 | C14: Share Advance - I.B. Multipurpose Pvt Ltd | E14: =+D13 -> 5000000
B15: 2082.03.02 | C15: Laxmi Sunrise Bank | D15: 10000000
B16: 2082.03.02 | C16: Share Advance - I.B. Multipurpose Pvt Ltd | E16: =+D15 -> 10000000
B17: 2083.03.04 | C17: Laxmi Sunrise Bank | D17: 15600000
B18: 2083.03.04 | C18: Share Advance - Happy Nepal Investment | E18: =+D17 -> 15600000
B19: 2083.03.03 | C19: Bidhya Rai - Advance Return | D19: 8700000
B20: 2083.03.03 | C20: Laxmi Sunrise Bank | E20: =+D19 -> 8700000
B21: 2083.03.05 | C21: Hem Raj Bhattarai - Advance Return | D21: 1800000
B22: 2083.03.05 | C22: Laxmi Sunrise Bank | E22: =+D21 -> 1800000
B23: 2083.03.05 | C23: Ambe Hydropower Pvt Ltd | D23: 2000000
B24: 2083.03.05 | C24: Laxmi Sunrise Bank | E24: =+D23 -> 2000000
B25: 2083.03.03 | C25: Rajendra Karki | D25: 910000
B26: 2083.03.03 | C26: Laxmi Sunrise Bank | E26: =+D25 -> 910000
B27: 2083.03.04 | C27: Divya Jyoti Construction Pvt. Ltd. - Advance Return | D27: 15600000
B28: 2083.03.04 | C28: Laxmi Sunrise Bank | E28: =+D27 -> 15600000
B29: 2083.03.04 | C29: Mamata Acharya Salary | D29: 175000
B30: 2083.03.04 | C30: SST | E30: =+D29*1% -> 1750
B31: 2083.03.04 | C31: Laxmi Sunrise Bank | E31: =+D29-E30 -> 173250
B32: 2083.03.04 | C32: Slesha Engineering Consultancy Pvt Ltd | D32: 1000000
B33: 2083.03.04 | C33: Laxmi Sunrise Bank | E33: =+D32 -> 1000000
B34: 2083.03.04 | C34: Environmental Partner | D34: 339000
B35: 2083.03.04 | C35: Laxmi Sunrise Bank | E35: 339000
B36: 2083.03.04 | C36: IEE Study Expenses | D36: 339000
B37: 2083.03.04 | C37: TDS PVT LTD | E37: =300000*1.5% -> 4500
B38: 2083.03.04 | C38: Environmental Partner | E38: =+D36-E37 -> 334500
B39: 2083.03.09 | C39: Laxmi Sunrise Bank | D39: 1500000
B40: 2083.03.09 | C40: Share Capital Advance - Indra Bahadur Bista | E40: =+D39 -> 1500000
B41: 2083.03.09 | C41: Laxmi Sunrise Bank | D41: 2500000
B42: 2083.03.09 | C42: Share Capital Advance - Tanka Prasad Pandey | E42: =+D41 -> 2500000
B43: 2083.03.05 | C43: Rajendra Karki | D43: 75000
B44: 2083.03.05 | C44: Laxmi Sunrise Bank | E44: =+D43 -> 75000
B45: 2083.03.11 | C45: Rajendra Karki | D45: 600000
B46: 2083.03.11 | C46: Laxmi Sunrise Bank | E46: =+D45 -> 600000
B47: 2083.03.11 | C47: Babita Katwal | D47: 400000
B48: 2083.03.11 | C48: Laxmi Sunrise Bank | E48: =+D47 -> 400000
B49: 2083.03.11 | C49: Rajendra Karki | D49: =+D47 -> 400000
B50: 2083.03.11 | C50: Babita Katwal | E50: =+D49 -> 400000
B51: 2083.03.11 | C51: Rajendra Karki | D51: 400000
B52: 2083.03.11 | C52: Laxmi Sunrise Bank | E52: =+D51 -> 400000
B53: 2083.03.11 | C53: Bikram Bista | D53: 800000
B54: 2083.03.11 | C54: Laxmi Sunrise Bank | E54: =+D53 -> 800000
B55: 2083.03.11 | C55: Raj Kumar Mishra | D55: 200000
B56: 2083.03.11 | C56: Laxmi Sunrise Bank | E56: =+D55 -> 200000
B57: 2083.03.11 | C57: Bank Charge | D57: 200
B58: 2083.03.11 | C58: Laxmi Sunrise Bank | E58: =+D57 -> 200

Sheet JV 2082.04.01-10.18
B2: Date | C2: Particulars | D2: Dr | E2: Cr
B3: 2082.04.04 | C3: Elite Power Pvt Ltd | D3: 820000
B4: 2082.04.04 | C4: Laxmi Sunrise Bank | E4: =+D3 -> 820000
B5: 2082.04.03 | C5: Laxmi Sunrise Bank | D5: 220000
B6: 2082.04.03 | C6: Elite Power Pvt Ltd | E6: =+D5 -> 220000
B7: 2082.04.13 | C7: Laxmi Sunrise Bank | D7: 780000
B8: 2082.04.13 | C8: Elite Steel Pvt Ltd | E8: =+D7 -> 780000
B9: 2082.04.14 | C9: Rajendra Karki | D9: 25000
B10: 2082.04.14 | C10: Laxmi Sunrise Bank | E10: 25000
B11: 2082.04.14 | C11: Bijay Bista | D11: 1000000
B12: 2082.04.14 | C12: Laxmi Sunrise Bank | E12: =+D11 -> 1000000
B13: 2082.04.16 | C13: Laxmi Sunrise Bank | D13: 700000
B14: 2082.04.16 | C14: Sita Karki | E14: =+D13 -> 700000
B15: 2082.04.20 | C15: Mamata Acharya Salary | D15: 25000
B16: 2082.04.20 | C16: Kamal Karki Salary | D16: 25000
B17: 2082.04.20 | C17: Ashmita B.K. Salary | D17: 15000
B18: 2082.04.20 | C18: Prem Prasad Tiwasena Salary | D18: 20000
B19: 2082.04.20 | C19: SST | E19: 850
B20: 2082.04.20 | C20: Laxmi Sunrise Bank | E20: =+D15+D16+D17+D18-E19 -> 84150
B21: 2082.04.23 | C21: Rajendra Karki | D21: 50000
B22: 2082.04.23 | C22: Laxmi Sunrise Bank | E22: =+D21 -> 50000
B23: 2082.04.23 | C23: Elite Steel Pvt Ltd | D23: 100000
B24: 2082.04.23 | C24: Laxmi Sunrise Bank | E24: =+D23 -> 100000
B25: 2082.04.23 | C25: Elite Steel Pvt Ltd | D25: 160000
B26: 2082.04.23 | C26: Laxmi Sunrise Bank | E26: =+D25 -> 160000
B27: 2082.04.30 | C27: Stationary | D27: =3475+3000 -> 6475
B28: 2082.04.30 | C28: Grocery | D28: 1030
B29: 2082.04.30 | C29: Kitchen | D29: 760
B30: 2082.04.30 | C30: Other Office Expenses | D30: 4000
B31: 2082.04.30 | C31: Fuel | D31: 3090
B32: 2082.04.30 | C32: Mamata Acharya - Payable | E32: =SUM(D27:D31) -> 15355
B33: 2082.05.05 | C33: Mamata Acharya - Payable | D33: 10000
B34: 2082.05.05 | C34: Laxmi Sunrise Bank | E34: 10000
B35: 2082.05.05 | C35: Rajendra Karki | D35: 100000
B36: 2082.05.05 | C36: Laxmi Sunrise Bank | E36: =+D35 -> 100000
B37: 2082.05.09 | C37: Laxmi Sunrise Bank | D37: 40000
B38: 2082.05.09 | C38: Siddhartha Bank | E38: =+D37 -> 40000
B39: 2082.05.09 | C39: Laxmi Sunrise Bank | D39: 25000
B40: 2082.05.09 | C40: Share Advance -Naresh Poudel | E40: =+D39 -> 25000
B41: 2082.05.09 | C41: Samyak Consulting Engineering Pvt. Ltd. | D41: 264812.5
B42: 2082.05.09 | C42: Laxmi Sunrise Bank | E42: =+D41 -> 264812.5
B43: 2082.05.09 | C43: Due Diligence Expense | D43: 0
B44: 2082.05.09 | C44: TDS PVT LTD | E44: =+D43/1.13*1.5% -> 0
B45: 2082.05.09 | C45: Samyak Consulting Engineering Pvt. Ltd. | E45: =+D43-E44 -> 0
B46: 2082.05.18 | C46: Laxmi Sunrise Bank | D46: 200000
B47: 2082.05.18 | C47: Baba Gas | E47: 200000
B48: 2082.05.19 | C48: Kamal Karki - Site Visit | D48: 160000
B49: 2082.05.19 | C49: Laxmi Sunrise Bank | E49: =+D48 -> 160000
B50: 2082.05.19 | C50: Naresh Poudel - Site Visit | D50: 40000
B51: 2082.05.19 | C51: Laxmi Sunrise Bank | E51: =+D50 -> 40000
B52: 2082.06.12 | C52: Laxmi Sunrise Bank | D52: 500000
B53: 2082.06.12 | C53: Share Advance - Uttam Kumar | E53: =+D52 -> 500000
B54: 2082.06.12 | C54: Rajendra Karki | D54: 200000
B55: 2082.06.12 | C55: Laxmi Sunrise Bank | E55: =+D54 -> 200000
B56: 2082.06.12 | C56: Stationary | D56: 400
B57: 2082.06.12 | C57: Grocery | D57: 110
B58: 2082.06.12 | C58: Kitchen | D58: 770
B59: 2082.06.12 | C59: Mamata Acharya - Payable | E59: =+D56+D57+D58 -> 1280
B60: 2082.06.12 | C60: Mamata Acharya Salary | D60: 50000
B61: 2082.06.12 | C61: Kamal Karki Salary | D61: 50000
B62: 2082.06.12 | C62: Ashmita B.K. Salary | D62: 30000
B63: 2082.06.12 | C63: SST | E63: 1300
B64: 2082.06.12 | C64: Laxmi Sunrise Bank | E64: =+D60+D61+D62-E63 -> 128700
B65: 2082.06.15 | C65: Buddha Law Assocites Pvt Ltd | D65: 75000
B66: 2082.06.15 | C66: Laxmi Sunrise Bank | E66: =+D65 -> 75000
B67: 2082.06.25 | C67: Mamata Acharya Salary | D67: 25000
B68: 2082.06.25 | C68: Kamal Karki Salary | D68: 25000
B69: 2082.06.25 | C69: SST | E69: 500
B70: 2082.06.25 | C70: Laxmi Sunrise Bank | E70: 49500
B71: 2082.06.30 | C71: Stationary | D71: 90
B72: 2082.06.30 | C72: Kitchen | D72: 775
B73: 2082.06.30 | C73: Mamata Acharya - Payable | E73: =+D71+D72 -> 865
B74: 2082.07.23 | C74: Mamata Acharya - Payable | D74: 20000
B75: 2082.07.23 | C75: Laxmi Sunrise Bank | E75: =+D74 -> 20000
B76: 2082.07.24 | C76: Meeting Allowance - Presentation feasibility | D76: 11500
B77: 2082.07.24 | C77: TDS 15% | E77: =+D76*15% -> 1725
B78: 2082.07.24 | C78: Mamata Acharya - Payable | E78: =+D76-E77 -> 9775
B79: 2082.07.24 | C79: Fuel | D79: 1500
B80: 2082.07.24 | C80: Misceallaneous | D80: 550
B81: 2082.07.24 | C81: Mamata Acharya - Payable | E81: =+D79+D80 -> 2050
B82: 2082.08.02 | C82: Laxmi Sunrise Bank | D82: 3800000
B83: 2082.08.02 | C83: Elite Power Pvt Ltd | E83: =+D82 -> 3800000
B84: 2082.08.02 | C84: Bhadra Venture | D84: 3700000
B85: 2082.08.02 | C85: Laxmi Sunrise Bank | E85: =+D84 -> 3700000
B86: 2082.08.02 | C86: Sky Bridge Tours and Travels Pvt Ltd | D86: 113785
B87: 2082.08.02 | C87: Laxmi Sunrise Bank | E87: =+D86 -> 113785
B88: 2082.08.02 | C88: Travelling | D88: 113785
B89: 2082.08.02 | C89: Sky Bridge Tours and Travels Pvt Ltd | E89: =+D88 -> 113785
B90: 2082.08.10 | C90: Laxmi Sunrise Bank | D90: 200000
B91: 2082.08.10 | C91: Share Advance - Shiv Ram Bhandari | E91: =+D90 -> 200000
B92: 2082.08.10 | C92: Mamata Acharya Salary | D92: 25000
B93: 2082.08.10 | C93: Kamal Karki Salary | D93: 25000
B94: 2082.08.10 | C94: SST | E94: 500
B95: 2082.08.10 | C95: Laxmi Sunrise Bank | E95: 49500
B96: 2082.08.10 | C96: Mohan Bista - Auditor (SST, TDS, Audit Fee) | D96: 124300
B97: 2082.08.10 | C97: Laxmi Sunrise Bank | E97: =+D96 -> 124300
B98: 2082.08.21 | C98: Kamal Karki - Site Visit | D98: 30000
B99: 2082.08.21 | C99: Laxmi Sunrise Bank | E99: =+D98 -> 30000
B100: 2082.09.11 | C100: Laxmi Sunrise Bank | D100: 1800000 | E100: =+D101 -> 0
B101: 2082.09.11 | C101: Share Advance - Bond Construction | D101: 0 | E101: =+D100 -> 1800000
...

Sheet After 03.15
B2: Date | C2: Particulars | D2: Dr | E2: Cr
B3: 2083.03.17 | C3: Office Furnishing - Pool E | D3: 545083.75
B4: 2083.03.17 | C4: TDS PVT LTD | E4: =482375*1.5% -> 7235.625
B5: 2083.03.17 | C5: Gajulkot Engineering And Construction Pvt. Ltd. | E5: =+D3-E4 -> 537848.12
B6: 2083.03.04 | C6: Printing & Stationary | D6: 2000
B7: 2083.03.04 | C7: Mamata Acharya - Payable | E7: =+D6 -> 2000
B8: 2083.03.04 | C8: Printing & Stationary | D8: 210
B9: 2083.03.04 | C9: Mamata Acharya - Payable | E9: =+D8 -> 210
B10: 2083.03.30 | C10: Travelling | D10: =9311+9311+38044+14800+9311+7700+8491+9511+9511 -> 115990
B11: 2083.03.30 | C11: Pragya Travels And Tours Pvt Ltd | E11: =+D10 -> 115990
B12: 2083.03.30 | C12: Bank Charge | D12: 2101
B13: 2083.03.30 | C13: Laxmi Sunrise Bank | E13: 2101
B14: 2083.03.30 | C14: TADA | D14: 15000
B15: 2083.03.30 | C15: Travelling | D15: 9311
B16: 2083.03.30 | C16: TDS 15% | E16: =+D14*15% -> 2250
B17: 2083.03.30 | C17: Samyog Bashyal | E17: =+D14+D15-E16 -> 22061

Sheet TB 2082.04.01-10.18
B1: Opening | D1: During the Year | F1: Closing
A2: Particulars | B2: Debit | C2: Credit | D2: Debit | E2: Credit | F2: Debit | G2: Credit
A3: Elite Power Pvt Ltd | D3: =MAX(SUMIF('JV 2082.04.01-10.18'!C:C,$A3,'JV 2082.04.01-10.18'!D:D)-SUMIF('JV 2082.04.01-10.18'!C:C,$A3,'JV 2082.04.01-10.18'!E:E),0) -> 0 | E3: =MAX(SUMIF('JV 2082.04.01-10.18'!C:C,$A3,'JV 2082.04.01-10.18'!E:E)-SUMIF('JV 2082.04.01-10.18'!C:C,$A3,'JV 2082.04.01-10.18'!D:D),0) -> 3200000
A4: Laxmi Sunrise Bank | D4: =MAX(SUMIF('JV 2082.04.01-10.18'!C:C,$A4,'JV 2082.04.01-10.18'!D:D)-SUMIF('JV 2082.04.01-10.18'!C:C,$A4,'JV 2082.04.01-10.18'!E:E),0) -> 0 | E4: =MAX(SUMIF('JV 2082.04.01-10.18'!C:C,$A4,'JV 2082.04.01-10.18'!E:E)-SUMIF('JV 2082.04.01-10.18'!C:C,$A4,'JV 2082.04.01-10.18'!D:D),0) -> 838559.5
A5: Elite Steel Pvt Ltd | D5: =MAX(SUMIF('JV 2082.04.01-10.18'!C:C,$A5,'JV 2082.04.01-10.18'!D:D)-SUMIF('JV 2082.04.01-10.18'!C:C,$A5,'JV 2082.04.01-10.18'!E:E),0) -> 260000 | E5: =MAX(SUMIF('JV 2082.04.01-10.18'!C:C,$A5,'JV 2082.04.01-10.18'!E:E)-SUMIF('JV 2082.04.01-10.18'!C:C,$A5,'JV 2082.04.01-10.18'!D:D),0) -> 0
A6: Rajendra Karki | D6: =MAX(SUMIF('JV 2082.04.01-10.18'!C:C,$A6,'JV 2082.04.01-10.18'!D:D)-SUMIF('JV 2082.04.01-10.18'!C:C,$A6,'JV 2082.04.01-10.18'!E:E),0) -> 2310000 | E6: =MAX(SUMIF('JV 2082.04.01-10.18'!C:C,$A6,'JV 2082.04.01-10.18'!E:E)-SUMIF('JV 2082.04.01-10.18'!C:C,$A6,'JV 2082.04.01-10.18'!D:D),0) -> 0
A7: Bijay Bista | D7: =MAX(SUMIF('JV 2082.04.01-10.18'!C:C,$A7,'JV 2082.04.01-10.18'!D:D)-SUMIF('JV 2082.04.01-10.18'!C:C,$A7,'JV 2082.04.01-10.18'!E:E),0) -> 1000000 | E7: =MAX(SUMIF('JV 2082.04.01-10.18'!C:C,$A7,'JV 2082.04.01-10.18'!E:E)-SUMIF('JV 2082.04.01-10.18'!C:C,$A7,'JV 2082.04.01-10.18'!D:D),0) -> 0
A8: Sita Karki | D8: =MAX(SUMIF('JV 2082.04.01-10.18'!C:C,$A8,'JV 2082.04.01-10.18'!D:D)-SUMIF('JV 2082.04.01-10.18'!C:C,$A8,'JV 2082.04.01-10.18'!E:E),0) -> 0 | E8: =MAX(SUMIF('JV 2082.04.01-10.18'!C:C,$A8,'JV 2082.04.01-10.18'!E:E)-SUMIF('JV 2082.04.01-10.18'!C:C,$A8,'JV 2082.04.01-10.18'!D:D),0) -> 700000
A9: Mamata Acharya Salary | D9: =MAX(SUMIF('JV 2082.04.01-10.18'!C:C,$A9,'JV 2082.04.01-10.18'!D:D)-SUMIF('JV 2082.04.01-10.18'!C:C,$A9,'JV 2082.04.01-10.18'!E:E),0) -> 175000 | E9: =MAX(SUMIF('JV 2082.04.01-10.18'!C:C,$A9,'JV 2082.04.01-10.18'!E:E)-SUMIF('JV 2082.04.01-10.18'!C:C,$A9,'JV 2082.04.01-10.18'!D:D),0) -> 0
A10: Kamal Karki Salary | D10: =MAX(SUMIF('JV 2082.04.01-10.18'!C:C,$A10,'JV 2082.04.01-10.18'!D:D)-SUMIF('JV 2082.04.01-10.18'!C:C,$A10,'JV 2082.04.01-10.18'!E:E),0) -> 175000 | E10: =MAX(SUMIF('JV 2082.04.01-10.18'!C:C,$A10,'JV 2082.04.01-10.18'!E:E)-SUMIF('JV 2082.04.01-10.18'!C:C,$A10,'JV 2082.04.01-10.18'!D:D),0) -> 0
A11: Ashmita B.K. Salary | D11: =MAX(SUMIF('JV 2082.04.01-10.18'!C:C,$A11,'JV 2082.04.01-10.18'!D:D)-SUMIF('JV 2082.04.01-10.18'!C:C,$A11,'JV 2082.04.01-10.18'!E:E),0) -> 45000 | E11: =MAX(SUMIF('JV 2082.04.01-10.18'!C:C,$A11,'JV 2082.04.01-10.18'!E:E)-SUMIF('JV 2082.04.01-10.18'!C:C,$A11,'JV 2082.04.01-10.18'!D:D),0) -> 0
A12: Prem Prasad Tiwasena Salary | D12: =MAX(SUMIF('JV 2082.04.01-10.18'!C:C,$A12,'JV 2082.04.01-10.18'!D:D)-SUMIF('JV 2082.04.01-10.18'!C:C,$A12,'JV 2082.04.01-10.18'!E:E),0) -> 20000 | E12: =MAX(SUMIF('JV 2082.04.01-10.18'!C:C,$A12,'JV 2082.04.01-10.18'!E:E)-SUMIF('JV 2082.04.01-10.18'!C:C,$A12,'JV 2082.04.01-10.18'!D:D),0) -> 0
A13: SST | D13: =MAX(SUMIF('JV 2082.04.01-10.18'!C:C,$A13,'JV 2082.04.01-10.18'!D:D)-SUMIF('JV 2082.04.01-10.18'!C:C,$A13,'JV 2082.04.01-10.18'!E:E),0) -> 0 | E13: =MAX(SUMIF('JV 2082.04.01-10.18'!C:C,$A13,'JV 2082.04.01-10.18'!E:E)-SUMIF('JV 2082.04.01-10.18'!C:C,$A13,'JV 2082.04.01-10.18'!D:D),0) -> 4150
A14: Stationary | D14: =MAX(SUMIF('JV 2082.04.01-10.18'!C:C,$A14,'JV 2082.04.01-10.18'!D:D)-SUMIF('JV 2082.04.01-10.18'!C:C,$A14,'JV 2082.04.01-10.18'!E:E),0) -> 6965 | E14: =MAX(SUMIF('JV 2082.04.01-10.18'!C:C,$A14,'JV 2082.04.01-10.18'!E:E)-SUMIF('JV 2082.04.01-10.18'!C:C,$A14,'JV 2082.04.01-10.18'!D:D),0) -> 0
... A46: Shiva Ram Bhandari - Other Advance | D46: =MAX(SUMIF('JV 2082.04.01-10.18'!C:C,$A46,'JV 2082.04.01-10.18'!D:D)-SUMIF('JV 2082.04.01-10.18'!C:C,$A46,'JV 2082.04.01-10.18'!E:E),0) -> 0 | E46: =MAX(SUMIF('JV 2082.04.01-10.18'!C:C,$A46,'JV 2082.04.01-10.18'!E:E)-SUMIF('JV 2082.04.01-10.18'!C:C,$A46,'JV 2082.04.01-10.18'!D:D),0) -> 40000
A47: Total | D47: =SUM(D3:D46) -> 27356984 | E47: =SUM(E3:E46) -> 27356984

Sheet TB 10.18 to 03.15
A1: Particulars | B1: Debit | C1: Credit
A2: Stationary | B2: =MAX(SUMIF('10.18 to 03.15'!C:C,$A2,'10.18 to 03.15'!D:D)-SUMIF('10.18 to 03.15'!C:C,$A2,'10.18 to 03.15'!E:E),0) -> 11565 | C2: =MAX(SUMIF('10.18 to 03.15'!C:C,$A2,'10.18 to 03.15'!E:E)-SUMIF('10.18 to 03.15'!C:C,$A2,'10.18 to 03.15'!D:D),0) -> 0
A3: Fuel | B3: =MAX(SUMIF('10.18 to 03.15'!C:C,$A3,'10.18 to 03.15'!D:D)-SUMIF('10.18 to 03.15'!C:C,$A3,'10.18 to 03.15'!E:E),0) -> 2000 | C3: =MAX(SUMIF('10.18 to 03.15'!C:C,$A3,'10.18 to 03.15'!E:E)-SUMIF('10.18 to 03.15'!C:C,$A3,'10.18 to 03.15'!D:D),0) -> 0
A4: Mamata Acharya - Payable | B4: =MAX(SUMIF('10.18 to 03.15'!C:C,$A4,'10.18 to 03.15'!D:D)-SUMIF('10.18 to 03.15'!C:C,$A4,'10.18 to 03.15'!E:E),0) -> 0 | C4: =MAX(SUMIF('10.18 to 03.15'!C:C,$A4,'10.18 to 03.15'!E:E)-SUMIF('10.18 to 03.15'!C:C,$A4,'10.18 to 03.15'!D:D),0) -> 9065
A5: Bank Charge | B5: =MAX(SUMIF('10.18 to 03.15'!C:C,$A5,'10.18 to 03.15'!D:D)-SUMIF('10.18 to 03.15'!C:C,$A5,'10.18 to 03.15'!E:E),0) -> 370 | C5: =MAX(SUMIF('10.18 to 03.15'!C:C,$A5,'10.18 to 03.15'!E:E)-SUMIF('10.18 to 03.15'!C:C,$A5,'10.18 to 03.15'!D:D),0) -> 0
A6: Laxmi Sunrise Bank | B6: =MAX(SUMIF('10.18 to 03.15'!C:C,$A6,'10.18 to 03.15'!D:D)-SUMIF('10.18 to 03.15'!C:C,$A6,'10.18 to 03.15'!E:E),0) -> 1602380 | C6: =MAX(SUMIF('10.18 to 03.15'!C:C,$A6,'10.18 to 03.15'!E:E)-SUMIF('10.18 to 03.15'!C:C,$A6,'10.18 to 03.15'!D:D),0) -> 0
A7: Rajendra Karki | B7: =MAX(SUMIF('10.18 to 03.15'!C:C,$A7,'10.18 to 03.15'!D:D)-SUMIF('10.18 to 03.15'!C:C,$A7,'10.18 to 03.15'!E:E),0) -> 2380000 | C7: =MAX(SUMIF('10.18 to 03.15'!C:C,$A7,'10.18 to 03.15'!E:E)-SUMIF('10.18 to 03.15'!C:C,$A7,'10.18 to 03.15'!D:D),0) -> 0
A8: Other Office Expenses | B8: =MAX(SUMIF('10.18 to 03.15'!C:C,$A8,'10.18 to 03.15'!D:D)-SUMIF('10.18 to 03.15'!C:C,$A8,'10.18 to 03.15'!E:E),0) -> 500 | C8: =MAX(SUMIF('10.18 to 03.15'!C:C,$A8,'10.18 to 03.15'!E:E)-SUMIF('10.18 to 03.15'!C:C,$A8,'10.18 to 03.15'!D:D),0) -> 0
A9: Share Advance - I.B. Multipurpose Pvt Ltd | B9: =MAX(SUMIF('10.18 to 03.15'!C:C,$A9,'10.18 to 03.15'!D:D)-SUMIF('10.18 to 03.15'!C:C,$A9,'10.18 to 03.15'!E:E),0) -> 0 | C9: =MAX(SUMIF('10.18 to 03.15'!C:C,$A9,'10.18 to 03.15'!E:E)-SUMIF('10.18 to 03.15'!C:C,$A9,'10.18 to 03.15'!D:D),0) -> 15000000
A10: Share Advance - Happy Nepal Investment | B10: =MAX(SUMIF('10.18 to 03.15'!C:C,$A10,'10.18 to 03.15'!D:D)-SUMIF('10.18 to 03.15'!C:C,$A10,'10.18 to 03.15'!E:E),0) -> 0 | C10: =MAX(SUMIF('10.18 to 03.15'!C:C,$A10,'10.18 to 03.15'!E:E)-SUMIF('10.18 to 03.15'!C:C,$A10,'10.18 to 03.15'!D:D),0) -> 15600000
A11: Bidhya Rai - Advance Return | B11: =MAX(SUMIF('10.18 to 03.15'!C:C,$A11,'10.18 to 03.15'!D:D)-SUMIF('10.18 to 03.15'!C:C,$A11,'10.18 to 03.15'!E:E),0) -> 8700000 | C11: =MAX(SUMIF('10.18 to 03.15'!C:C,$A11,'10.18 to 03.15'!E:E)-SUMIF('10.18 to 03.15'!C:C,$A11,'10.18 to 03.15'!D:D),0) -> 0
A12: Hem Raj Bhattarai - Advance Return | B12: =MAX(SUMIF('10.18 to 03.15'!C:C,$A12,'10.18 to 03.15'!D:D)-SUMIF('10.18 to 03.15'!C:C,$A12,'10.18 to 03.15'!E:E),0) -> 1800000 | C12: =MAX(SUMIF('10.18 to 03.15'!C:C,$A12,'10.18 to 03.15'!E:E)-SUMIF('10.18 to 03.15'!C:C,$A12,'10.18 to 03.15'!D:D),0) -> 0
A13: Ambe Hydropower Pvt Ltd | B13: =MAX(SUMIF('10.18 to 03.15'!C:C,$A13,'10.18 to 03.15'!D:D)-SUMIF('10.18 to 03.15'!C:C,$A13,'10.18 to 03.15'!E:E),0) -> 2000000 | C13: =MAX(SUMIF('10.18 to 03.15'!C:C,$A13,'10.18 to 03.15'!E:E)-SUMIF('10.18 to 03.15'!C:C,$A13,'10.18 to 03.15'!D:D),0) -> 0
... A25: Raj Kumar Mishra | B25: =MAX(SUMIF('10.18 to 03.15'!C:C,$A25,'10.18 to 03.15'!D:D)-SUMIF('10.18 to 03.15'!C:C,$A25,'10.18 to 03.15'!E:E),0) -> 200000 | C25: =MAX(SUMIF('10.18 to 03.15'!C:C,$A25,'10.18 to 03.15'!E:E)-SUMIF('10.18 to 03.15'!C:C,$A25,'10.18 to 03.15'!D:D),0) -> 0
A26: Total | B26: =SUM(B2:B25) -> 34615315 | C26: =SUM(C2:C25) -> 34615315

Sheet TB After 03.15
A1: Particulars | B1: Debit | C1: Credit
A2: Office Furnishing - Pool E | B2: =MAX(SUMIF('After 03.15'!C:C,$A2,'After 03.15'!D:D)-SUMIF('After 03.15'!C:C,$A2,'After 03.15'!E:E),0) -> 545083.75 | C2: =MAX(SUMIF('After 03.15'!C:C,$A2,'After 03.15'!E:E)-SUMIF('After 03.15'!C:C,$A2,'After 03.15'!D:D),0) -> 0
A3: TDS PVT LTD | B3: =MAX(SUMIF('After 03.15'!C:C,$A3,'After 03.15'!D:D)-SUMIF('After 03.15'!C:C,$A3,'After 03.15'!E:E),0) -> 0 | C3: =MAX(SUMIF('After 03.15'!C:C,$A3,'After 03.15'!E:E)-SUMIF('After 03.15'!C:C,$A3,'After 03.15'!D:D),0) -> 7235.625
A4: Gajulkot Engineering And Construction Pvt. Ltd. | B4: =MAX(SUMIF('After 03.15'!C:C,$A4,'After 03.15'!D:D)-SUMIF('After 03.15'!C:C,$A4,'After 03.15'!E:E),0) -> 0 | C4: =MAX(SUMIF('After 03.15'!C:C,$A4,'After 03.15'!E:E)-SUMIF('After 03.15'!C:C,$A4,'After 03.15'!D:D),0) -> 537848.12
A5: Printing & Stationary | B5: =MAX(SUMIF('After 03.15'!C:C,$A5,'After 03.15'!D:D)-SUMIF('After 03.15'!C:C,$A5,'After 03.15'!E:E),0) -> 2210 | C5: =MAX(SUMIF('After 03.15'!C:C,$A5,'After 03.15'!E:E)-SUMIF('After 03.15'!C:C,$A5,'After 03.15'!D:D),0) -> 0
A6: Mamata Acharya - Payable | B6: =MAX(SUMIF('After 03.15'!C:C,$A6,'After 03.15'!D:D)-SUMIF('After 03.15'!C:C,$A6,'After 03.15'!E:E),0) -> 0 | C6: =MAX(SUMIF('After 03.15'!C:C,$A6,'After 03.15'!E:E)-SUMIF('After 03.15'!C:C,$A6,'After 03.15'!D:D),0) -> 2210
A7: Travelling | B7: =MAX(SUMIF('After 03.15'!C:C,$A7,'After 03.15'!D:D)-SUMIF('After 03.15'!C:C,$A7,'After 03.15'!E:E),0) -> 125301 | C7: =MAX(SUMIF('After 03.15'!C:C,$A7,'After 03.15'!E:E)-SUMIF('After 03.15'!C:C,$A7,'After 03.15'!D:D),0) -> 0
A8: Pragya Travels And Tours Pvt Ltd | B8: =MAX(SUMIF('After 03.15'!C:C,$A8,'After 03.15'!D:D)-SUMIF('After 03.15'!C:C,$A8,'After 03.15'!E:E),0) -> 0 | C8: =MAX(SUMIF('After 03.15'!C:C,$A8,'After 03.15'!E:E)-SUMIF('After 03.15'!C:C,$A8,'After 03.15'!D:D),0) -> 115990
A9: Bank Charge | B9: =MAX(SUMIF('After 03.15'!C:C,$A9,'After 03.15'!D:D)-SUMIF('After 03.15'!C:C,$A9,'After 03.15'!E:E),0) -> 2101 | C9: =MAX(SUMIF('After 03.15'!C:C,$A9,'After 03.15'!E:E)-SUMIF('After 03.15'!C:C,$A9,'After 03.15'!D:D),0) -> 0
A10: Laxmi Sunrise Bank | B10: =MAX(SUMIF('After 03.15'!C:C,$A10,'After 03.15'!D:D)-SUMIF('After 03.15'!C:C,$A10,'After 03.15'!E:E),0) -> 0 | C10: =MAX(SUMIF('After 03.15'!C:C,$A10,'After 03.15'!E:E)-SUMIF('After 03.15'!C:C,$A10,'After 03.15'!D:D),0) -> 2101
A11: TADA | B11: =MAX(SUMIF('After 03.15'!C:C,$A11,'After 03.15'!D:D)-SUMIF('After 03.15'!C:C,$A11,'After 03.15'!E:E),0) -> 15000 | C11: =MAX(SUMIF('After 03.15'!C:C,$A11,'After 03.15'!E:E)-SUMIF('After 03.15'!C:C,$A11,'After 03.15'!D:D),0) -> 0
A12: TDS 15% | B12: =MAX(SUMIF('After 03.15'!C:C,$A12,'After 03.15'!D:D)-SUMIF('After 03.15'!C:C,$A12,'After 03.15'!E:E),0) -> 0 | C12: =MAX(SUMIF('After 03.15'!C:C,$A12,'After 03.15'!E:E)-SUMIF('After 03.15'!C:C,$A12,'After 03.15'!D:D),0) -> 2250
A13: Samyog Bashyal | B13: =MAX(SUMIF('After 03.15'!C:C,$A13,'After 03.15'!D:D)-SUMIF('After 03.15'!C:C,$A13,'After 03.15'!E:E),0) -> 0 | C13: =MAX(SUMIF('After 03.15'!C:C,$A13,'After 03.15'!E:E)-SUMIF('After 03.15'!C:C,$A13,'After 03.15'!D:D),0) -> 22061
A14: Total | B14: =SUM(B2:B13) -> 689695.75 | C14: =SUM(C2:C13) -> 689695.75

Sheet TB Sheet1
A1: Particulars | B1: Debit | C1: Credit
A2: Elite Power Pvt Ltd | B2: =MAX(SUMIF(Sheet1!B:B,$A2,Sheet1!C:C)-SUMIF(Sheet1!B:B,$A2,Sheet1!D:D),0) -> 0 | C2: =MAX(SUMIF(Sheet1!B:B,$A2,Sheet1!D:D)-SUMIF(Sheet1!B:B,$A2,Sheet1!C:C),0) -> 3200000
A3: Laxmi Sunrise Bank | B3: =MAX(SUMIF(Sheet1!B:B,$A3,Sheet1!C:C)-SUMIF(Sheet1!B:B,$A3,Sheet1!D:D),0) -> 761719.5 | C3: =MAX(SUMIF(Sheet1!B:B,$A3,Sheet1!D:D)-SUMIF(Sheet1!B:B,$A3,Sheet1!C:C),0) -> 0
A4: Elite Steel Pvt Ltd | B4: =MAX(SUMIF(Sheet1!B:B,$A4,Sheet1!C:C)-SUMIF(Sheet1!B:B,$A4,Sheet1!D:D),0) -> 260000 | C4: =MAX(SUMIF(Sheet1!B:B,$A4,Sheet1!D:D)-SUMIF(Sheet1!B:B,$A4,Sheet1!C:C),0) -> 0
A5: Rajendra Karki | B5: =MAX(SUMIF(Sheet1!B:B,$A5,Sheet1!C:C)-SUMIF(Sheet1!B:B,$A5,Sheet1!D:D),0) -> 4690000 | C5: =MAX(SUMIF(Sheet1!B:B,$A5,Sheet1!D:D)-SUMIF(Sheet1!B:B,$A5,Sheet1!C:C),0) -> 0
A6: Bijay Bista | B6: =MAX(SUMIF(Sheet1!B:B,$A6,Sheet1!C:C)-SUMIF(Sheet1!B:B,$A6,Sheet1!D:D),0) -> 1000000 | C6: =MAX(SUMIF(Sheet1!B:B,$A6,Sheet1!D:D)-SUMIF(Sheet1!B:B,$A6,Sheet1!C:C),0) -> 0
A7: Sita Karki | B7: =MAX(SUMIF(Sheet1!B:B,$A7,Sheet1!C:C)-SUMIF(Sheet1!B:B,$A7,Sheet1!D:D),0) -> 0 | C7: =MAX(SUMIF(Sheet1!B:B,$A7,Sheet1!D:D)-SUMIF(Sheet1!B:B,$A7,Sheet1!C:C),0) -> 700000
A8: Mamata Acharya Salary | B8: =MAX(SUMIF(Sheet1!B:B,$A8,Sheet1!C:C)-SUMIF(Sheet1!B:B,$A8,Sheet1!D:D),0) -> 350000 | C8: =MAX(SUMIF(Sheet1!B:B,$A8,Sheet1!D:D)-SUMIF(Sheet1!B:B,$A8,Sheet1!C:C),0) -> 0
A9: Kamal Karki Salary | B9: =MAX(SUMIF(Sheet1!B:B,$A9,Sheet1!C:C)-SUMIF(Sheet1!B:B,$A9,Sheet1!D:D),0) -> 175000 | C9: =MAX(SUMIF(Sheet1!B:B,$A9,Sheet1!D:D)-SUMIF(Sheet1!B:B,$A9,Sheet1!C:C),0) -> 0
A10: Ashmita B.K. Salary | B10: =MAX(SUMIF(Sheet1!B:B,$A10,Sheet1!C:C)-SUMIF(Sheet1!B:B,$A10,Sheet1!D:D),0) -> 45000 | C10: =MAX(SUMIF(Sheet1!B:B,$A10,Sheet1!D:D)-SUMIF(Sheet1!B:B,$A10,Sheet1!C:C),0) -> 0
A11: Prem Prasad Tiwasena Salary | B11: =MAX(SUMIF(Sheet1!B:B,$A11,Sheet1!C:C)-SUMIF(Sheet1!B:B,$A11,Sheet1!D:D),0) -> 20000 | C11: =MAX(SUMIF(Sheet1!B:B,$A11,Sheet1!D:D)-SUMIF(Sheet1!B:B,$A11,Sheet1!C:C),0) -> 0
A12: SST | B12: =MAX(SUMIF(Sheet1!B:B,$A12,Sheet1!C:C)-SUMIF(Sheet1!B:B,$A12,Sheet1!D:D),0) -> 0 | C12: =MAX(SUMIF(Sheet1!B:B,$A12,Sheet1!D:D)-SUMIF(Sheet1!B:B,$A12,Sheet1!C:C),0) -> 5900
A13: Stationary | B13: =MAX(SUMIF(Sheet1!B:B,$A13,Sheet1!C:C)-SUMIF(Sheet1!B:B,$A13,Sheet1!D:D),0) -> 18530 | C13: =MAX(SUMIF(Sheet1!B:B,$A13,Sheet1!D:D)-SUMIF(Sheet1!B:B,$A13,Sheet1!C:C),0) -> 0
... A65: Samyog Bashyal | B65: =MAX(SUMIF(Sheet1!B:B,$A65,Sheet1!C:C)-SUMIF(Sheet1!B:B,$A65,Sheet1!D:D),0) -> 0 | C65: =MAX(SUMIF(Sheet1!B:B,$A65,Sheet1!D:D)-SUMIF(Sheet1!B:B,$A65,Sheet1!C:C),0) -> 22061
A66: Total | B66: =SUM(B2:B65) -> 61812110 | C66: =SUM(C2:C65) -> 61812110
